Workbook

Sheet Portafolio P&D
A2: N° | B2: Código de Planeamiento | C2: Nombre del Proyecto | D2: Alcance del Proyecto | E2: Gerencia Líder | F2: Líder del Proyecto | G2: Usuario Funcional | H2: Gestor de Planeamiento | I2: Presupuesto asignado | J2: Valor Ganado (EV) | K2: Costo Actual (AC) | L2: CPI | M2: Fecha Comité Ejec. Proy. | N2: N° Acta Comité (aprobación) | O2: Dimensión | P2: Objetivo | Q2: Año Inicio Planificado | R2: Año Fin Planificado | S2: N° Solicitudes de cambio | T2: Componente Tecnológico | U2: Transformación Digital | V2: Cartera | W2: Anexo 1 (Modelo de Negocio) | X2: Líder Técnico | Y2: Fecha Inicio | Z2: Fecha Fin | AA2: % Avance Planificado | AB2: % Avance ejecutado | AC2: Desv. % | AD2: Estado | AE2: SEGUIMIENTO (Planeamiento y Control de Gestión)
A3: 1 | B3: Iniciativa | C3: Proyecto 1 | E3: G1 | F3: Lider 1 | G3: Usuario 1 | H3: Gestor 1 | I3: =RANDBETWEEN(100,100000) -> 70305 | M3: =DATE(RANDBETWEEN(2020,2026),RANDBETWEEN(1,12),RANDBETWEEN(1,30)) -> 44724 | N3: 1 | O3: Dimension 1 | Q3: =YEAR(Tabla3[[#This Row],[Fecha Comité Ejec. Proy.]]) -> 2022 | R3: =Tabla3[[#This Row],[Año Inicio Planificado]] + 2 -> 2024 | S3: =RANDBETWEEN(1,4) -> 2 | V3: Cartera 1 | AA3: 0 | AB3: 0 | AC3: =Tabla3[[#This Row],[% Avance ejecutado]]-Tabla3[[#This Row],[% Avance Planificado]]/Tabla3[[#This Row],[% Avance Planificado]] -> #DIV/0! | AD3: 04. Cerrado
A4: 2 | B4: Iniciativa | C4: Proyecto 2 | E4: G1 | F4: Lider 2 | G4: Usuario 2 | H4: Gestor 2 | I4: =RANDBETWEEN(100,100000) -> 91002 | M4: =DATE(RANDBETWEEN(2020,2026),RANDBETWEEN(1,12),RANDBETWEEN(1,30)) -> 46074 | N4: 2 | O4: Dimension 1 | Q4: =YEAR(Tabla3[[#This Row],[Fecha Comité Ejec. Proy.]]) -> 2026 | R4: =Tabla3[[#This Row],[Año Inicio Planificado]] + 2 -> 2028 | S4: =RANDBETWEEN(1,4) -> 1 | V4: Cartera 1 | AA4: 0 | AB4: 0 | AC4: =Tabla3[[#This Row],[% Avance ejecutado]]-Tabla3[[#This Row],[% Avance Planificado]]/Tabla3[[#This Row],[% Avance Planificado]] -> #DIV/0! | AD4: 04. Cerrado
A5: 3 | B5: Iniciativa | C5: Proyecto 3 | E5: G1 | F5: Lider 3 | G5: Usuario 3 | H5: Gestor 3 | I5: =RANDBETWEEN(100,100000) -> 48611 | M5: =DATE(RANDBETWEEN(2020,2026),RANDBETWEEN(1,12),RANDBETWEEN(1,30)) -> 43840 | N5: 1 | O5: Dimension 1 | Q5: =YEAR(Tabla3[[#This Row],[Fecha Comité Ejec. Proy.]]) -> 2020 | R5: =Tabla3[[#This Row],[Año Inicio Planificado]] + 2 -> 2022 | S5: =RANDBETWEEN(1,4) -> 3 | V5: Cartera 1 | AA5: 0 | AB5: 0 | AC5: =Tabla3[[#This Row],[% Avance ejecutado]]-Tabla3[[#This Row],[% Avance Planificado]]/Tabla3[[#This Row],[% Avance Planificado]] -> #DIV/0! | AD5: 04. Cerrado
A6: 4 | B6: Iniciativa | C6: Proyecto 4 | E6: G1 | F6: Lider 4 | G6: Usuario 4 | H6: Gestor 4 | I6: =RANDBETWEEN(100,100000) -> 53926 | M6: =DATE(RANDBETWEEN(2020,2026),RANDBETWEEN(1,12),RANDBETWEEN(1,30)) -> 44409 | N6: 2 | O6: Dimension 1 | Q6: =YEAR(Tabla3[[#This Row],[Fecha Comité Ejec. Proy.]]) -> 2021 | R6: =Tabla3[[#This Row],[Año Inicio Planificado]] + 2 -> 2023 | S6: =RANDBETWEEN(1,4) -> 1 | V6: Cartera 1 | AA6: 0 | AB6: 0 | AC6: =Tabla3[[#This Row],[% Avance ejecutado]]-Tabla3[[#This Row],[% Avance Planificado]]/Tabla3[[#This Row],[% Avance Planificado]] -> #DIV/0! | AD6: 04. Cerrado
A7: 5 | C7: Proyecto 5 | E7: G1 | F7: Lider 5 | G7: Usuario 5 | H7: Gestor 5 | I7: =RANDBETWEEN(100,100000) -> 42718 | M7: =DATE(RANDBETWEEN(2020,2026),RANDBETWEEN(1,12),RANDBETWEEN(1,30)) -> 45887 | N7: 2 | O7: Dimension 1 | Q7: =YEAR(Tabla3[[#This Row],[Fecha Comité Ejec. Proy.]]) -> 2025 | R7: =Tabla3[[#This Row],[Año Inicio Planificado]] + 2 -> 2027 | S7: =RANDBETWEEN(1,4) -> 4 | V7: Cartera 1 | AA7: 0.88 | AB7: 0.85 | AC7: =Tabla3[[#This Row],[% Avance ejecutado]]-Tabla3[[#This Row],[% Avance Planificado]]/Tabla3[[#This Row],[% Avance Planificado]] -> -0.15 | AD7: 02. En Curso
A8: 6 | C8: Proyecto 6 | E8: G1 | F8: Lider 6 | G8: Usuario 6 | H8: Gestor 6 | I8: =RANDBETWEEN(100,100000) -> 47299 | M8: =DATE(RANDBETWEEN(2020,2026),RANDBETWEEN(1,12),RANDBETWEEN(1,30)) -> 45106 | N8: 2.2 | O8: Dimension 1 | Q8: =YEAR(Tabla3[[#This Row],[Fecha Comité Ejec. Proy.]]) -> 2023 | R8: =Tabla3[[#This Row],[Año Inicio Planificado]] + 2 -> 2025 | S8: =RANDBETWEEN(1,4) -> 3 | V8: Cartera 1 | AA8: 0.87 | AB8: 0.84 | AC8: =Tabla3[[#This Row],[% Avance ejecutado]]-Tabla3[[#This Row],[% Avance Planificado]]/Tabla3[[#This Row],[% Avance Planificado]] -> -0.16 | AD8: 02. En Curso
A9: 7 | C9: Proyecto 7 | E9: G1 | F9: Lider 7 | G9: Usuario 7 | H9: Gestor 7 | I9: =RANDBETWEEN(100,100000) -> 14855 | M9: =DATE(RANDBETWEEN(2020,2026),RANDBETWEEN(1,12),RANDBETWEEN(1,30)) -> 45372 | N9: 2.4 | O9: Dimension 1 | Q9: =YEAR(Tabla3[[#This Row],[Fecha Comité Ejec. Proy.]]) -> 2024 | R9: =Tabla3[[#This Row],[Año Inicio Planificado]] + 2 -> 2026 | S9: =RANDBETWEEN(1,4) -> 2 | V9: Cartera 1 | AA9: 0.76 | AB9: 0.71 | AC9: =Tabla3[[#This Row],[% Avance ejecutado]]-Tabla3[[#This Row],[% Avance Planificado]]/Tabla3[[#This Row],[% Avance Planificado]] -> -0.29 | AD9: 02. En Curso
A10: 8 | C10: Proyecto 8 | E10: G1 | F10: Lider 8 | G10: Usuario 8 | H10: Gestor 8 | I10: =RANDBETWEEN(100,100000) -> 86061 | M10: =DATE(RANDBETWEEN(2020,2026),RANDBETWEEN(1,12),RANDBETWEEN(1,30)) -> 45932 | N10: 2.6 | O10: Dimension 1 | Q10: =YEAR(Tabla3[[#This Row],[Fecha Comité Ejec. Proy.]]) -> 2025 | R10: =Tabla3[[#This Row],[Año Inicio Planificado]] + 2 -> 2027 | S10: =RANDBETWEEN(1,4) -> 4 | V10: Cartera 1 | AA10: 0.97 | AB10: 0.97 | AC10: =Tabla3[[#This Row],[% Avance ejecutado]]-Tabla3[[#This Row],[% Avance Planificado]]/Tabla3[[#This Row],[% Avance Planificado]] -> -0.03 | AD10: 02. En Curso
A11: 9 | C11: Proyecto 9 | E11: G1 | F11: Lider 9 | G11: Usuario 9 | H11: Gestor 9 | I11: =RANDBETWEEN(100,100000) -> 24869 | M11: =DATE(RANDBETWEEN(2020,2026),RANDBETWEEN(1,12),RANDBETWEEN(1,30)) -> 43848 | N11: 2.8 | O11: Dimension 1 | Q11: =YEAR(Tabla3[[#This Row],[Fecha Comité Ejec. Proy.]]) -> 2020 | R11: =Tabla3[[#This Row],[Año Inicio Planificado]] + 2 -> 2022 | S11: =RANDBETWEEN(1,4) -> 2 | V11: Cartera 1 | AC11: =Tabla3[[#This Row],[% Avance ejecutado]]-Tabla3[[#This Row],[% Avance Planificado]]/Tabla3[[#This Row],[% Avance Planificado]] -> #DIV/0! | AD11: 02. En Curso
A12: 10 | C12: Proyecto 10 | E12: G1 | F12: Lider 10 | G12: Usuario 10 | H12: Gestor 10 | I12: =RANDBETWEEN(100,100000) -> 3975 | M12: =DATE(RANDBETWEEN(2020,2026),RANDBETWEEN(1,12),RANDBETWEEN(1,30)) -> 44450 | N12: 3 | O12: Dimension 1 | Q12: =YEAR(Tabla3[[#This Row],[Fecha Comité Ejec. Proy.]]) -> 2021 | R12: =Tabla3[[#This Row],[Año Inicio Planificado]] + 2 -> 2023 | S12: =RANDBETWEEN(1,4) -> 2 | V12: Cartera 1 | AA12: 1 | AB12: 1 | AC12: =Tabla3[[#This Row],[% Avance ejecutado]]-Tabla3[[#This Row],[% Avance Planificado]]/Tabla3[[#This Row],[% Avance Planificado]] -> 0 | AD12: 03. Implementado
A13: 11 | C13: Proyecto 11 | E13: G1 | F13: Lider 11 | G13: Usuario 11 | H13: Gestor 11 | I13: =RANDBETWEEN(100,100000) -> 52281 | M13: =DATE(RANDBETWEEN(2020,2026),RANDBETWEEN(1,12),RANDBETWEEN(1,30)) -> 44282 | N13: 3.2 | O13: Dimension 1 | Q13: =YEAR(Tabla3[[#This Row],[Fecha Comité Ejec. Proy.]]) -> 2021 | R13: =Tabla3[[#This Row],[Año Inicio Planificado]] + 2 -> 2023 | S13: =RANDBETWEEN(1,4) -> 3 | V13: Cartera 1 | AA13: 1 | AB13: 1 | AC13: =Tabla3[[#This Row],[% Avance ejecutado]]-Tabla3[[#This Row],[% Avance Planificado]]/Tabla3[[#This Row],[% Avance Planificado]] -> 0 | AD13: 03. Implementado
A14: 12 | C14: Proyecto 12 | E14: G1 | F14: Lider 12 | G14: Usuario 12 | H14: Gestor 12 | I14: =RANDBETWEEN(100,100000) -> 27557 | M14: =DATE(RANDBETWEEN(2020,2026),RANDBETWEEN(1,12),RANDBETWEEN(1,30)) -> 45056 | N14: 3.4 | O14: Dimension 1 | Q14: =YEAR(Tabla3[[#This Row],[Fecha Comité Ejec. Proy.]]) -> 2023 | R14: =Tabla3[[#This Row],[Año Inicio Planificado]] + 2 -> 2025 | S14: =RANDBETWEEN(1,4) -> 4 | V14: Cartera 1 | AA14: 1 | AB14: 1 | AC14: =Tabla3[[#This Row],[% Avance ejecutado]]-Tabla3[[#This Row],[% Avance Planificado]]/Tabla3[[#This Row],[% Avance Planificado]] -> 0 | AD14: 03. Implementado
A15: 13 | C15: Proyecto 13 | E15: G1 | F15: Lider 13 | G15: Usuario 13 | H15: Gestor 13 | I15: =RANDBETWEEN(100,100000) -> 5578 | M15: =DATE(RANDBETWEEN(2020,2026),RANDBETWEEN(1,12),RANDBETWEEN(1,30)) -> 46380 | N15: 3.6 | O15: Dimension 1 | Q15: =YEAR(Tabla3[[#This Row],[Fecha Comité Ejec. Proy.]]) -> 2026 | R15: =Tabla3[[#This Row],[Año Inicio Planificado]] + 2 -> 2028 | S15: =RANDBETWEEN(1,4) -> 1 | V15: Cartera 1 | AA15: 0.44 | AB15: 0.4 | AC15: =Tabla3[[#This Row],[% Avance ejecutado]]-Tabla3[[#This Row],[% Avance Planificado]]/Tabla3[[#This Row],[% Avance Planificado]] -> -0.6 | AD15: 04. Cerrado
A16: 14 | C16: Proyecto 14 | E16: G1 | F16: Lider 14 | G16: Usuario 14 | H16: Gestor 14 | I16: =RANDBETWEEN(100,100000) -> 4467 | M16: =DATE(RANDBETWEEN(2020,2026),RANDBETWEEN(1,12),RANDBETWEEN(1,30)) -> 43866 | N16: 3.8 | O16: Dimension 1 | Q16: =YEAR(Tabla3[[#This Row],[Fecha Comité Ejec. Proy.]]) -> 2020 | R16: =Tabla3[[#This Row],[Año Inicio Planificado]] + 2 -> 2022 | S16: =RANDBETWEEN(1,4) -> 2 | V16: Cartera 1 | AA16: 1 | AB16: 1 | AC16: =Tabla3[[#This Row],[% Avance ejecutado]]-Tabla3[[#This Row],[% Avance Planificado]]/Tabla3[[#This Row],[% Avance Planificado]] -> 0 | AD16: 03. Implementado
A17: 15 | C17: Proyecto 15 | E17: G1 | F17: Lider 15 | G17: Usuario 15 | H17: Gestor 15 | I17: =RANDBETWEEN(100,100000) -> 40631 | M17: =DATE(RANDBETWEEN(2020,2026),RANDBETWEEN(1,12),RANDBETWEEN(1,30)) -> 44054 | N17: 4 | O17: Dimension 1 | Q17: =YEAR(Tabla3[[#This Row],[Fecha Comité Ejec. Proy.]]) -> 2020 | R17: =Tabla3[[#This Row],[Año Inicio Planificado]] + 2 -> 2022 | S17: =RANDBETWEEN(1,4) -> 3 | V17: Cartera 2 | AA17: 1 | AB17: 1 | AC17: =Tabla3[[#This Row],[% Avance ejecutado]]-Tabla3[[#This Row],[% Avance Planificado]]/Tabla3[[#This Row],[% Avance Planificado]] -> 0 | AD17: 03. Implementado
A18: 16 | C18: Proyecto 16 | E18: G1 | F18: Lider 16 | G18: Usuario 16 | H18: Gestor 16 | I18: =RANDBETWEEN(100,100000) -> 47889 | M18: =DATE(RANDBETWEEN(2020,2026),RANDBETWEEN(1,12),RANDBETWEEN(1,30)) -> 43933 | N18: 4.2 | O18: Dimension 1 | Q18: =YEAR(Tabla3[[#This Row],[Fecha Comité Ejec. Proy.]]) -> 2020 | R18: =Tabla3[[#This Row],[Año Inicio Planificado]] + 2 -> 2022 | S18: =RANDBETWEEN(1,4) -> 2 | V18: Cartera 2 | AA18: 0.56 | AB18: 0.47 | AC18: =Tabla3[[#This Row],[% Avance ejecutado]]-Tabla3[[#This Row],[% Avance Planificado]]/Tabla3[[#This Row],[% Avance Planificado]] -> -0.53 | AD18: 02. En Curso
A19: 17 | C19: Proyecto 17 | E19: G1 | F19: Lider 17 | G19: Usuario 17 | H19: Gestor 17 | I19: =RANDBETWEEN(100,100000) -> 43642 | M19: =DATE(RANDBETWEEN(2020,2026),RANDBETWEEN(1,12),RANDBETWEEN(1,30)) -> 44334 | N19: 4.4 | O19: Dimension 1 | Q19: =YEAR(Tabla3[[#This Row],[Fecha Comité Ejec. Proy.]]) -> 2021 | R19: =Tabla3[[#This Row],[Año Inicio Planificado]] + 2 -> 2023 | S19: =RANDBETWEEN(1,4) -> 3 | V19: Cartera 2 | AA19: 0.71 | AB19: 0.6 | AC19: =Tabla3[[#This Row],[% Avance ejecutado]]-Tabla3[[#This Row],[% Avance Planificado]]/Tabla3[[#This Row],[% Avance Planificado]] -> -0.4 | AD19: 04. Cerrado
A20: 18 | C20: Proyecto 18 | E20: G1 | F20: Lider 18 | G20: Usuario 18 | H20: Gestor 18 | I20: =RANDBETWEEN(100,100000) -> 75723 | M20: =DATE(RANDBETWEEN(2020,2026),RANDBETWEEN(1,12),RANDBETWEEN(1,30)) -> 44596 | N20: 4.6 | O20: Dimension 1 | Q20: =YEAR(Tabla3[[#This Row],[Fecha Comité Ejec. Proy.]]) -> 2022 | R20: =Tabla3[[#This Row],[Año Inicio Planificado]] + 2 -> 2024 | S20: =RANDBETWEEN(1,4) -> 4 | V20: Cartera 2 | AA20: 1 | AB20: 1 | AC20: =Tabla3[[#This Row],[% Avance ejecutado]]-Tabla3[[#This Row],[% Avance Planificado]]/Tabla3[[#This Row],[% Avance Planificado]] -> 0 | AD20: 03. Implementado
A21: 19 | C21: Proyecto 19 | E21: G1 | F21: Lider 19 | G21: Usuario 19 | H21: Gestor 19 | I21: =RANDBETWEEN(100,100000) -> 92119 | M21: =DATE(RANDBETWEEN(2020,2026),RANDBETWEEN(1,12),RANDBETWEEN(1,30)) -> 46279 | N21: 4.8 | O21: Dimension 1 | Q21: =YEAR(Tabla3[[#This Row],[Fecha Comité Ejec. Proy.]]) -> 2026 | R21: =Tabla3[[#This Row],[Año Inicio Planificado]] + 2 -> 2028 | S21: =RANDBETWEEN(1,4) -> 3 | V21: Cartera 2 | AA21: 0 | AB21: 0 | AC21: =Tabla3[[#This Row],[% Avance ejecutado]]-Tabla3[[#This Row],[% Avance Planificado]]/Tabla3[[#This Row],[% Avance Planificado]] -> #DIV/0! | AD21: 03. Implementado
A22: 20 | C22: Proyecto 20 | E22: G1 | F22: Lider 20 | G22: Usuario 20 | H22: Gestor 20 | I22: =RANDBETWEEN(100,100000) -> 4481 | M22: =DATE(RANDBETWEEN(2020,2026),RANDBETWEEN(1,12),RANDBETWEEN(1,30)) -> 45483 | N22: 5 | O22: Dimension 1 | Q22: =YEAR(Tabla3[[#This Row],[Fecha Comité Ejec. Proy.]]) -> 2024 | R22: =Tabla3[[#This Row],[Año Inicio Planificado]] + 2 -> 2026 | S22: =RANDBETWEEN(1,4) -> 3 | V22: Cartera 2 | AA22: 1 | AB22: 1 | AC22: =Tabla3[[#This Row],[% Avance ejecutado]]-Tabla3[[#This Row],[% Avance Planificado]]/Tabla3[[#This Row],[% Avance Planificado]] -> 0 | AD22: 03. Implementado
A23: 21 | C23: Proyecto 21 | E23: G1 | F23: Lider 21 | G23: Usuario 21 | H23: Gestor 21 | I23: =RANDBETWEEN(100,100000) -> 19054 | M23: =DATE(RANDBETWEEN(2020,2026),RANDBETWEEN(1,12),RANDBETWEEN(1,30)) -> 44080 | N23: 5.2 | O23: Dimension 1 | Q23: =YEAR(Tabla3[[#This Row],[Fecha Comité Ejec. Proy.]]) -> 2020 | R23: =Tabla3[[#This Row],[Año Inicio Planificado]] + 2 -> 2022 | S23: =RANDBETWEEN(1,4) -> 1 | V23: Cartera 2 | AA23: 1 | AB23: 1 | AC23: =Tabla3[[#This Row],[% Avance ejecutado]]-Tabla3[[#This Row],[% Avance Planificado]]/Tabla3[[#This Row],[% Avance Planificado]] -> 0 | AD23: 03. Implementado
... A42: 40 | C42: Proyecto 40 | E42: G2 | F42: Lider 40 | G42: Usuario 40 | H42: Gestor 40 | I42: =RANDBETWEEN(100,100000) -> 37568 | M42: =DATE(RANDBETWEEN(2020,2026),RANDBETWEEN(1,12),RANDBETWEEN(1,30)) -> 44800 | N42: 9 | O42: Dimension 2 | Q42: =YEAR(Tabla3[[#This Row],[Fecha Comité Ejec. Proy.]]) -> 2022 | R42: =Tabla3[[#This Row],[Año Inicio Planificado]] + 2 -> 2024 | S42: =RANDBETWEEN(1,4) -> 4 | V42: Cartera 2 | AA42: 0.6 | AB42: 0.26 | AC42: =Tabla3[[#This Row],[% Avance ejecutado]]-Tabla3[[#This Row],[% Avance Planificado]]/Tabla3[[#This Row],[% Avance Planificado]] -> -0.74 | AD42: 04. Cerrado
A43: 41 | B43: Iniciativa | C43: Proyecto 41 | E43: G2 | F43: Lider 41 | G43: Usuario 41 | H43: Gestor 41 | I43: =RANDBETWEEN(100,100000) -> 2574 | J43: =Tabla3[[#This Row],[Presupuesto asignado]]/2 -> 1287 | K43: =Tabla3[[#This Row],[Valor Ganado (EV)]] -> 1287 | L43: =Tabla3[[#This Row],[Valor Ganado (EV)]]/Tabla3[[#This Row],[Costo Actual (AC)]] -> 1 | M43: =DATE(RANDBETWEEN(2020,2026),RANDBETWEEN(1,12),RANDBETWEEN(1,30)) -> 46052 | N43: 9.2 | O43: Dimension 2 | Q43: =YEAR(Tabla3[[#This Row],[Fecha Comité Ejec. Proy.]]) -> 2026 | R43: =Tabla3[[#This Row],[Año Inicio Planificado]] + 2 -> 2028 | S43: =RANDBETWEEN(1,4) -> 2 | V43: Cartera 2 | AA43: 0 | AB43: 0 | AC43: =Tabla3[[#This Row],[% Avance ejecutado]]-Tabla3[[#This Row],[% Avance Planificado]]/Tabla3[[#This Row],[% Avance Planificado]] -> #DIV/0! | AD43: 01. No Iniciado

Sheet Demanda Estrategica CT
A1: TOTAL: | C1: =COUNT(DemandaEstrateg_[ID]) -> 111 | F1: =TODAY() -> 46150
A2: SEGUIMIENTO DE LA DEMANDA ESTRATÉGICA
AK3: OK | AL3: OK | AM3: OK | AN3: PENDIENTE | AO3: PENDIENTE
A4: ID | B4: ID Trámite | C4: ID Dependencia | D4: ID Proyecto / Mantenimiento asociado | E4: Tipo de Requerimiento | F4: Nombre del Proyecto | G4: Alcance del Proyecto | H4: Gerencia Líder | I4: Líder del Proyecto | J4: Usuario Funcional | K4: Gestor de Planeamiento | L4: Fecha de Solicitud a TI | M4: Memorando STD | N4: Canal de Atención | O4: Producto | P4: Servicio | Q4: Categoría | R4: Entidad reguladora / Organo de Control | S4: N° Norma / N° Informe | T4: N° recomendación | U4: Año Inicio Planificado | V4: Año Fin Planificado | W4: Fecha de Aprobación en Comité | X4: Presupuesto asignado | Y4: Cartera | Z4: Gestor TI | AA4: Aplicativo | AB4: Área Responsable TI | AC4: Entidad / Proveedor Asignado | AD4: Líder Técnico | AE4: Analista asignado | AF4: Motivo según estado | AG4: Fecha registro trámite | AH4: Fecha Inicio- Plan | AI4: Fecha Fin- Plan | AJ4: Fecha Fin Ral (CQ) | AK4: % Avance Planificado | AL4: % Avance ejecutado | AM4: Desv. % | AN4: Días faltantes | AO4: ALERTA | AP4: Fecha Fin TI Propuesta | AQ4: Fecha Fin TI (Trimestre) | AR4: Últ. Estado CQ 30.04 | AS4: Estado TI | AT4: Estado Proyecto TI | AU4: Seguimiento OPP | AV4: Código de Planeamiento
A5: 1 | E5: Proyecto | F5: Proyecto 1 | H5: G1 | AH5: ='Portafolio P&D'!Y11 -> 0 | AI5: 46142 | AK5: ='Portafolio P&D'!AA11 -> 0 | AL5: ='Portafolio P&D'!AB11 -> 0 | AM5: =IF(DemandaEstrateg_[[#This Row],[Tipo de Requerimiento]]="Proyecto",(DemandaEstrateg_[[#This Row],[% Avance ejecutado]]-DemandaEstrateg_[[#This Row],[% Avance Planificado]])/DemandaEstrateg_[[#This Row],[% Avance Planificado]],"No aplica") -> #DIV/0! | AN5: =IF(DemandaEstrateg_[[#This Row],[Tipo de Requerimiento]]="Proyecto",(DemandaEstrateg_[[#This Row],[% Avance ejecutado]]-DemandaEstrateg_[[#This Row],[% Avance Planificado]])/DemandaEstrateg_[[#This Row],[% Avance Planificado]],"No aplica") -> #DIV/0! | AP5: 46113 | AQ5: 2026-I | AR5: No Aplica | AS5: 03. En Desarrollo | AT5: =VLOOKUP(DemandaEstrateg_[[#This Row],[Estado TI]],#REF!,3,FALSE) -> #REF! | AU5: 14/01/2026: El estado es el sgte: Entregable 7 (fase 1): Certificado en 12/2024. Entregable 7 (fase 2): A espera que el proveedor confirme inicio de pruebas en Calidad. Oplaft remitirá solicitud de enmascaramiento de data de prueba traida de Producción. Entregable 9: A espera que el Proveedor brinde disponibilidad para realizar las pruebas técnicas de integración en el mes de enero, para luego continuar con las pruebas de usuario. Entregable 10: Paso a producción el 28/11, se hicieron ajustes de configuración hasta el 10/12 informando su puesta en producción. Entregable 12: Certificado en 12/2024. Existen vulnerabilidades pendientes, respecto al cual el proveedor a remitido su compromiso (correo) para ser subsanado en May26. En coordinación con el proveedor, se están llevando a cabo reuniones para actualizar el cronograma del Proyecto. 15/12/2025: El estado es el sgte: Entregable 7 (fase 1): Certificado en 12/2024. Entregable 7 (fase 2): A espera que el proveedor confirme inicio de pruebas en Calidad. Entregable 9: Se están realizando nuevas pruebas técnicas de integración, para continuar con las pruebas de usuario. Entregable 10: Paso a producción el 28/11, se hicieron ajustes de configuración hasta el 10/12 informando su puesta en producción. Entregable 12: Certificado en 12/2024. Existen vulnerabilidades pendientes, respecto al cual el proveedor a remitido su compromiso (correo) para ser subsanado en May26. Existe un plan a alto nivel propuesto por el Proveedor, sobre el cual se están ejecutando las actividades. 05/09/2025: El estado es el sgte: Entregable 7 (fase 1): Certificado el 12/2024. Entregable 7 (fase 2): En adecuaciones de las transacciones faltantes, compromiso 15-Oct-25. Entregable 9: Pruebas técnicas culminaron, se está actualizando el mapeo técnico/funcional, el Proveedor está actualizando la versión de Sentinel en desarrollo (15 días). Entregable 10: Certificado el 06/2025 Entregable 12: Certificado 12/2024. BN ejecutó en Jul-25 un nuevo de análisis de vulnerabilidad en certificación, donde se evidencia que las vulnerabilidades permanecen. Pendiente reunión para revisar los resultados de las pruebas de rendimiento que efectuó el proveedor. En reunión con los usuarios de Riesgos, Oplaft y Fraudes se estableció hitos de pase a producción: Entregable 10 y 12 (Dic2025), Entregable 7 y Entregable 9 (Mar2026). Está pendiente que el usuario gestione la ampliación de plazo e informar a Planeamiento. 25/07/2025: Entregable 7 (fase 1): Certificado el 12/2024; Entregable 7 (fase 2): Se culmino con la generación y entrega de data de 6 meses. A la espera que el proveedor complete el despliegue en calidad y confirme el inicio de las pruebas; Entregable 9: Se están realizando nuevas pruebas técnicas en los canales, de acuerdo a lo solicitado por el proveedor.; Entregable 10: Certificado el 06/2025; Entregable 12: Certificado 12/2024. BN ejecutó un nuevo de analisis de vulnerabilidad en el ambiente de certificación la semana del 14 al 18/07 donde se evidencia que las vulnerabilidades permanecen, se remitirá informe al Proveedor reiterando se subsanen las vulnerabilidades, como tambien se subsane las observaciones de las pruebas de rendimiento; antes de un pase a Producción. 11/06/2025:Según la información enviada de 17/07/2025: Entregable 7 (fase 1): Certificado el 12/2024; Entregable 7 (fase 2): Se culmino con la generación y entrega de data de 6 meses. A la espera que el proveedor complete el despliegue en calidad y confirme el inicio de las pruebas; Entregable 9: Se están realizando nuevas pruebas técnicas en los canales del alcance, de acuerdo a lo solicitado por el proveedor.; Entregable 10: Certificado 06/2025; Entregable 12: Certificado 12/2024; Pendiente que el proveedor resuelva las observaciones de vulnerabilidades y pruebas de rendimiento, antes de un pase a Producción. 11/06/2025:Según la información enviada de Planeamiento en el mes de Mayo se precisa lo siguiente: Entregable 7 Fase 2 Ambiente de Desarrollo continúan las pruebas de perfiles ,funcionales y la validación de Calidad de datos de los archivos de 5 días, en paralelo se están generando desde 2/5 los archivos de 6 meses con los programas extractores v2 . Entregable 9 se culmino la integración de datos desde los canales en el ambiente Desarrollo. Entregable 10 se culmino las pruebas en el ambiente de Certificación esta en proceso la firma de los IRPF y RC . 03/06/2025: Según la información enviada de Planeamiento mediante correo respecto al proyecto en el mes de abril se tiene que: Se encuentra en actualización el Cronograma entre el BN y SS el cual generara la versión 3. Se desplego la versión 7.12.1 de Sentinel Core y Predictions en el ambiente de desarrollo. 07/05/2025: Según la información remitida por Planeamiento mediante correo: Se esta desplegando la nueva versión de Sentinel Core y Predictions que resuelve issues identificadas durante las pruebas hasta dic 2024. Entregable 7 La revisión de Calidad de datos no se esta cumpliendo en fecha debido a la que la información aun sigue siendo corregida por parte de TI-BN , existe una alta dependencia de un solo especialista para el análisis y construcción de los programas extractores . Entregable 9 Hay retraso en el inicio de las pruebas funcionales en el ambiente de desarrollo debido a las actividades previas por parte de TI-BN y Smartsoft. Entregable 10 Aún están pendientes de firma las RC , ya que dependen de los IRPF, tanto de Producto como Funcional, los cuales no han sido remitidos con las firmas correspondientes por parte de Smartsoft. Una vez que Smartsoft entregue los IRPF debidamente visados, los usuarios y el equipo de TI - BN procederán con el visado final para su cierre. 31/12/2024: A nivel entregables se encuentran en ejecución 4 entregables. OPLAFT El entregable 7 se encuentra a un 86 %. Se culmino la certificación de la Fase 1 (Productos y Perfiles). Fraudes El entregable 9 se encuentra a un 70 %. Se definió el tema de las pruebas RT y NRT . El entregable 10 se encuentra a un 65 %. El entregable 12 se encuentra a un 92 % Se culmino la certificación. 23/05/2024 Mediante Comité Estratégico de proyectos de fecha 06.05.24 se informa la aprobación de control de cambios del proyecto 08/04/24 Se ha cambiado la fecha de inicio de proyecto de 2023 a 2021 20/03/24 TI compartirá con Planeamiento el nuevo plan actualizado para que se gestione el control de cambios con el Líder del Proyecto. 03/06/2025: Según la información enviada de Planeamiento mediante correo respecto al proyecto en el mes de abril se tiene que: Se encuentra en actualización el Cronograma entre el BN y SS el cual generara la versión 3. Se desplego la versión 7.12.1 de Sentinel Core y Predictions en el ambiente de desarrollo. 08/05/25: A espera de actas visadas por el área usuaria del Entregable 10 para su certificación. Se ejecuto las pruebas de rendimiento, pero con observaciones remitidos al Proveedor y BNDesa. Respecto al Entregable 7, se encuentra en proceso de despliegue de la nueva version Sentinel Core y Reporter en el ambiente de Calidad para iniciar las pruebas del Entregable 7 (fase2). 04/04/25: Del Entregable 10 se concluyeron con las pruebas funcionales. A la espera de actas visadas por el área usuaria y el proveedor para su certificación. Se está culminando las pruebas de rendimiento y está en proceso de elaboración del informe. Respecto al Entregable 9 se inició con las pruebas del producto y perfiles el 25/03 en Desarrollo. Se espera iniciar las pruebas funcionales la 2da semana de abril luego de que el proveedor culmine con la configuración de reglas de los canales. Respecto al Entregable 7 (fase 2), queda pendiente culminar solo las pruebas de calidad de datos en coordinación diaria con construcción, usuario y proveedor. 21/03/25: Mediante correo del 21/03/25 de Planeamiento se indica: Entregable 7: 86% Entregable 9: 72% Entregable 10: 81% Entregable 12: 93% 03/03/25: Se concluyeron con las pruebas funcionales del entregable 10 (en firma de actas) y se iniciarán con las pruebas de rendimiento. Respecto al entregable 9, se estima iniciar el 05/03 las pruebas funcionales en Desarrollo (previa confirmación del proveedor). Respecto al entregable 7 (fase 2), continuan las pruebas de calidad de datos en coordinación diaria con construcción, usuario y proveedor, ademas se culminaron con lsa pruebas del producto (en firma de actas por parte del proveedor y usuarios), perfiles (en elaboración de actas, pruebas funcionales (avanzando en coordinaciones entre el usuario y proveedor). 31/01/25: Se inició las pruebas del entregable 10 en Calidad. Se continuan con las pruebas del entregable 7 (fase 2) con demora por parte del proveedor en resolver las observaciones; tambien se están realizando pruebas de integración del entregable 9. 31/12/24: A nivel entregables se encuentran en ejecución 4 entregables. OPLAFT El entregable 7 se encuentra a un 86 %. Se culmino la certificación de la Fase 1 (Productos y Perfiles). Fraudes El entregable 9 se encuentra a un 70 %. Se definió el tema de las pruebas RT y NRT . El entregable 10 se encuentra a un 65 %. El entregable 12 se encuentra a un 92 % Se culmino la certificación. 24/10/24 El proyecto se encuentra en proceso de implementación, en base a una estrategia definida para sacar el proyecto en el presente año 2024 con el proyecto 7 y 12. 26/09/2023: En coordinación con Construcción se creó el ID de Proyecto, para almanenar toda la informacion referente al proyecto de forma integral en todas sus etapas de integración. | AV5: ='Portafolio P&D'!B11 -> 0
A6: 2 | E6: Proyecto-Hijo | F6: Proyecto 2 | H6: G1 | AH6: 44963 | AI6: 45838 | AK6: No aplica | AL6: No aplica | AM6: =IF(DemandaEstrateg_[[#This Row],[Tipo de Requerimiento]]="Proyecto",(DemandaEstrateg_[[#This Row],[% Avance ejecutado]]-DemandaEstrateg_[[#This Row],[% Avance Planificado]])/DemandaEstrateg_[[#This Row],[% Avance Planificado]],"No aplica") -> No aplica | AN6: =IF(DemandaEstrateg_[[#This Row],[Tipo de Requerimiento]]="Proyecto",(DemandaEstrateg_[[#This Row],[% Avance ejecutado]]-DemandaEstrateg_[[#This Row],[% Avance Planificado]])/DemandaEstrateg_[[#This Row],[% Avance Planificado]],"No aplica") -> No aplica | AP6: 46082 | AQ6: 2026-I | AR6: Certificado | AS6: =VLOOKUP(DemandaEstrateg_[[#This Row],[Últ. Estado CQ 30.04]],#REF!,3,FALSE) -> #REF! | AT6: =VLOOKUP(DemandaEstrateg_[[#This Row],[Estado TI]],#REF!,3,FALSE) -> #REF! | AU6: 5/12/2024: Según CQ, se actualizó el estado de 03. En Desarrollo a 05. En Calidad 13/12/2023: COMITÉ DEMANDA REGULARIZACIÓN: Se regulariza su registro según lo aprobado en comité 29/09/2023: Se observa retraso en las actividades por obervaciones encontradas en lo extractores, se estima se concluya el 06/10. Los roles y perfiles ya fueron unificados por los usuarios, se espera pruebas para validar que los roles funcionales y de seguridad funcionen correctamente. Pendiente que el proveedor concluya con sus actividades de desarrollo del componente de seguridad como de los procesos de consolidación y configuracion de reglas de PLAYFT. 26/09/2023: De acuerdo al compromiso de Construcción con GG, las obs de los extractores culminarán el 29/09. 19/09/2023: En coordinación con JRuiz y MArquiñigo los archivos extractores será remitidos hoy al proveedor con la validación a nivel de estructura. Respecto a las obs a nivel de data se seguirá revisando y corrigiendo hasta antes del pase a Calidad. 31/07/2023: Se actualizaron las fechas según lo conversado con Jorge Ruiz 19/06/2023: Se actualizó la fecha de fin de producción de acuerdo al cronograma de Sentinel. 17/05/2023: Se actualiza su prioridad (adquirida) 27/01/2023: Se avanzó el analisis y mapeo técnico de OPLAFT, se remitió al usuario para que valide y se envié luego a Fabrica para su desarrollo. Respecto a Fraudes, está pendiente que el usuario confirme la entrega del mapeo segun lo que indica las bases para continuar con el analisis y mapeo técnico. ---------------------------------------------------------------------------------- 07/06: Líder técnico no está claramente definido. Indicado por MCarbajo 30/05: Gestor anterior. Omar Sarmiento 10/05: Luis García, solicita culminación de mapeo de datos de movimientos y transacciones de Mario Carbajo (3 semanas sin rpta del mail). Se indicó que como hay sobrecarga laboral de Mario, de acuerdo a la reunión de hoy al medio día se validará dicha carga laboral con Carmen Iriarte. Mario depende de disponibilidad de tiempo de Carmen para tener dicha reunión. 24/03: Mario Carbajo indico que el 28/03 se incorporaria 1 recurso de OLSSA para mapeo y construcción de extractores. 15/03: Arquitectura compartio el TDR para el Middleware para revisión de las sub-gerencias del TI. 11/02: Ante la licencia solicitada por el líder de integración (Mario Carbajo) hasta el 08/03, queda como líder de integración Jorge Pazos. 10/02: Se identificaron y priorizaron las principales transacciones por Canal para la Entidad Movimiento y Transacciones. 03/02: Se entregó el Mapeo de datos para la Entidad Clientes. 02/02: Se continua con el mapo de entidades de cliente, y esto está demorando por encontrarse en diferentes BD (incluye Excel). 05/01: Se modifica las fechas al año y medio faltante que indicó el usuario se espera para concluir el proyecto. 04/01: La subdivisión de una sola actividad de mapeo de datos la cual se particiona en 5 mapeos. Productos (100%), Catálogos (100%), Data histórica (100%), Clientes (50%- Le falta una parte) y Movimiento y transacciones (0%- Banca celular, ventanilla, ATM y Told). 28/12: Solo una persona asignado (LI). Se ha avanzado el mapeo y extractores de catálogos y productos. El de clientes es más complejo. Transacciones y movimientos ya hubo reunión la semana pasada.La prox semana habrá reunión con Sentinel. 22/12: De 5 partes del proyecto se ha mepado Productos, catálogos y una parte de clientes. Lo que es movimientos y transacciones aún no está contemplado como parte del mapeo. | AV6: No Aplica
A7: 3 | E7: Proyecto-Hijo | F7: Proyecto 3 | H7: G1 | AH7: 45161 | AI7: 45723 | AK7: No aplica | AL7: No aplica | AM7: =IF(DemandaEstrateg_[[#This Row],[Tipo de Requerimiento]]="Proyecto",(DemandaEstrateg_[[#This Row],[% Avance ejecutado]]-DemandaEstrateg_[[#This Row],[% Avance Planificado]])/DemandaEstrateg_[[#This Row],[% Avance Planificado]],"No aplica") -> No aplica | AN7: =IF(DemandaEstrateg_[[#This Row],[Tipo de Requerimiento]]="Proyecto",(DemandaEstrateg_[[#This Row],[% Avance ejecutado]]-DemandaEstrateg_[[#This Row],[% Avance Planificado]])/DemandaEstrateg_[[#This Row],[% Avance Planificado]],"No aplica") -> No aplica | AP7: 46023 | AQ7: 2026-I | AR7: Asignado | AS7: =VLOOKUP(DemandaEstrateg_[[#This Row],[Últ. Estado CQ 30.04]],#REF!,3,FALSE) -> #REF! | AT7: =VLOOKUP(DemandaEstrateg_[[#This Row],[Estado TI]],#REF!,3,FALSE) -> #REF! | AU7: 24/10/24 Segun lo coordinar con Omar Cribillero, Prestamos por IVR se encuentra en Producción y Prestamos por Agentes fué desestimado en el ulitmo comité de Proyectos. 27/06/2024 Se regulariza su registro en la demanda Estratégica. 10/06/2024: Se registró en el Backlog de requerimientos | AV7: No Aplica
A8: 4 | E8: Proyecto-Hijo | F8: Proyecto 4 | H8: G1 | AH8: 45183 | AI8: 45723 | AK8: No aplica | AL8: No aplica | AM8: =IF(DemandaEstrateg_[[#This Row],[Tipo de Requerimiento]]="Proyecto",(DemandaEstrateg_[[#This Row],[% Avance ejecutado]]-DemandaEstrateg_[[#This Row],[% Avance Planificado]])/DemandaEstrateg_[[#This Row],[% Avance Planificado]],"No aplica") -> No aplica | AN8: =IF(DemandaEstrateg_[[#This Row],[Tipo de Requerimiento]]="Proyecto",(DemandaEstrateg_[[#This Row],[% Avance ejecutado]]-DemandaEstrateg_[[#This Row],[% Avance Planificado]])/DemandaEstrateg_[[#This Row],[% Avance Planificado]],"No aplica") -> No aplica | AP8: 46023 | AQ8: 2026-I | AR8: Asignado | AS8: =VLOOKUP(DemandaEstrateg_[[#This Row],[Últ. Estado CQ 30.04]],#REF!,3,FALSE) -> #REF! | AT8: =VLOOKUP(DemandaEstrateg_[[#This Row],[Estado TI]],#REF!,3,FALSE) -> #REF! | AU8: 31/12/24: Ciclos de pruebas en marcha (379 Ok / 617 Total). Se esta coordinando y resolviendo día a día con proveedor y TI. A la par ya culminaron con remitir solicitud de cambio y cronograma de actividades para que sea aprobado por el comité. 13/12/2024 El Proyecto se está certificando, se remitió nuevo cronograma con las nuevas fechas de implementación. 19/11/2024 Se aprobó un nuevo cronograma con fecha de incio del Piloto para Enero 2025. El proyecto se encuentra a un 74% de avance segun cronograma actualizado al 07 de Noviembre. 12/08/2024 Avance del Proyecto segun cronograma. 27/06/2024 Seregulariza su ingreso a la demanda estratégica. | AV8: No Aplica
A9: 5 | E9: Proyecto-Hijo | F9: Proyecto 5 | H9: G1 | AH9: 44726 | AI9: 45930 | AK9: No aplica | AL9: No aplica | AM9: =IF(DemandaEstrateg_[[#This Row],[Tipo de Requerimiento]]="Proyecto",(DemandaEstrateg_[[#This Row],[% Avance ejecutado]]-DemandaEstrateg_[[#This Row],[% Avance Planificado]])/DemandaEstrateg_[[#This Row],[% Avance Planificado]],"No aplica") -> No aplica | AN9: =IF(DemandaEstrateg_[[#This Row],[Tipo de Requerimiento]]="Proyecto",(DemandaEstrateg_[[#This Row],[% Avance ejecutado]]-DemandaEstrateg_[[#This Row],[% Avance Planificado]])/DemandaEstrateg_[[#This Row],[% Avance Planificado]],"No aplica") -> No aplica | AP9: 46082 | AQ9: 2026-I | AR9: Aprobado | AS9: =VLOOKUP(DemandaEstrateg_[[#This Row],[Últ. Estado CQ 30.04]],#REF!,3,FALSE) -> #REF! | AT9: =VLOOKUP(DemandaEstrateg_[[#This Row],[Estado TI]],#REF!,3,FALSE) -> #REF! | AU9: 13/12/2023: COMITÉ DEMANDA REGULARIZACIÓN: Se regulariza su registro según lo aprobado en comité | AV9: No Aplica
A10: 6 | E10: Proyecto-Hijo | F10: Proyecto 6 | H10: G1 | AH10: 45054 | AI10: 45869 | AK10: No aplica | AL10: No aplica | AM10: =IF(DemandaEstrateg_[[#This Row],[Tipo de Requerimiento]]="Proyecto",(DemandaEstrateg_[[#This Row],[% Avance ejecutado]]-DemandaEstrateg_[[#This Row],[% Avance Planificado]])/DemandaEstrateg_[[#This Row],[% Avance Planificado]],"No aplica") -> No aplica | AN10: =IF(DemandaEstrateg_[[#This Row],[Tipo de Requerimiento]]="Proyecto",(DemandaEstrateg_[[#This Row],[% Avance ejecutado]]-DemandaEstrateg_[[#This Row],[% Avance Planificado]])/DemandaEstrateg_[[#This Row],[% Avance Planificado]],"No aplica") -> No aplica | AP10: 46082 | AQ10: 2026-I | AR10: Aprobado | AS10: =VLOOKUP(DemandaEstrateg_[[#This Row],[Últ. Estado CQ 30.04]],#REF!,3,FALSE) -> #REF! | AT10: =VLOOKUP(DemandaEstrateg_[[#This Row],[Estado TI]],#REF!,3,FALSE) -> #REF! | AU10: 13/12/2023: COMITÉ DEMANDA REGULARIZACIÓN: Se regulariza su registro según lo aprobado en comité | AV10: No Aplica
A11: 7 | E11: Proyecto-Hijo | F11: Proyecto 7 | H11: G1 | AH11: 45236 | AI11: 45869 | AK11: No aplica | AL11: No aplica | AM11: =IF(DemandaEstrateg_[[#This Row],[Tipo de Requerimiento]]="Proyecto",(DemandaEstrateg_[[#This Row],[% Avance ejecutado]]-DemandaEstrateg_[[#This Row],[% Avance Planificado]])/DemandaEstrateg_[[#This Row],[% Avance Planificado]],"No aplica") -> No aplica | AN11: =IF(DemandaEstrateg_[[#This Row],[Tipo de Requerimiento]]="Proyecto",(DemandaEstrateg_[[#This Row],[% Avance ejecutado]]-DemandaEstrateg_[[#This Row],[% Avance Planificado]])/DemandaEstrateg_[[#This Row],[% Avance Planificado]],"No aplica") -> No aplica | AP11: 46082 | AQ11: 2026-I | AR11: Aprobado | AS11: =VLOOKUP(DemandaEstrateg_[[#This Row],[Últ. Estado CQ 30.04]],#REF!,3,FALSE) -> #REF! | AT11: =VLOOKUP(DemandaEstrateg_[[#This Row],[Estado TI]],#REF!,3,FALSE) -> #REF! | AU11: 13/12/2023: COMITÉ DEMANDA REGULARIZACIÓN: Se regulariza su registro según lo aprobado en comité | AV11: No Aplica
A12: 8 | E12: Proyecto-Hijo | F12: Proyecto 8 | H12: G1 | AH12: 44739 | AI12: 45838 | AJ12: 46050 | AK12: No aplica | AL12: No aplica | AM12: =IF(DemandaEstrateg_[[#This Row],[Tipo de Requerimiento]]="Proyecto",(DemandaEstrateg_[[#This Row],[% Avance ejecutado]]-DemandaEstrateg_[[#This Row],[% Avance Planificado]])/DemandaEstrateg_[[#This Row],[% Avance Planificado]],"No aplica") -> No aplica | AN12: =IF(DemandaEstrateg_[[#This Row],[Tipo de Requerimiento]]="Proyecto",(DemandaEstrateg_[[#This Row],[% Avance ejecutado]]-DemandaEstrateg_[[#This Row],[% Avance Planificado]])/DemandaEstrateg_[[#This Row],[% Avance Planificado]],"No aplica") -> No aplica | AP12: 45992 | AQ12: 2025-IV | AR12: Procesado | AS12: =VLOOKUP(DemandaEstrateg_[[#This Row],[Últ. Estado CQ 30.04]],#REF!,3,FALSE) -> #REF! | AT12: =VLOOKUP(DemandaEstrateg_[[#This Row],[Estado TI]],#REF!,3,FALSE) -> #REF! | AU12: 13/12/2023: COMITÉ DEMANDA REGULARIZACIÓN: Se regulariza su registro según lo aprobado en comité | AV12: No Aplica
A13: 9 | E13: Proyecto-Hijo | F13: Proyecto 9 | H13: G1 | AH13: 45045 | AI13: 45723 | AJ13: 46052 | AK13: No aplica | AL13: No aplica | AM13: =IF(DemandaEstrateg_[[#This Row],[Tipo de Requerimiento]]="Proyecto",(DemandaEstrateg_[[#This Row],[% Avance ejecutado]]-DemandaEstrateg_[[#This Row],[% Avance Planificado]])/DemandaEstrateg_[[#This Row],[% Avance Planificado]],"No aplica") -> No aplica | AN13: =IF(DemandaEstrateg_[[#This Row],[Tipo de Requerimiento]]="Proyecto",(DemandaEstrateg_[[#This Row],[% Avance ejecutado]]-DemandaEstrateg_[[#This Row],[% Avance Planificado]])/DemandaEstrateg_[[#This Row],[% Avance Planificado]],"No aplica") -> No aplica | AP13: 45992 | AQ13: 2025-IV | AR13: Procesado | AS13: =VLOOKUP(DemandaEstrateg_[[#This Row],[Últ. Estado CQ 30.04]],#REF!,3,FALSE) -> #REF! | AT13: =VLOOKUP(DemandaEstrateg_[[#This Row],[Estado TI]],#REF!,3,FALSE) -> #REF! | AU13: 17/10/2024: Según CQ, se actualizó el estado de 04. Desarrollo Finalizado a 05. En Calidad 13/12/2023: COMITÉ DEMANDA REGULARIZACIÓN: Se regulariza su registro según lo aprobado en comité | AV13: No Aplica
A14: 10 | E14: Proyecto-Hijo | F14: Proyecto 10 | H14: G1 | AH14: 45652 | AI14: 46139 | AK14: 0.71 | AL14: 0.51 | AM14: =IF(DemandaEstrateg_[[#This Row],[Tipo de Requerimiento]]="Proyecto",(DemandaEstrateg_[[#This Row],[% Avance ejecutado]]-DemandaEstrateg_[[#This Row],[% Avance Planificado]])/DemandaEstrateg_[[#This Row],[% Avance Planificado]],"No aplica") -> No aplica | AN14: =IF(DemandaEstrateg_[[#This Row],[Tipo de Requerimiento]]="Proyecto",(DemandaEstrateg_[[#This Row],[% Avance ejecutado]]-DemandaEstrateg_[[#This Row],[% Avance Planificado]])/DemandaEstrateg_[[#This Row],[% Avance Planificado]],"No aplica") -> No aplica | AP14: 46082 | AQ14: 2026-I | AR14: Certificado | AS14: =VLOOKUP(DemandaEstrateg_[[#This Row],[Últ. Estado CQ 30.04]],#REF!,3,FALSE) -> #REF! | AT14: =VLOOKUP(DemandaEstrateg_[[#This Row],[Estado TI]],#REF!,3,FALSE) -> #REF! | AU14: 29/08/2024: Según CQ, se actualizó el estado de 03. En Desarrollo a 05. En Calidad 13/12/2023: COMITÉ DEMANDA REGULARIZACIÓN: Se regulariza su registro según lo aprobado en comité | AV14: No Aplica
A15: 11 | E15: Proyecto | F15: Proyecto 11 | H15: G1 | AH15: ='Portafolio P&D'!Y9 -> 0 | AI15: ='Portafolio P&D'!Z9 -> 0 | AK15: 0.87 | AL15: 0.83 | AM15: =IF(DemandaEstrateg_[[#This Row],[Tipo de Requerimiento]]="Proyecto",(DemandaEstrateg_[[#This Row],[% Avance ejecutado]]-DemandaEstrateg_[[#This Row],[% Avance Planificado]])/DemandaEstrateg_[[#This Row],[% Avance Planificado]],"No aplica") -> -0.045977011 | AN15: =IF(DemandaEstrateg_[[#This Row],[Tipo de Requerimiento]]="Proyecto",(DemandaEstrateg_[[#This Row],[% Avance ejecutado]]-DemandaEstrateg_[[#This Row],[% Avance Planificado]])/DemandaEstrateg_[[#This Row],[% Avance Planificado]],"No aplica") -> -0.045977011 | AP15: 45931 | AQ15: 2026-I | AR15: Pendiente | AS15: 03. En Desarrollo | AT15: =VLOOKUP(DemandaEstrateg_[[#This Row],[Estado TI]],#REF!,3,FALSE) -> #REF! | AU15: 12/01/2026: Mediante correo del 07/12/2026, Luis Palacios Q. comunicó que las siguientes actividades del Realease 3 se encuentran pendientes de culminar para pasar a Producción: - Revisión y firma de Actas de Conformidad de pruebas funcionales, (Usuario Secc. Canales Virtuales) - Revisión del WorkBook de QR, nueva versión (4.0) - Cámara de Compensación E., (Marco Obando / Luis Palacios ) - Revisión de reportes contables (TEMENOS) - Pruebas de seguridad, (TEMENOS / Oficina de Seguridad Informática) 04/12/2025: Mediante correo del 01/12/2025, Karin Robles indicó el estado de los siguientes requerimientos del Realise 3: Pendiente de coordinación para pasar a Producción - Responsable BACKBASE 2024-M0299 Validación de identidad externa para enrolamiento en Cuenta DNI con registro de titular en línea: 05. En Calidad, Pruebas de Usuario FUNCIONAL: En revisión de las actas de conformidad por los Usuarios. Pruebas de RENDIMIENTO: Se cuenta con la APROBACIÓN del PO sobre los informes de Rendimiento Pruebas de SEGURIDAD: Se envió el informe y reporte de las pruebas al Proveedor de BACKBASE para su revisión y validación en conjunto con el área de Seguridad. 2025-M0071 Transferencias interbancarias inmediatas en la Aplicación móvil de Cuenta DNI 05. En Calidad 2025-M0072 Transferencias Interbancarias inmediatas a Celular (búsqueda de contactos) y con código QR en la Aplicación móvil de Cuenta DNI 05. En Calidad 2025-M0372 Integración del Orquestador de Novatronic con el Core de Cuenta DNI par transferencias inmediatas a otros Bancos. 05. En Calidad 2025-M0280 Integración de Orquestador para Transferencia Inmediata desde Cta. DNI – Servidor para tarifario dinámico (3 ambientes). 05. En Calidad 27/11/2025: Mediante correo del 27/11/2025, Luis Palacios indicóque presentaron una solicitud de cambio donde se estara llevando un mejor control del avance del proyecto, hasta el momento se han mantenido las fechas con los avances porcentuales correspondientes. 05/09/2025: Mediante correo del 04/09/2025, Luis Palacios indicó el estado de las siguientes actividades: - Transferencias inmediatas de entrada: Entrega pendiente de API por NOVATRONIC. - Transferencias Internas CTA-DNI a CTA-BN: pendiente el inicio de pruebas. BACKBASE propone realizar pruebas con postman al API de Novatronic. - Depósito / Retiro en Agentes Corresponsales – Entrega pendiente de API por NOVATRONIC. - Depósito / Retiro en Ventanilla – Inicio de pruebas integrales con SARAWEB (29.09.25). Está pendiente que el usuario gestione la ampliación de plazo e informar a Planeamiento. 25/07/2025:• MP2 (R3) Se han culminado las pruebas funcionales (2do ciclo) en Calidad. Está pendiente la atención de las observaciones por parte del proveedor para dar inicio al 3er ciclo de pruebas. Está pendiente ejecutar las pruebas de rendimiento. Se estima su pase a producción agosto 2025 • MPV 3 (R4) Se encuentra con un avance de 50%, se entregó las Especificaciones técnicas de las APIs para el desarrollo de Novatronic para agentes y transferencia de entrada. En proceso el desarrollo de retiro y deposito por ventanilla. Luego de ello se realizará una prueba integral. Se estima su pase a producción Nov_2025. En coordinaciones con usuario para la actualizacion del cronograma. 7/07/2025: Según lo informado por el usuario LPalacios mediante correo del 17.07 indico: • MP2 (R3) Se encuentra con un avance de 90% quedando pendientes ejecutar las pruebas de rendimiento. Se estima su pase a producción agosto 2025 • MPV 3 (R4) Se encuentra con un avance de 50%, se entregará las Especificaciones técnicas de las APIs para el desarrollo de Novatronic. Luego de ello se realizará una prueba integral. Se estima su pase a producción Nov_2025 Estas fechas deberían ser comunicado a la Gerencia de Planeamiento. 11/06/2025:Según la información enviada de Planeamiento en el mes de Mayo se precisa lo siguiente: Durante la ejecución de las pruebas integrales en el entorno de desarrollo, en las que participan los tres proveedores (Backbase, Temenos y Novatronic), se han identificado incidencias relacionadas con la conexión a la Cámara de Compensaciones y con los tiempos de respuesta en las operaciones correspondientes al proceso de interoperabilidad (transferencias interbancarias inmediatas y pagos con QR). -Estas situaciones vienen siendo atendidas de manera conjunta por Novatronic, Temenos y el Banco de la Nación. 03/06/2025: Según la información enviada de Planeamiento mediante correo respecto al proyecto en el mes de abril se tiene que: Durante las pruebas integrales (participación de los 3 proveedores) se presentó incidencias con el tarifario dinámico que interactúa con todo el proceso de interoperabilidad (transferencias interbancarias inmediatas, pago con QR) la que está siendo atendidas por Novatronic. Asimismo, el proveedor Tenemos, presentó incidente en la data que se trasmite al core T24. Se realizan reuniones de seguimiento 2 veces al día para el seguimiento de las pruebas y corrección de los incidentes Se estima culminar las pruebas en desarrollo la primera semana de mayo iniciar pruebas en el ambiente de Calidad. 07/05/2025: Según la información enviada por Planeamiento mediante correo: Se continúan las pruebas en desarrollo de las funcionalidades de transferencias inmediatas, por contacto y QR con el proveedor BACKBASE, TEMENOS y NOVATRONIC. Se mantienen las pruebas en desarrollo de las funcionalidades de retiro y deposito en agente BN y para retiro y depósito en ventanilla con el proveedor TEMENOS y el BN. 31/12/2024: Las áreas usuarias validaron las funcionalidades de retiro y depósito en Ventanilla y se procedió con la generación del Anexo 2 para solicitar la inscripción en el Clear Quest. Se continúan coordinando con el proveedor Temenos para correcciones. Siguen en construcción la funcionalidad de transferencias Q 23/05/24 Mediante comité estratégico de proyectos con fecha 06.05.24 se aprobó el control de cambios del proyecto.Esto implica nuevas actividades y actualizacion en el cronograma. TI solicitará al usuario remtiir anexo 1 actualizado. 08/04/24 Se cambió la fecha de Fin de proyecto a 2025 20/03/24 Usuario remitió modelo de negocio y se registró en la demanda estrategica de TI, sin embargo se encuentra pendiente que el usuario remita modelo de negocio actualizado. Está retrasado porque el proveedor no contempló dentro del cronograma actividades funcionales que son necesarias para el proytecto. Presentarán un control de cambios a nivel de alcance, tiempo y presupuesto. 03/06/2025: Según la información enviada de Planeamiento mediante correo respecto al proyecto en el mes de abril se tiene que: Durante las pruebas integrales (participación de los 3 proveedores) se presentó incidencias con el tarifario dinámico que interactúa con todo el proceso de interoperabilidad (transferencias interbancarias inmediatas, pago con QR) la que está siendo atendidas por Novatronic. Asimismo, el proveedor Tenemos, presentó incidente en la data que se trasmite al core T24. Se realizan reuniones de seguimiento 2 veces al día para el seguimiento de las pruebas y corrección de los incidentes Se estima culminar las pruebas en desarrollo la primera semana de mayo iniciar pruebas en el ambiente de Calidad. 30/04/25: Según lo informado por el usuario LPalacios mediante correo, la fecha fin del proyecto que estaba proyectado de culminar en abril ahora se indica lo siguiente: • Transferencias inmediatas: Fines de mayo a quincena de junio. • Depósito / Retiro en Ventanilla: Fines de mayo a quincena de junio. • Depósito / Retiro en agentes: fines de junio a quincena de julio. 04/04/25: Según lo informado por el usuario LPalacios mediante correo del 28/03, la fecha fin del proyecto estaba programado para el 30 de marzo, sin embargo, todavía existe dependencias de los proveedores, por lo que se proyecta culminar con el Proyecto el 30 de abril.. 28/02/2025: Transferencias Interbancarias Inmediatas (CCI, QR, Contacto), Transferencias Internas CTA-BN a CTA-DNI, Retiro/Depósito Agentes Corresponsales, Retiro y Depósito en Ventanilla se encuentran en Desarrollo. Usuario remitió 1 nuevo requerimiento asociado al Proyecto, el mismo que se encuentran en Desarrollo 21/03/25: Mediante correo del 21/03/25 de Planeamiento se indica: Se encuentra en pruebas de desarrollo las funcionalidades de transferencias inmediatas, por contacto y QR con el proveedor BACKBASE, TEMENOS y NOVATRONIC. Se han culminado las pruebas en certificación para las funcionalides de Generación de Estados de Cuenta y Cambio de CCI con el proveedor TEMENOS. Para la quincena de marzo se espera el pase a producción 17/01/25 En proceso de atención 28/01/25 El desarrollo asociado a Saraweb (2024-M0299-Validación de identidad externa para enrolamiento en Cuenta DNI con registro de titular en línea) está culminado. A espera que el proveedor realice el cambio en su API para retomar las pruebas de integración. Usuario remitió 3 nuevos requerimientos asociados al Proyecto, el mismo que se encuentran en Planificación. 31/12/24: Las áreas usuarias validaron las funcionalidades de retiro y depósito en Ventanilla y se procedió con la generación del Anexo 2 para solicitar la inscripción en el Clear Quest. Se continúan coordinando con el proveedor Temenos para correcciones. 20/03/24 Usuario remitió modelo de negocio y se registró en la demanda estrategica de TI, sin embargo se encuentra pendiente que el usuario remita modelo de negocio actualizado. Según lo informado por Planeamiento, el Py está retrasado porque el proveedor no contempló dentro del cronograma actividades funcionales, que son necesarias para el proyecto. Presentarán un control de cambios a nivel de alcance, tiempo y presupuesto e informarán a TI. 16/02/2024: COMITE EXCPECIONAL: Se realiza su priorización El Proyecto fue priorizado por el Ejecutivo de Proyecto, se tiene el Anexo 1 - Modelo de Negocio. Usuario remitó requerimiento para enrolamiento con Bioemtría facial. | AV15: ='Portafolio P&D'!B9 -> 0
A16: 12 | E16: Proyecto | F16: Proyecto 12 | H16: G1 | AG16: No aplica | AH16: ='Portafolio P&D'!Y12 -> 0 | AI16: ='Portafolio P&D'!Z12 -> 0 | AK16: ='Portafolio P&D'!AA12 -> 1 | AL16: ='Portafolio P&D'!AB12 -> 1 | AM16: =IF(DemandaEstrateg_[[#This Row],[Tipo de Requerimiento]]="Proyecto",(DemandaEstrateg_[[#This Row],[% Avance ejecutado]]-DemandaEstrateg_[[#This Row],[% Avance Planificado]])/DemandaEstrateg_[[#This Row],[% Avance Planificado]],"No aplica") -> 0 | AN16: =IF(DemandaEstrateg_[[#This Row],[Tipo de Requerimiento]]="Proyecto",(DemandaEstrateg_[[#This Row],[% Avance ejecutado]]-DemandaEstrateg_[[#This Row],[% Avance Planificado]])/DemandaEstrateg_[[#This Row],[% Avance Planificado]],"No aplica") -> 0 | AP16: 45748 | AQ16: 2025-II | AR16: Pendiente | AS16: 09. Finalizado | AT16: =VLOOKUP(DemandaEstrateg_[[#This Row],[Estado TI]],#REF!,3,FALSE) -> #REF! | AU16: 17/07/2025: El Proyecto Culminó en el mes de abril2025. 11/06/2025:Según la información enviada de Planeamiento en el mes de Mayo se precisa lo siguiente: El Equipo Técnico del proyecto informó que, se culminó con la implementación al 100%. Asimismo, se presentó el avance de las siguientes actividades: Implementación: Ejecución: 100% (finalizado) Monitoreo y Control: 100% (finalizado) Cierre 100% (finalizado) 03/06/2025: Según la información enviada de Planeamiento mediante correo respecto al proyecto en el mes de abril se tiene que: El proyecto ha sido culminado. Fin del Proyecto. 21/05/2025: Según el Acta de Reunión N°04-2025 del Comité de Proyectos, se enviará a Planeamiento el Acta de Cierre del Proyecto y el fomato de lecciones aprendidas en las próximas semanas. 07/05/2025: Según la información remitida por Planeamiento mediante correo: A nivel tareas, actualmente se encuentra en la Etapa de Implementación del Proyecto. El Equipo Técnico del proyecto informó que, solo faltan instalar 45 equipos de 547 nuevos equipos en la Red de Agencias. Además, se revisaron posibles riesgos y desafíos que podrían impactar el cronograma, con el objetivo de tomar medidas preventivas y correctivas. Finalmente, se comunicó que las actividades del proyecto se vienen realizando de acuerdo a lo planificado. Asimismo, se presentó el avance de las siguientes actividades: • Implementación: Ejecución: 96% (en proceso) Monitoreo y Control: 97% (casi finalizado) 31/12/2024: *Se instalaron 280 switches para las sedes administrativas así como la implementación de los servidores plataforma de gestión, la solución NAC y Control de accesos. Dado esto, se viene realizando la entrega de la conformidad del servicio para el pago correspondiente por esta primera etapa. * Los usuarios de Canales Virtuales y Red de Agencias solicitaron no realizar trabajos durante esta semana por lo que se suspenden las actividades hasta el mes de enero. 23/05/24 Validar si se firmó el contrato. A espera que el proveedor entregue el plan de trabajo. 25/04/2024 Mediante Memo N° 63-2024-BN2810 en que se entrega la nueva lista de proyectos con componente TI se genera cambio en el lider del proyecto de José Macedo a Alejandro Sifuentes 25/04/2024 Mediante Memo N°60-2024-BN2810 se informa que se requiere el informe de las razones del retraso del proyecto asi como sus acciones correctivas para la presentación al comité del 26.04 20/03/24 Esta en proceso logistico (analisis de oferta y la buena pro se dará en marzo). Presentarán un nuevo cronograma con control de cambios. 03/06/2025: Según la información enviada de Planeamiento mediante correo respecto al proyecto en el mes de abril se tiene que el proyecto ha sido culminado. 21/05/2025: Según el Acta de Reunión N°04-2025 del Comité de Proyectos, se enviará a Planeamiento el Acta de Cierre del Proyecto y el fomato de lecciones aprendidas en las próximas semanas. 30/04/2025: El Equipo Técnico del proyecto informó que, se culminó con la implementación al 100%. Finalmente, también se comunicó que las actividades del proyecto se realizaron de acuerdo a lo planificado. Se comunicará y se enviará a la G. de Planeamiento el Acta de Cierre de proyecto y lecciones aprendidas 31/03/2025: Las actividades del proyecto se vienen realizando de acuerdo a lo planificado. Actualmente, solo faltan instalar 45 equipos de 547 nuevos equipos en la red de agencias. 21/03/25: Mediante correo del 21/03/25 de Planeamiento se indica: El Equipo Técnico del proyecto seguirá apoyando al proveedor en la instalación de switches en lobbys, agencias y oficinas especiales, reafirmando su compromiso con el éxito del proyecto. Para asegurar el cumplimiento del cronograma, el Equipo Técnico hará un seguimiento constante del avance de la instalación e informará sobre los hitos alcanzados. Si es necesario, se gestionará un control de cambio para ajustar el cronograma a las nuevas fechas y mantener la alineación con los objetivos del proyecto. 28/02/2025: El Equipo Técnico del proyecto informó que, desde febrero, ha estado brindando apoyo al Proveedor en la instalación de Switches en lobbys, agencias y oficinas especiales. Además, se revisaron posibles riesgos y desafíos que podrían impactar el cronograma, con el objetivo de tomar medidas preventivas y correctivas. Asimismo, se presentó el avance de las siguientes actividades: • Implementación: Planificación: 100% (completada) , Ejecución: 48% (en proceso), Monitoreo y Control: 94% (casi finalizado) 17/02/2025: El Proveedor esta realizando las actividades segun lo planificado en el nuevo cronograma, al respecto el Equipo Técnico del proyecto en caso de que sea necesario, solicitará un control de cambio, a fin de ajustar el cronograma conforme a las nuevas fechas. 31/01/2025:Se informa que el 13.01.2025 el BN recibe la solicitud de ampliación de plazo N°01 presentada por el contratista CONSORCIO ALFIL CONSULTORIA Y COMUNICACIONES S.A.C. - ADISTEC PERU S.A.C. donde solicitan 32 (treinta y dos) días calendario de ampliación del plazo contractual al contrato esto debido a que en el mes de diciembre 2024, las actividades fueron suspendidas a pedido del área usuaria (Sección Canales Presenciales de la Subgerencia Canales Alternos de la Gerencia Banca Digital). El 25/01/2025, la Sección Soporte de la Infraestructura emite el informe N° 022-2025-BN/2574 solicitado por la Sección Seguimiento Administrativo de contratos mediante Memorando N° 041-2025-BN/2664 el 14/01/2025. Finalmente, el 27/01/2025, Mediante Resolución de Gerencia de Administración y Logistica N° 007-2025-BN/5500, declara procedente la solicitud de ampliación de plazo N°01 presentada por el contratista CONSORCIO ALFIL CONSULTORIA Y COMUNICACIONES S.A.C. - ADISTEC PERU S.A.C. con fecha 13/01/2025, toda vez que cumple con los requisitos establecidos por ley. 31/12/24: *Se instalaron 280 switches para las sedes administrativas así como la implementación de los servidores plataforma de gestión, la solución NAC y Control de accesos. Dado esto, se viene realizando la entrega de la conformidad del servicio para el pago correspondiente por esta primera etapa. * Los usuarios de Canales Virtuales y Red de Agencias solicitaron no realizar trabajos durante esta semana por lo que se suspenden las actividades hasta el mes de enero. 13/12/2024: Se informó el avance de las siguientes actividades: Planificación: 95%, Ejecución: 40%, Monitoreo y Control: 82%.. Se culminó con la instalacion en la Sede Principal de San Borja y Elizalde. Nos informaron que el nuevo Líder Técnico es el analista Alberth Rivera 08/11/2024: Se informó el avance de las siguientes actividades: Planificación: 95%, Ejecución: 34%, Monitoreo y Control: 68%. Solo queda pendiente la instalación de switches en el piso 1 y el Network Access Control – NAC, progreso al 80%. 26/09/2024: Se informó el avance de las siguientes actividades: Planificación: 95%, Ejecución: 17%, Monitoreo y Control: 53% 09/08/2024: Durante el mes de agosto se realizarán actividades de instalación de Switches en el Local de Elizalde y San Borja. Actualmente se encuentra en la Etapa de Implementación del Proyecto y se realizan las actividades según el Plan de Trabajo presentado por el Proveedor. 11/07/2024: Se acepto el Control de Cambio para sincerar las fechas del cronograma de actividades, el Proyecto se desarrolla segun lo planificado. 21/06/24 El 02/05/2024 se firmó el Contrato y el 17/05/2024 se realizó la reunión de kickoff con la presentación y aprobación del Plan de Trabajo por parte del Proveedor. Actualmente se encuentra en la Etapa de Implementación del Proyecto, asimismo el Equipo del proyecto presentó Control de Cambio a la Gerencia de Planeamiento, para sincerar las fechas del cronograma. 03/05/24 La buena pro se dio el 22/03/24, actualmente se están revisando los documentos para la firma del contrato. Proyecto aprobado por P&D y comunicado a TI mediante MEMORANDO N° 00000201 - 2023-BN/2810 | AV16: ='Portafolio P&D'!B12 -> 0
A17: 13 | E17: Proyecto | F17: Proyecto 13 | H17: G1 | AH17: ='Portafolio P&D'!Y7 -> 0 | AI17: ='Portafolio P&D'!Z7 -> 0 | AK17: ='Portafolio P&D'!AA7 -> 0.88 | AL17: ='Portafolio P&D'!AB7 -> 0.85 | AM17: =IF(DemandaEstrateg_[[#This Row],[Tipo de Requerimiento]]="Proyecto",(DemandaEstrateg_[[#This Row],[% Avance ejecutado]]-DemandaEstrateg_[[#This Row],[% Avance Planificado]])/DemandaEstrateg_[[#This Row],[% Avance Planificado]],"No aplica") -> -0.034090909 | AN17: =IF(DemandaEstrateg_[[#This Row],[Tipo de Requerimiento]]="Proyecto",(DemandaEstrateg_[[#This Row],[% Avance ejecutado]]-DemandaEstrateg_[[#This Row],[% Avance Planificado]])/DemandaEstrateg_[[#This Row],[% Avance Planificado]],"No aplica") -> -0.034090909 | AP17: 46062 | AQ17: 2026-I | AR17: Pendiente | AS17: 03. En Desarrollo | AT17: =VLOOKUP(DemandaEstrateg_[[#This Row],[Estado TI]],#REF!,3,FALSE) -> #REF! | AU17: 30/12/2025: Según el acta de reunión del comité de proyectos, se debe entregar el cronograma firmado según el último control de cambios (noviembre 2025) y enviarlo vía STD a la Gerencia de Planeamiento y Control de Gestión. Asimismo, Banca Digital debe presentar el informe de evaluación costo–beneficio sobre las propuestas de alquiler de ATM’s. 05/09/2025 BN viene realizando la configuración del Zytrust para el ambiente de Desarrollo. El proveedor ha solicitado usuarios del Active Directory para el Zytrust y se está agendando reunión con el equipo de seguridad. Sobre los controles EMV, equipo de Seguridad Informática precisa que la validación EMV es un control requerido por la SBS, esta pendiente el pronunciamiento del Proveedor y realizarse reunión con la participación del Oficial de Cumplimiento y el Área Usuaria. El 29/08 se remitió al Proveedor observaciones al Plan de continuidad. El equipo de Construcción remitió la documentación de las APIs. El 29/08 se remitió al Proveedor observaciones al Plan de continuidad. El equipo de Construcción remitió la documentación de las APIs 25/07/2025: Usuaria MCarbajo confirmó el inicio de la Etapa de implementación a partir del 15/07, fecha en la cual el Quiosco fue internado en el laboratorio de la sede principal del BN, respecto al cual se están realizando coordinaciones con el Proveedor para efectuar la instalación y/o configuración del Quiosco. El BN-Construcción se encuentra desarrollando las APIs segun flujos definidos en el Modelo de Negocio. De acuerdo a revisión conjunta con el area usuaria de la matriz de riesgos, se requiere una actualización del Anexo1-modelo de negocio. Pendiente actualizar cronograma en coordinación con el Proveedor y usuarios. 17/07/2025: TI remitió el 11/07 los informes de conformidad a Banca Digital de acuerdo a su competencia. Banca digital confirmó el inicio de la etapa de instalación, configuración y desarrollo de la aplicación a partir del 15/07 (Por 90 días). El día 15/07 se realizo el internamiento del quiosco en el laboratorio del BN (Oficina Principal). Se agendarán reuniones para revisar el cronograma y definir las actividades técnicas y plazos. 07/07/2025: Los Informes de COnformidad de equipos se encuentran en proceso de emision para ser reportados a Banca Digital. 11/06/2025:Según la información enviada de Planeamiento en el mes de Mayo se precisa lo siguiente: Las áreas de Sección Soporte de la Infraestructura Tecnológica y Atención a Usuario, Sección Sistemas Bancarios, Sección Canales Presenciales y Subgerencia de Innovación digital ya verificaron los equipos de quioscos multimedia ingresados al almacén del Banco y está en proceso la firma de las actas de conformidad respectivas de cada área. Se espera tener el flujo funcional cerrado, para ello se esta realizando las reuniones de entendimiento entre las áreas responsables. 03/06/2025: Según la información enviada de Planeamiento mediante correo respecto al proyecto en el mes de abril se tiene que: Se recepcionó los quioscos multimedia en el almacén del Banco y se inició las coordinaciones para proceder a la verificación de los equipos durante el mes de mayo. Cabe resaltar que el proveedor efectuó la referida entrega con antelación, dado que estuvo planificada para el mes de julio. 07/05/2025: Según la información enviada por Planeamiento mediante correo: Se encuentra en proceso la definición del esquema de integración de los quioscos con el core del Banco para la transacción de reposición de tarjeta, lo que permitirá continuar con las actividades que se tenían planificadas, 31/12/2024: Se completó la firma del contrato con la empresa ganadora y se tiene un cronograma con control de cambios aprobado por el Comité de proyectos 23/05/24 Mediante comité estratégico del proyecto con fecha 06.05.24 se informa que se aprobó el control de cambios, que implica un nuevo cronograma; el alcance se mantiene. 15/05/2024 Mediante correo de Marita Carbajo entrega ETMS actualizados y deja constancia que con memo N°568-2024-BN-2662 hay consultas de Belltech de ser necesarias agregarlas a ETMS. 02/05/2024 Mediante correo de Hector Sevalla se da a conocer los temas e implementaciones que puede tener el proyecto, se deja en conocimiento la inclusión a un sistema ESP/LINK, aumento de funcionalidades de ATM e inclusión de BEVERTEC. A la espera de agendarse reunión para 02.05 y consolidar los temas pendientes. 26/04/2024 Mediante correo se espera la actualización del documento Anexo 1 que debe ser remitido por el área correspondiente por tener observaciones en el nombre del proyecto y falta de fecha del proyecto. Asi mismo, se espera la solicitud de validación del cronograma del proyecto. Mediante correo se pide reagendar reunión y confirmar la asistencia a esta del Subgerente de Construcción de aplicaciones. 25/04/2024 Mediante correo de Marita Carbajo se da conocimiento de la consulta en coordinacion de Construcción de aplicaciones y el proveedor sobre el intercambio de llaves para que el Kiosko se comporte como un ATM. Se pide agendar reunión para el 26.04 con miembros de TI 24/04/2024 Se entrega vía correo por parte de Marita Carbajo el Anexo 1"Modelo de Negocio". 24/04/2024 Se recibe el correo envíado por Marita Carbajo en el que se notifica la entrega de documentación de Viabilidad Técnica, Modelo funcional y Cronograma del proyecto. Se pide enviar el Modelo de Negocio - Anexo 1 08/04/24 Se realizó cambio de fecha de fin de proyecto de 2023 a 2025 20/03/24 Usuario se encuentra resolviendo las observaciones de las ETMs en coordinación con Logística. Habra un control de cambios, en base al cronograma que presentará el usuario. Pendiente que el usuario remita modelo de negocio para registrar el Proyecto en la demanda estrategica priorizada. Modelo de Negocio Observado 03/06/2025: Según la información enviada de Planeamiento mediante correo respecto al proyecto en el mes de abril se tiene que: Se recepcionó los quioscos multimedia en el almacén del Banco y se inició las coordinaciones para proceder a la verificación de los equipos durante el mes de mayo. Cabe resaltar que el proveedor efectuó la referida entrega con antelación, dado que estuvo planificada para el mes de julio. 02/06/2025 El 22/5/2025 se programó la visita de las áreas respectiva para la verificacion de levantamiento de observaciones. Banca Digital mediante Memo: N° 00000063 - 2025-BN/7920 del 26/05/2025, remitió a TI, las licencias pendientes de Quioscos por parte de contratista, los cuales fueron envidas a las áreas responsables de Banco para su revisión y elaboración de informe u observaciones. 09/05/2025 El 25/4/2025 el contratista entrego los equipos , mediante Guía De remisión N° T003-146; El 30/4/2025 se realizó la primero verificación física de equipos y el 8/5(2025 se realizo la segunda revision, se remitio informe via correo a Banca Digital; El 06/5/2025 se realizó reunión entre Bevertec , Belltech y Banco de la Nación para definir el tema de las API 04/04/2025: TI remitió informes técnicos con MEMORANDO N° 00000021 - 2025-BN/2542 y MEMORANDO N° 00000036 - 2025-BN/2542 con observaciones, respecto a las coordinaciones iniciales con el proveedor se solicitó al líder usuario que coordine con Legal, Logística y Planeamiento resolver las divergencias con el Proveedor. 21/03/25: Mediante correo del 21/03/25 de Planeamiento se indica: Se continuó efectuando las reuniones de entendimiento técnico y funcional entre los equipos del BN y Proveedor, sobre los flujos funcionales y técnicos, arquitectura, encriptamiento de disco, flujo de pantallas y prototipos, entre otros. 03/03/25: Se están ejecutando reuniones de entendimiento con el Proveedor, se revisaron los flujos con el area usuaria, además de la arquitectura y prototipos funcionales. 28/01/25 Se está realizando reuniones técnicas/funcionales con el equipo técnico involucrado, usuarios y Proveedor. 03/03/25: El equipo de TI, remitió informe respecto a los aspectos técnicos que deben de tomar en cuenta el proveedor para la implementación del proyecto. En reuniones periódicas para delimitar el alcance. 24/10/24 Se encuentra en Logística - comité de selección (absolución de consultas) 03/05/24: Anexo 1 recibido el 12/04/24. Actualmente se encuentra en modificación de TDR por estudio de mercado y en taller de riesgos. Responsable Actual Sub. Arquitectura de TIC | AV17: ='Portafolio P&D'!B7 -> 0
A18: 14 | E18: Proyecto-Hijo | F18: Proyecto 14 | H18: G1 | AH18: 45421 | AI18: 45723 | AK18: No aplica | AL18: No aplica | AM18: =IF(DemandaEstrateg_[[#This Row],[Tipo de Requerimiento]]="Proyecto",(DemandaEstrateg_[[#This Row],[% Avance ejecutado]]-DemandaEstrateg_[[#This Row],[% Avance Planificado]])/DemandaEstrateg_[[#This Row],[% Avance Planificado]],"No aplica") -> No aplica | AN18: =IF(DemandaEstrateg_[[#This Row],[Tipo de Requerimiento]]="Proyecto",(DemandaEstrateg_[[#This Row],[% Avance ejecutado]]-DemandaEstrateg_[[#This Row],[% Avance Planificado]])/DemandaEstrateg_[[#This Row],[% Avance Planificado]],"No aplica") -> No aplica | AP18: 46023 | AQ18: 2026-I | AR18: Asignado | AS18: =VLOOKUP(DemandaEstrateg_[[#This Row],[Últ. Estado CQ 30.04]],#REF!,3,FALSE) -> #REF! | AT18: =VLOOKUP(DemandaEstrateg_[[#This Row],[Estado TI]],#REF!,3,FALSE) -> #REF! | AU18: 09/05/2024: Se registró en la demanda integral | AV18: No Aplica
A19: 15 | E19: Proyecto-Hijo | F19: Proyecto 15 | H19: G1 | AH19: 45442 | AI19: 45723 | AK19: No aplica | AL19: No aplica | AM19: =IF(DemandaEstrateg_[[#This Row],[Tipo de Requerimiento]]="Proyecto",(DemandaEstrateg_[[#This Row],[% Avance ejecutado]]-DemandaEstrateg_[[#This Row],[% Avance Planificado]])/DemandaEstrateg_[[#This Row],[% Avance Planificado]],"No aplica") -> No aplica | AN19: =IF(DemandaEstrateg_[[#This Row],[Tipo de Requerimiento]]="Proyecto",(DemandaEstrateg_[[#This Row],[% Avance ejecutado]]-DemandaEstrateg_[[#This Row],[% Avance Planificado]])/DemandaEstrateg_[[#This Row],[% Avance Planificado]],"No aplica") -> No aplica | AP19: No Aplica | AQ19: No Aplica | AR19: No Aplica | AS19: 10. Descartado | AT19: 05. Descartado | AU19: 23/19/2025: Se descarta por duplicidad ID 1751 21/05/2024: Se registró en la demanda integral y estrategica. | AV19: No Aplica
A20: 16 | E20: Proyecto-Hijo | F20: Proyecto 16 | H20: G1 | AH20: 45442 | AI20: 45723 | AK20: No aplica | AL20: No aplica | AM20: =IF(DemandaEstrateg_[[#This Row],[Tipo de Requerimiento]]="Proyecto",(DemandaEstrateg_[[#This Row],[% Avance ejecutado]]-DemandaEstrateg_[[#This Row],[% Avance Planificado]])/DemandaEstrateg_[[#This Row],[% Avance Planificado]],"No aplica") -> No aplica | AN20: =IF(DemandaEstrateg_[[#This Row],[Tipo de Requerimiento]]="Proyecto",(DemandaEstrateg_[[#This Row],[% Avance ejecutado]]-DemandaEstrateg_[[#This Row],[% Avance Planificado]])/DemandaEstrateg_[[#This Row],[% Avance Planificado]],"No aplica") -> No aplica | AP20: 46082 | AQ20: 2026-I | AR20: No Aplica | AS20: 10. Descartado | AT20: =VLOOKUP(DemandaEstrateg_[[#This Row],[Estado TI]],#REF!,3,FALSE) -> #REF! | AU20: 23/19/2025: Se descarta por duplicidad ID 1752 21/05/2024: Se registró en la demanda integral y estrategica. | AV20: No Aplica
A21: 17 | E21: Proyecto-Hijo | F21: Proyecto 17 | H21: G1 | AH21: 45524 | AI21: 45777 | AK21: No aplica | AL21: No aplica | AM21: =IF(DemandaEstrateg_[[#This Row],[Tipo de Requerimiento]]="Proyecto",(DemandaEstrateg_[[#This Row],[% Avance ejecutado]]-DemandaEstrateg_[[#This Row],[% Avance Planificado]])/DemandaEstrateg_[[#This Row],[% Avance Planificado]],"No aplica") -> No aplica | AN21: =IF(DemandaEstrateg_[[#This Row],[Tipo de Requerimiento]]="Proyecto",(DemandaEstrateg_[[#This Row],[% Avance ejecutado]]-DemandaEstrateg_[[#This Row],[% Avance Planificado]])/DemandaEstrateg_[[#This Row],[% Avance Planificado]],"No aplica") -> No aplica | AQ21: 2026-I | AR21: Certificado | AS21: =VLOOKUP(DemandaEstrateg_[[#This Row],[Últ. Estado CQ 30.04]],#REF!,3,FALSE) -> #REF! | AT21: =VLOOKUP(DemandaEstrateg_[[#This Row],[Estado TI]],#REF!,3,FALSE) -> #REF! | AU21: 25/10/2024 De acuerdo a lo coordinado con ARisco el Desarrollo está terminado. En paralelo se está realizando el desarrollo en Saraweb, posterior a ello se podra realizar la prueba en desarrollo y efectuar el pase a Calidad. 28/05/2024: Se registra en la demanda integral y estrategica. El requerimiento es hijo del Proyecto Cuenta DNI (ID padre 2056). | AV21: No Aplica
A22: 18 | E22: Proyecto | F22: Proyecto 18 | H22: G1 | AH22: 45427 | AI22: 46044 | AK22: 1 | AL22: 0.94 | AM22: =IF(DemandaEstrateg_[[#This Row],[Tipo de Requerimiento]]="Proyecto",(DemandaEstrateg_[[#This Row],[% Avance ejecutado]]-DemandaEstrateg_[[#This Row],[% Avance Planificado]])/DemandaEstrateg_[[#This Row],[% Avance Planificado]],"No aplica") -> -0.06 | AN22: =IF(DemandaEstrateg_[[#This Row],[Tipo de Requerimiento]]="Proyecto",(DemandaEstrateg_[[#This Row],[% Avance ejecutado]]-DemandaEstrateg_[[#This Row],[% Avance Planificado]])/DemandaEstrateg_[[#This Row],[% Avance Planificado]],"No aplica") -> -0.06 | AP22: 46023 | AQ22: 2026-I | AR22: Aprobado | AS22: 05. En Calidad | AT22: =VLOOKUP(DemandaEstrateg_[[#This Row],[Estado TI]],#REF!,3,FALSE) -> #REF! | AU22: 14/01/2026 EEl Proyecto tuvo un retraso por parte del Proveedor en la entrega de la documentación del ciclo de vida de software, requisito para el pase a Calidad, motivo por el cual el pase a calidad se realizó el 16/12/25, a partir del cual se inició el proceso de despliegue hasta el 12/01/26. El avance de las pruebas previas de Calidad es del 11% y se ejecutará del 13 al 18/01. Las pruebas de usuario, se llevará a cabo del 19/01 al 23/01. Se estima pase a producción fines del mes de enero, considerando que el Proveedor haya resuelto todos los defectos y haya subsanada las vulnerabilidades 15/12/2025 Con fecha de hoy, se aprobó el pase a Calidad. Las vulnerabilidad detectadas fueron asumidas por el area de Riesgos (ver correo de fecha jueves, 11 de diciembre de 2025 10:00 replicado por Leslie Vallejos). A la fecha, en coordinación con el Proveedor se están inciando las actividades de despliegue en el ambiente de Certificación para lueo iniciar con las pruebas de usuario. 10/10/2025: El area líder del Proyecto elaboró el plan actualizado 05/09/2025: El proveedor en coordinación con TI-BN realizaron el despliegue de los microservicios en desarrollo para integrar con Oracle e Ivanti, siendo exitosa la prueba. El proveedor remitió plan para para culminar el 19/09 la integración de ISIM con BN. Se tendrá reunión el 09/09 para revisar la arquitectura y para configurar las licencias de RedHat. El usuario viene compartiendo con TI los casos de prueba para revisar el cumplimiento del formato solicitado. Está pendiente que el usuario gestione la ampliación de plazo e informar a Planeamiento. 25/07/2025: La integración con ISIM-IBM presenta error y continua en revisión del Proveedor. Sobre los Casos de Prueba, se encuentra en proceso de elaboración del lado proveedor en coordinación con los usuarios de cada módulo. Respecto a los nuevos servidores solicitados para los reportes de los usuarios, el equipo de TI manifestó que no se encuentra especificado en los TDR por lo que se recomendó coordinar con Logística. 11/06/2025:Según la información enviada de Planeamiento en el mes de Mayo se precisa lo siguiente: Hay retrasos en las tareas de reportería, conector ISIM, pruebas, etc., Estos se deben a la alta dependencia de Telefónica con su partner Global Suite. En abril se reporto avance de 43%, proyecto tiene fecha de fin julio 2025. 03/06/2025: Según la información enviada de Planeamiento mediante correo respecto al proyecto en el mes de abril se tiene que: Los retrasos en las tareas como reportería, conectores ISIM, etc., se deben a la dependencia de Telefónica con su partner GlobalSuite. Adicionalmente, la limitada flexibilidad del proveedor para ofrecer alternativas a los impases está generando demoras en los ajustes y aprobaciones del área de riesgo 07/05/2025: Según la información remitida por Planeamiento mediante correo: Se han completado 4 de los 15 entregables. El quinto está retrasado por incumplimientos de Global Suite. Por lo que se espera sean superadas en abril. 31/12/2024: Esta en ejecución las tareas: Instalación, Parametrización, Conversión y Migración que tienen retrasos de hasta 7 meses ,debido a las integraciones con las Aplicaciones IVANTI y Oracle y las pruebas de los módulos nuevos con los usuarios. 22/05/24 Usuario presentará un control de cambios; confirman que culminan este año 2024. Contrato firmado el 15/05/24, revisar Memo 086-2024/2182 donde solicitan apoyo de TI.AO24 03/05/2024 En proceso logístico para el otorgamiento de Buena pro 08/04/24 Se ha cambiado la fecha de Fin de proyecto de 2025 a 2024. 20/03/24 Está retrasado en la suscripcion del contrato. Se agendará una reunión para revisar las siguientes actividades que involucra a TI según cronograma. Pendiente que el usuario remita modelo de negocio para registrar el Proyecto en la demanda estrategica priorizada. Pendiente envío Modelo de Negocio 03/06/2025: Según la información enviada de Planeamiento mediante correo respecto al proyecto en el mes de abril se tiene que: Los retrasos en las tareas como reportería, conectores ISIM, etc., se deben a la dependencia de Telefónica con su partner GlobalSuite. Adicionalmente, la limitada flexibilidad del proveedor para ofrecer alternativas a los impases está generando demoras en los ajustes y aprobaciones del área de riesgo 08/05/25: Está pendiente que el Proveedor realice la integración con ISIM y la elaboración de los Casos de Prueba para el inicio de las pruebas en el ambiente de Desarrollo 09/04/25 Segun reunión con el usuario 04/04/2025 En coordinación con LCachuan se tiene el sgte estatus: Las configuraciones de las vistas del lado del proveedor se encuentran en proceso, el proveedor concluyó la integración con Ivanti a 100%; En coordinaciones para crear el grupo en AD; La integración con ISIM debió culminar el 31/03 (retraso por entrega de los servidores), Usuarios se encuentran revisando la malla de roles y perfiles en coordinación con el proveedor; el proveedor debe concluir con los casos de prueba para que el usuario pueda iniciar sus pruebas en desarrollo (aprox. mayo 2025). 21/03/25: Mediante correo del 21/03/25 de Planeamiento se indica: Aprobado el control de cambios se está realizando el proceso de actualización del cronograma detallado del proyecto por parte del Proveedor Telefónica y asimismo continua el proceso de implementación de las funcionalidades del software. 03/03/25: La integración con el AD está concluido. El desarrollo-BN de las vistas en Oracle está terminado al 100% (sigue su flujo de ciclo de vida de sw). La integración con Ivanti esta siendo desarrollado por el proveedor de Telefónica. La integración con ISIM por parte del proveedor está al 80%. El formato de Roles y Perfiles está en proceso a cargo del usuario y el proveedor. 31/01/25: Se validó la integración con AD-GlobalSuite. Usuario dió conformidad a las vistas desarrolladas en Oracle-BN. Proveedor está desarrollando la integración con Invanti, e-mail y el componente de ISIM. Pendiente que el proveedor remita casos de prueba de cada módulo. Usuario se encuentra elaborando el formato 7 de roles y perfiles. 28/01/25: En reuniones técnicas / funcionales con el proveedor y usuariosm hasta la 1ra semana de febrero. 31/12/24: Esta en ejecución las tareas: Instalación, Parametrización, Conversión y Migración que tienen retrasos de hasta 7 meses ,debido a las integraciones con las Aplicaciones IVANTI y Oracle y las pruebas de los módulos nuevos con los usuarios. 24/10/24 Segun lo informado por Luis Cachuan: En Oracle está listo el desarrollo de las vistas, pendiente reunion con el Proveedor para definir como consumir las vistas. Con Ivanti presentaron una cotización para implementar el flujo, usuario está coordinando reunión con telefónica para determinar como se realizará dicha atención. La arquitectura se encuentra aprobada. Con respecto a la integración con AD, el usuario se encuentra completando formato para generar la cuenta de Integración. En paralelo el Proveedor esta atiendo en el propio aplicativo con data de prueba proporcionada por el area usuaria. 27/06/24 Se aprueba su ingreso a la demanda estrategoca. 13/06/2024: Se registró en el Backlog de requerimientos | AV22: ='Portafolio P&D'!B10 -> 0
A23: 19 | E23: Proyecto | F23: Proyecto 19 | H23: G1 | AG23: No aplica | AH23: ='Portafolio P&D'!Y33 -> 0 | AI23: ='Portafolio P&D'!Z33 -> 0 | AK23: ='Portafolio P&D'!AA33 -> 0.9 | AL23: ='Portafolio P&D'!AB33 -> 0.26 | AM23: =IF(DemandaEstrateg_[[#This Row],[Tipo de Requerimiento]]="Proyecto",(DemandaEstrateg_[[#This Row],[% Avance ejecutado]]-DemandaEstrateg_[[#This Row],[% Avance Planificado]])/DemandaEstrateg_[[#This Row],[% Avance Planificado]],"No aplica") -> -0.71111111 | AN23: =IF(DemandaEstrateg_[[#This Row],[Tipo de Requerimiento]]="Proyecto",(DemandaEstrateg_[[#This Row],[% Avance ejecutado]]-DemandaEstrateg_[[#This Row],[% Avance Planificado]])/DemandaEstrateg_[[#This Row],[% Avance Planificado]],"No aplica") -> -0.71111111 | AP23: 45839 | AQ23: 2025-II | AR23: Pendiente | AS23: 09. Finalizado | AT23: =VLOOKUP(DemandaEstrateg_[[#This Row],[Estado TI]],#REF!,3,FALSE) -> #REF! | AU23: 07/07/2025: El proyecto ha sido cerrado formalmente, luego de la culminación exitosa de la negociación entre el Banco de la Nación y el Tribunal Constitucional, mediante la cual se amplió el plazo de cesión de uso de los ambientes ocupados por el Data Center Alterno, extendiéndose del 06 de octubre de 2026 al 06 de octubre de 2029. Ejecutado 26% y planificado 98% 11/06/2025:Según la información enviada de Planeamiento en el mes de Mayo se precisa lo siguiente: El Equipo Técnico continuará con el seguimiento de las actividades relacionadas con la condición suspensiva, asegurando su cumplimiento dentro del plazo estipulado. Con la aceptación de la minuta y la culminación de las actividades suspensivas, el proyecto alcanza su fase de cierre. Se procederá con el envío del informe y el formato de cierre de proyecto, incluyendo las lecciones aprendidas. 03/06/2025: Según la información enviada de Planeamiento mediante correo respecto al proyecto en el mes de abril se tiene que: A nivel tareas, el Equipo Técnico informó que las actividades del proyecto continúan en estado de espera debido a la negociación en curso de la extensión del plazo de cesión en uso de los ambientes ocupados por el Data Center de Contingencia del Banco hasta octubre del 2028 con el Tribunal Constitucional, cuyo resultado determinará la continuidad o cierre del proyecto. Si la negociación no prospera, las actividades pendientes se reanudarán conforme al plan establecido. Actualmente, en espera de la respuesta formal del Tribunal Constitucional al proyecto enviado el 7/03/2025 por la Gerencia General, donde se propone una ampliación de plazo por la cesión de uso de espacio físico donde se aloja el Data Center hasta por tres (03) años (10/2029). 21/05/2025: Según el Acta de Reunión N°04-2025 del Comité de Proyectos, la Gerencia líder debe esperar la respuesta del Tribunal Constitucional para elaborar el Acta de Cierre del Proyecto y el formato de captura de lecciones aprendidas. 07/05/2025: Según la información remitida por Planeamiento mediante correo: A nivel tareas, el Equipo Técnico informó que las actividades del proyecto continúan en estado de espera debido a la negociación en curso de la extensión del plazo de cesión en uso de los ambientes ocupados por el Data Center de Contingencia del Banco hasta octubre del 2028 con el Tribunal Constitucional, cuyo resultado determinará la continuidad o cierre del proyecto. Si la negociación no prospera, las actividades pendientes se reanudarán conforme al plan establecido. Actualmente, en espera de la respuesta formal del Tribunal Constitucional al proyecto enviado el 7/03/2025 por la Gerencia General, donde se propone una ampliación de plazo por la cesión de uso de espacio físico donde se aloja el Data Center hasta por tres (03) años (06 oct 2029). 31/12/2024: El proyecto se encuentra a la espera de la respuesta del Tribunal Constitucional para que indiquen si el tiempo de permanencia del centro de datos se aplaza o no. 23/05/24 TI concluyo con la alaboración del TDR, pendiente envío a Logistica para inicio de estudio de MErcado. 03/05/2024 En elaboración de TDR's y otros documentos para iniciar el estudio del mercado. 25/04/2024 Mediante Memo N° 63-2024-BN2810 en que se entrega la nueva lista de proyectos con componente TI en el mismo se registra nuevo Lider del proyecto por lo que se procede al cambio correspondiente de José Macedo a Alejandro Sifuentes. 10/04/2024 Con correo se envía el memorando N°00000044-2024-BN/2810 "Retraso de envío de información" comunica que el pedido fue atendido mediante memorando 00000012-2024-BN/2540 a la fecha de 08.04.2024. Proyecto fue aprobado por el Comité ejecutivo de Proyectos el 27.03.2024 solicitando ajustes a los documentos iniciales que fueron atendidos y enviados por medio de correo. 06/06/2025: El Equipo Técnico continuará con el seguimiento de las actividades relacionadas con la condición suspensiva, asegurando su cumplimiento dentro del plazo estipulado. Con la aceptación de la minuta y la culminación de las actividades suspensivas, el proyecto alcanza su fase de cierre. Se procederá con el envío del informe y el formato de cierre de proyecto, incluyendo las lecciones aprendidas. 03/06/2025: Según la información enviada de Planeamiento mediante correo respecto al proyecto en el mes de abril se tiene que: A nivel tareas, el Equipo Técnico informó que las actividades del proyecto continúan en estado de espera debido a la negociación en curso de la extensión del plazo de cesión en uso de los ambientes ocupados por el Data Center de Contingencia del Banco hasta octubre del 2028 con el Tribunal Constitucional, cuyo resultado determinará la continuidad o cierre del proyecto. Si la negociación no prospera, las actividades pendientes se reanudarán conforme al plan establecido. Actualmente, en espera de la respuesta formal del Tribunal Constitucional al proyecto enviado el 7/03/2025 por la Gerencia General, donde se propone una ampliación de plazo por la cesión de uso de espacio físico donde se aloja el Data Center hasta por tres (03) años (10/2029). 21/05/2025: Según el Acta de Reunión N°04-2025 del Comité de Proyectos, la Gerencia líder debe esperar la respuesta del Tribunal Constitucional para elaborar el Acta de Cierre del Proyecto y el formato de captura de lecciones aprendidas. 08/05/25: Se coordinará con el líder técnico de producción para el cierre del proyecto de Traslado de Centro de Cómputo de San Isidro y se informará a la Gerencia de Planeamiento. 30/04/2025: El Equipo Técnico informó que las actividades del proyecto continúan en estado de espera debido a la negociación en curso de la extensión del plazo de cesión en uso de los ambientes ocupados por el Data Center de Contingencia del Banco hasta octubre del 2028 con el Tribunal Constitucional, cuyo resultado determinará la continuidad o cierre del proyecto. Si la negociación no prospera, las actividades pendientes se reanudarán conforme al plan establecido. Actualmente, en espera de la respuesta formal del Tribunal Constitucional al proyecto enviado el 7/03/2025 por la Gerencia General, donde se propone una ampliación de plazo por la cesión de uso de espacio físico donde se aloja el Data Center hasta por tres (03) años (10/2029). 31/03/2025: Las actividades del proyecto continúan en estado de espera debido a la negociación en curso de la extensión del plazo de cesión en uso de los ambientes ocupados por el Data Center de Contingencia del Banco hasta octubre del 2028 con el Tribunal Constitucional, cuyo resultado determinará la continuidad o cierre del proyecto. Si la negociación no prospera, las actividades pendientes se reanudarán conforme al plan establecido. Actualmente, estamos a la espera de la respuesta formal del Tribunal Constitucional al proyecto enviado el 7/03/2025 por la Gerencia General, donde se propone una ampliación de plazo por la cesión de uso de espacio físico donde se aloja el Data Center hasta por tres (03) años (06 oct 2029), 21/03/25: Mediante correo del 21/03/25 de Planeamiento se indica: El Equipo Técnico informó que las actividades del proyecto continúan en estado de espera debido a la negociación en curso de la extensión del plazo de cesión en uso de los ambientes ocupados por el Data Center de Contingencia del Banco hasta octubre del 2028 con el Tribunal Constitucional, cuyo resultado determinará la continuidad o cierre del proyecto. Si la negociación no prospera, las actividades pendientes se reanudarán conforme al plan establecido. 28/02/2025: El Equipo Técnico informó que las actividades del proyecto continúan en estado de espera debido a la negociación en curso de la extensión del plazo de cesión en uso de los ambientes ocupados por el Data Center de Contingencia del Banco hasta octubre del 2028 con el Tribunal Constitucional, cuyo resultado determinará la continuidad o cierre del proyecto. Si la negociación no prospera, las actividades pendientes se reanudarán conforme al plan establecido. Actualmente, la Gerencia Legal está elaborando el informe sobre la viabilidad legal de la modificación del contrato, así como la minuta correspondiente. 17/02/2025:El 12/02/2025 el Tribunal Constitucional respondió mediante comunicación formal indicando que la propuesta del BN se encuentra en evaluación y que, para continuar con el proceso de aprobación, es necesario remitir un proyecto de adenda. En ese sentido, el área legal del BN ya se encuentra trabajando en la elaboración de dicha propuesta. 31/01/2025: A la espera de la respuesta formal del Tribunal Constitucional (TC) a solicitud formulada por la Gerencia de Innovación y Transformación Digital (a través de nuestra Gerencia General) con la formalización para extender la permanencia del CDR BN San Isidro más allá de la fecha límite (05.10.2026). de acuerdo a la respuesta se continuarán con las atividades pendientes como la aprobación de la Solicitud de Cambio (actualización de fechas del Cronograma), la instalación del Comité de Concurso de Méritos y la aprobación de Bases Administrativas por parte del Comité de Concurso de Méritos a fin de dar continuidad al proceso logístico , también que la Gerencia de Tecnologías de Información remita – a la Gerencia de Riesgos – la Matriz de Riesgos (formato firmado) para su elevación al Comité de Riesgos. 31/12/2024: El proyecto se encuentra a la espera de la respuesta del Tribunal Constitucional para que indiquen si el tiempo de permanencia del centro de datos se aplaza o no. 13/12/2024: El avance de las actividades pendientes es el siguiente: Proforma de Contrato: EN PROCESO (Gerencia Legal), Control de Cambios del Proyecto: EN PROCESO (Gerencia de Administración y Logística) Matriz de Riesgos: EN PROCESO (Gerencia de Riesgos y Gerencia de Tecnologías de Información) 08/11/2024: El avance de las actividades pendientes es el siguiente: Estudio de mercado culminado: 100%, Informe (Estudio) Viabilidad Económico Financiero: EN PROCESO. El 23.10.2024, mediante el Memorándum N° 0132-2024-BN/2570, el Equipo solicitó Control de Cambio a la Gerencia de Planeamiento para la actualización de fechas del Cronograma. se encuentra en proceso de evaluación de la disponibilidad de recursos presupuestales dentro de la Gerencia, a fin de solicitar a la Gerencia de Finanzas y Tesorería emita la Cobertura de Recursos Presupuestales 26/09/2024: En proceso de estudio de mercado: 95%, El Equipo Técnico está a la espera de la culminación del estudio de mercado a fin de continuar con los trámites administrativos requeridos. 12/08/2024: Actualmente se encuentra en etapa de Estudio de Mercado, excepto otros proveedores remitan nuevo portafolio de consultas y/o se vea necesario actualizar TDRs producto de la evaluación de Riesgos. 27/06/24 Se regulariza su registro en la demanda por ser un Proyecto Estratégico del Banco. | AV23: ='Portafolio P&D'!B33 -> 0
A24: 20 | E24: Proyecto-Hijo | F24: Proyecto 20 | H24: G1 | AH24: 45505 | AI24: 45723 | AK24: No aplica | AL24: No aplica | AM24: =IF(DemandaEstrateg_[[#This Row],[Tipo de Requerimiento]]="Proyecto",(DemandaEstrateg_[[#This Row],[% Avance ejecutado]]-DemandaEstrateg_[[#This Row],[% Avance Planificado]])/DemandaEstrateg_[[#This Row],[% Avance Planificado]],"No aplica") -> No aplica | AN24: =IF(DemandaEstrateg_[[#This Row],[Tipo de Requerimiento]]="Proyecto",(DemandaEstrateg_[[#This Row],[% Avance ejecutado]]-DemandaEstrateg_[[#This Row],[% Avance Planificado]])/DemandaEstrateg_[[#This Row],[% Avance Planificado]],"No aplica") -> No aplica | AP24: 46023 | AQ24: 2026-I | AR24: Asignado | AS24: =VLOOKUP(DemandaEstrateg_[[#This Row],[Últ. Estado CQ 30.04]],#REF!,3,FALSE) -> #REF! | AT24: =VLOOKUP(DemandaEstrateg_[[#This Row],[Estado TI]],#REF!,3,FALSE) -> #REF! | AU24: 01/08/2024 Se registro en el Backlog, se creo el tramite Documentario y se Registro en la Demanda Estrategica. Requerimiento corresponde al entregable 7 de Sentinel. | AV24: No Aplica
A25: 21 | E25: Proyecto-Hijo | F25: Proyecto 21 | H25: G2 | AH25: 45513 | AI25: 45723 | AJ25: 46050 | AK25: No aplica | AL25: No aplica | AM25: =IF(DemandaEstrateg_[[#This Row],[Tipo de Requerimiento]]="Proyecto",(DemandaEstrateg_[[#This Row],[% Avance ejecutado]]-DemandaEstrateg_[[#This Row],[% Avance Planificado]])/DemandaEstrateg_[[#This Row],[% Avance Planificado]],"No aplica") -> No aplica | AN25: =IF(DemandaEstrateg_[[#This Row],[Tipo de Requerimiento]]="Proyecto",(DemandaEstrateg_[[#This Row],[% Avance ejecutado]]-DemandaEstrateg_[[#This Row],[% Avance Planificado]])/DemandaEstrateg_[[#This Row],[% Avance Planificado]],"No aplica") -> No aplica | AP25: 45992 | AQ25: 2025-IV | AR25: Procesado | AS25: =VLOOKUP(DemandaEstrateg_[[#This Row],[Últ. Estado CQ 30.04]],#REF!,3,FALSE) -> #REF! | AT25: =VLOOKUP(DemandaEstrateg_[[#This Row],[Estado TI]],#REF!,3,FALSE) -> #REF! | AU25: 5/12/2024: Según CQ, se actualizó el estado de 01. Registrado a 05. En Calidad 09/08/2024: Se registró en el Backlog de requerimientos. Requerimiento corresponde al entregable 7 de Sentinel. | AV25: No Aplica
A26: 22 | E26: Proyecto-Hijo | F26: Proyecto 22 | H26: G2 | AH26: 45520 | AI26: 45723 | AK26: No aplica | AL26: No aplica | AM26: =IF(DemandaEstrateg_[[#This Row],[Tipo de Requerimiento]]="Proyecto",(DemandaEstrateg_[[#This Row],[% Avance ejecutado]]-DemandaEstrateg_[[#This Row],[% Avance Planificado]])/DemandaEstrateg_[[#This Row],[% Avance Planificado]],"No aplica") -> No aplica | AN26: =IF(DemandaEstrateg_[[#This Row],[Tipo de Requerimiento]]="Proyecto",(DemandaEstrateg_[[#This Row],[% Avance ejecutado]]-DemandaEstrateg_[[#This Row],[% Avance Planificado]])/DemandaEstrateg_[[#This Row],[% Avance Planificado]],"No aplica") -> No aplica | AP26: 46023 | AQ26: 2026-I | AR26: Asignado | AS26: =VLOOKUP(DemandaEstrateg_[[#This Row],[Últ. Estado CQ 30.04]],#REF!,3,FALSE) -> #REF! | AT26: =VLOOKUP(DemandaEstrateg_[[#This Row],[Estado TI]],#REF!,3,FALSE) -> #REF! | AU26: 03/09/24: Según CQ, actualizó el estado a 02. En Planificación 29/08/2024: Se registró en el Backlog de requerimientos. | AV26: No Aplica
A27: 23 | E27: Proyecto-Hijo | F27: Proyecto 23 | H27: G2 | AH27: 45520 | AI27: 45723 | AK27: No aplica | AL27: No aplica | AM27: =IF(DemandaEstrateg_[[#This Row],[Tipo de Requerimiento]]="Proyecto",(DemandaEstrateg_[[#This Row],[% Avance ejecutado]]-DemandaEstrateg_[[#This Row],[% Avance Planificado]])/DemandaEstrateg_[[#This Row],[% Avance Planificado]],"No aplica") -> No aplica | AN27: =IF(DemandaEstrateg_[[#This Row],[Tipo de Requerimiento]]="Proyecto",(DemandaEstrateg_[[#This Row],[% Avance ejecutado]]-DemandaEstrateg_[[#This Row],[% Avance Planificado]])/DemandaEstrateg_[[#This Row],[% Avance Planificado]],"No aplica") -> No aplica | AP27: 46023 | AQ27: 2026-I | AR27: Asignado | AS27: =VLOOKUP(DemandaEstrateg_[[#This Row],[Últ. Estado CQ 30.04]],#REF!,3,FALSE) -> #REF! | AT27: =VLOOKUP(DemandaEstrateg_[[#This Row],[Estado TI]],#REF!,3,FALSE) -> #REF! | AU27: 03/09/24: Según CQ, actualizó el estado a 02. En Planificación 29/08/2024: Se registró en el Backlog de requerimientos. | AV27: No Aplica
A28: 24 | E28: Proyecto-Hijo | F28: Proyecto 24 | H28: G2 | AH28: 45547 | AI28: 45723 | AK28: No aplica | AL28: No aplica | AM28: =IF(DemandaEstrateg_[[#This Row],[Tipo de Requerimiento]]="Proyecto",(DemandaEstrateg_[[#This Row],[% Avance ejecutado]]-DemandaEstrateg_[[#This Row],[% Avance Planificado]])/DemandaEstrateg_[[#This Row],[% Avance Planificado]],"No aplica") -> No aplica | AN28: =IF(DemandaEstrateg_[[#This Row],[Tipo de Requerimiento]]="Proyecto",(DemandaEstrateg_[[#This Row],[% Avance ejecutado]]-DemandaEstrateg_[[#This Row],[% Avance Planificado]])/DemandaEstrateg_[[#This Row],[% Avance Planificado]],"No aplica") -> No aplica | AP28: 45992 | AQ28: 2025-IV | AR28: Descartado | AS28: =VLOOKUP(DemandaEstrateg_[[#This Row],[Últ. Estado CQ 30.04]],#REF!,3,FALSE) -> #REF! | AT28: =VLOOKUP(DemandaEstrateg_[[#This Row],[Estado TI]],#REF!,3,FALSE) -> #REF! | AU28: 05/09/2024: Se registró en el Backlog de requerimientos. 21/08 Refiere a nuevo desarrollo para el entregable 10 de Sentinel. | AV28: No Aplica
A29: 25 | E29: Proyecto | F29: Proyecto 25 | H29: G2 | AH29: ='Portafolio P&D'!Y34 -> 0 | AI29: ='Portafolio P&D'!Z34 -> 0 | AK29: ='Portafolio P&D'!AA34 -> 0.86 | AL29: ='Portafolio P&D'!AB34 -> 0.84 | AM29: =IF(DemandaEstrateg_[[#This Row],[Tipo de Requerimiento]]="Proyecto",(DemandaEstrateg_[[#This Row],[% Avance ejecutado]]-DemandaEstrateg_[[#This Row],[% Avance Planificado]])/DemandaEstrateg_[[#This Row],[% Avance Planificado]],"No aplica") -> -0.023255814 | AN29: =IF(DemandaEstrateg_[[#This Row],[Tipo de Requerimiento]]="Proyecto",(DemandaEstrateg_[[#This Row],[% Avance ejecutado]]-DemandaEstrateg_[[#This Row],[% Avance Planificado]])/DemandaEstrateg_[[#This Row],[% Avance Planificado]],"No aplica") -> -0.023255814 | AP29: 45839 | AQ29: 2025-II | AR29: Pendiente | AS29: 08. Producción Finalizada | AT29: =VLOOKUP(DemandaEstrateg_[[#This Row],[Estado TI]],#REF!,3,FALSE) -> #REF! | AU29: 30/12/2025: Según el acta de reunión del comité de proyectos, se debe reiterar al MEF la conformidad del diseño de las tarjetas, a fin de cumplir con las fechas propuestas actualizadas. 05/09/2025: Las actividades del Piloto Controlado, se realizarán después del 16 de Setiembre. El área usuaria no ha remitido los anexos 2 para levantar las observaciones de los reportes Operativos Contables. 25/07/2025: Se realizaron las actividades de despliegue en producción, el área usuaria viene realizando las validaciones correspondientes con los equipos de BN y MEF. Se ha coordinado reaunadar las actividades del piloto controlado en Producción la primera semana del mes de Agosto. 17/07/2025: Está en proceso de despliegue de la Fase IV en el ambiente de Producción. Las observaciones que se presenten durante el piloto y/o pendientes se atenderán inmediatamente. 11/06/2025:Según la información enviada de Planeamiento en el mes de Mayo se precisa lo siguiente: La demora en el pase a Producción Fase IV está afectando la fase de marcha blanca. Además, la reciente solicitud de especificar los procesos contables podría obligar a un control de cambios en mayo para ajustar el plan original del proyecto. 03/06/2025: Según la información enviada de Planeamiento mediante correo respecto al proyecto en el mes de abril se tiene que: La conclusión total del servicio requiere la colaboración de las unidades orgánicas participantes. A la vez, el equipo de Desarrollo del BN trabaja en los cinco entregables finales, la certificación y el pase a producción, abordando los retrasos actuales. 21/05/2025: Según el Acta de Reunión N°04-2025 del Comité de Proyectos, se solicita a Planeamiento hacer seguimiento al proyecto y que este incluya la parte contable. 07/05/2025: Según la información remitida por Planeamiento mediante correo: Se han completado 5 de los 10 entregables. A pesar de los retrasos de Izipay, las pruebas en POS comenzarán en abril. El equipo de Desarrollo del BN trabaja para cumplir los plazos y completar los entregables restantes. 31/12/2024: Ciclos de pruebas en marcha (379 Ok / 617 Total). Se esta coordinando y resolviendo día a día con proveedor y TI. A la par ya culminaron con remitir solicitud de cambio y cronograma de actividades para que sea aprobado por el comité. 13/05/2024 A la espera del Anexo 1 para poder incorporar el proyecto a la Demanda Estratégica 25/04/2024 Mediante Memo N° 63-2024-BN2810 en que se entrega la nueva lista de proyectos con componente TI se crea el proyecto en base de datos y se asigna el Lider usuario al proyecto, anteriormente no existia . 03/06/2025: Según la información enviada de Planeamiento mediante correo respecto al proyecto en el mes de abril se tiene que: La conclusión total del servicio requiere la colaboración de las unidades orgánicas participantes. A la vez, el equipo de Desarrollo del BN trabaja en los cinco entregables finales, la certificación y el pase a producción, abordando los retrasos actuales. 21/05/2025: Según el Acta de Reunión N°04-2025 del Comité de Proyectos, se solicita a Planeamiento hacer seguimiento al proyecto y que este incluya la parte contable. 30/04/2025: La Fase III del proyecto fue desplegada a Producción, se ha creado la primera Tarjeta Guía y los equipos BN y MEF, dieron inicio al piloto con el Kick Off a 4 entidades, Promperú, SUNAT, MEF y Relaciones Exteriores. Estamos realizando el ciclo de pruebas Fase IV en ambiente de Certificación, donde se ha incorporado principalmente pruebas en comercios y canales foráneos, por lo que estimamos culminar esta fase de pruebas en el mes de junio 2025. 31/03/25: La Fase III del proyecto fue desplegada a Producción, se ha creado la primera Tarjeta Guía y el área usuaria está coordinado con el MEF, el inicio del piloto con 4 entidades (Promperú, SUNAT, MEF y Relaciones Exteriores). Estamos realizando el segundo ciclo de pruebas Fase IV en ambiente de Certificación, donde se está incorporando pruebas en comercios y canales foráneos, por lo que estimamos culminar las pruebas en Certificación en abril para el Inicio del Piloto Integral en abril 2025. 21/03/25: Mediante correo del 21/03/25 de Planeamiento se indica: Se culminó con la 3ra. fase de certificación, iniciando la 4ta. y ultima fase (entregable N° 6). Se culminará la fabricación del material de difusión durante el mes de marzo. 28/02/2025 1. Proyecto Tarjeta Tesoro: Nos encontramos realizado el Piloto de la Fase III en Producción.Iniciamos el Piloto Controlado, se ha creado la primera Tarjeta Guía en Producción, se solicitó el Emboce de la Tarjeta Guía y procederemos a la verificación de Canales.En paralelo, el equipo de Calidad está realizando el segundo ciclo de pruebas Fase IV, donde se está incorporando comercios y canales Foráneos. Alcance Módulo Administrativo: Afiliar entidades y Representantes, Actualizar, Consultar Afiliados y desafiliados, representantes y usuarios autorizados de las entidades habilitadas para solicitar tarjetas. Alcance Módulo Operativo: Solicitud de tarjetas, habilitación de la Línea de crédito, asignaciones, Reporte de las transacciones con los servicios WEB, Agentes, ATM y Ventanilla. Duración del Piloto Controlado Canales BN Marzo 2025. Inicio del Piloto Integral Abril 2025. 28/01/25: Se encuentra realizando pruebas en Calidad y en coordinaciones constantes con Izipay, con un avance de 70%. 31/12/24: Ciclos de pruebas en marcha (379 Ok / 617 Total). Se esta coordinando y resolviendo día a día con proveedor y TI. A la par ya culminaron con remitir solicitud de cambio y cronograma de actividades para que sea aprobado por el comité. 13/12/2024 El Proyecto se está certificando, se remitió nuevo cronograma con las nuevas fechas de implementación. 19/11/2024 Se aprobó un nuevo cronograma con fecha de incio del Piloto para Enero 2025. El proyecto se encuentra a un 74% de avance segun cronograma actualizado al 07 de Noviembre. 12/08/2024 Avance del Proyecto segun cronograma. 27/06/2024 Seregulariza su ingreso a la demanda estratégica. | AV29: ='Portafolio P&D'!B34 -> 0
A30: 26 | E30: Proyecto-Hijo | F30: Proyecto 26 | H30: G2 | AH30: 45567 | AI30: Pendiente | AK30: No aplica | AL30: No aplica | AM30: =IF(DemandaEstrateg_[[#This Row],[Tipo de Requerimiento]]="Proyecto",(DemandaEstrateg_[[#This Row],[% Avance ejecutado]]-DemandaEstrateg_[[#This Row],[% Avance Planificado]])/DemandaEstrateg_[[#This Row],[% Avance Planificado]],"No aplica") -> No aplica | AN30: =IF(DemandaEstrateg_[[#This Row],[Tipo de Requerimiento]]="Proyecto",(DemandaEstrateg_[[#This Row],[% Avance ejecutado]]-DemandaEstrateg_[[#This Row],[% Avance Planificado]])/DemandaEstrateg_[[#This Row],[% Avance Planificado]],"No aplica") -> No aplica | AQ30: 2026-I | AR30: Certificado | AS30: =VLOOKUP(DemandaEstrateg_[[#This Row],[Últ. Estado CQ 30.04]],#REF!,3,FALSE) -> #REF! | AT30: =VLOOKUP(DemandaEstrateg_[[#This Row],[Estado TI]],#REF!,3,FALSE) -> #REF! | AU30: 02/10/2024: Se registró en el Backlog de requerimientos. | AV30: No Aplica
A31: 27 | E31: Proyecto-Hijo | F31: Proyecto 27 | H31: G2 | AH31: 45162 | AI31: 45838 | AK31: No aplica | AL31: No aplica | AM31: =IF(DemandaEstrateg_[[#This Row],[Tipo de Requerimiento]]="Proyecto",(DemandaEstrateg_[[#This Row],[% Avance ejecutado]]-DemandaEstrateg_[[#This Row],[% Avance Planificado]])/DemandaEstrateg_[[#This Row],[% Avance Planificado]],"No aplica") -> No aplica | AN31: =IF(DemandaEstrateg_[[#This Row],[Tipo de Requerimiento]]="Proyecto",(DemandaEstrateg_[[#This Row],[% Avance ejecutado]]-DemandaEstrateg_[[#This Row],[% Avance Planificado]])/DemandaEstrateg_[[#This Row],[% Avance Planificado]],"No aplica") -> No aplica | AP31: 46082 | AQ31: 2026-I | AR31: En_Certificación | AS31: =VLOOKUP(DemandaEstrateg_[[#This Row],[Últ. Estado CQ 30.04]],#REF!,3,FALSE) -> #REF! | AT31: =VLOOKUP(DemandaEstrateg_[[#This Row],[Estado TI]],#REF!,3,FALSE) -> #REF! | AU31: 06/11/24: Se registró en el Backlog | AV31: No Aplica
A32: 28 | E32: Proyecto-Hijo | F32: Proyecto 28 | H32: G2 | AH32: 45604 | AI32: 45930 | AK32: No aplica | AL32: No aplica | AM32: =IF(DemandaEstrateg_[[#This Row],[Tipo de Requerimiento]]="Proyecto",(DemandaEstrateg_[[#This Row],[% Avance ejecutado]]-DemandaEstrateg_[[#This Row],[% Avance Planificado]])/DemandaEstrateg_[[#This Row],[% Avance Planificado]],"No aplica") -> No aplica | AN32: =IF(DemandaEstrateg_[[#This Row],[Tipo de Requerimiento]]="Proyecto",(DemandaEstrateg_[[#This Row],[% Avance ejecutado]]-DemandaEstrateg_[[#This Row],[% Avance Planificado]])/DemandaEstrateg_[[#This Row],[% Avance Planificado]],"No aplica") -> No aplica | AP32: 46082 | AQ32: 2026-I | AR32: Asignado | AS32: =VLOOKUP(DemandaEstrateg_[[#This Row],[Últ. Estado CQ 30.04]],#REF!,3,FALSE) -> #REF! | AT32: =VLOOKUP(DemandaEstrateg_[[#This Row],[Estado TI]],#REF!,3,FALSE) -> #REF! | AU32: 06/11/24: Se registró en el Backlog | AV32: No Aplica
A33: 29 | E33: Proyecto-Hijo | F33: Proyecto 29 | H33: G2 | AH33: 45629 | AI33: Pendiente | AK33: No aplica | AL33: No aplica | AM33: =IF(DemandaEstrateg_[[#This Row],[Tipo de Requerimiento]]="Proyecto",(DemandaEstrateg_[[#This Row],[% Avance ejecutado]]-DemandaEstrateg_[[#This Row],[% Avance Planificado]])/DemandaEstrateg_[[#This Row],[% Avance Planificado]],"No aplica") -> No aplica | AN33: =IF(DemandaEstrateg_[[#This Row],[Tipo de Requerimiento]]="Proyecto",(DemandaEstrateg_[[#This Row],[% Avance ejecutado]]-DemandaEstrateg_[[#This Row],[% Avance Planificado]])/DemandaEstrateg_[[#This Row],[% Avance Planificado]],"No aplica") -> No aplica | AQ33: 2026-I | AR33: Certificado | AS33: =VLOOKUP(DemandaEstrateg_[[#This Row],[Últ. Estado CQ 30.04]],#REF!,3,FALSE) -> #REF! | AT33: =VLOOKUP(DemandaEstrateg_[[#This Row],[Estado TI]],#REF!,3,FALSE) -> #REF! | AU33: 03/12/2024: Se registró en el Backlog y se creó el trámite. | AV33: No Aplica
A34: 30 | E34: Proyecto | F34: Proyecto 30 | H34: G2 | AH34: ='Portafolio P&D'!Y17 -> 0 | AI34: ='Portafolio P&D'!Z17 -> 0 | AK34: ='Portafolio P&D'!AA17 -> 1 | AL34: 0.99 | AM34: =IF(DemandaEstrateg_[[#This Row],[Tipo de Requerimiento]]="Proyecto",(DemandaEstrateg_[[#This Row],[% Avance ejecutado]]-DemandaEstrateg_[[#This Row],[% Avance Planificado]])/DemandaEstrateg_[[#This Row],[% Avance Planificado]],"No aplica") -> -0.01 | AN34: =IF(DemandaEstrateg_[[#This Row],[Tipo de Requerimiento]]="Proyecto",(DemandaEstrateg_[[#This Row],[% Avance ejecutado]]-DemandaEstrateg_[[#This Row],[% Avance Planificado]])/DemandaEstrateg_[[#This Row],[% Avance Planificado]],"No aplica") -> -0.01 | AP34: 45992 | AQ34: 2025-II | AR34: 09. Finalizado | AS34: 09. Finalizado | AT34: =VLOOKUP(DemandaEstrateg_[[#This Row],[Estado TI]],#REF!,3,FALSE) -> #REF! | AU34: 06/10/25: Paquete 1: 2024-P0630 paso a producción en enero 2025. Paquete 2: Los mantenimientos 2025-M0166, 2025-M03192025-M0321 se certificaron el 02.10, el mantenimiento 2025-M0320 se certificó el 03.10. Se planifico el despliegue para la 3era semana de octubre Paquete 3: Se encuentra en Desarrollo. Está pendiente que el usuario gestione la ampliación de plazo e informe a Planeamiento. 05/09/2025: Paquete 1: 2024-P0630 paso a producción en enero 2025. Paquete 2: Está presentando retrasos, se está realizando el 3er ciclo de pruebas en calidad de los procesos 11,12 y 17. El proceso 13 se encuentra en su 4to ciclo de pruebas. Se está planificado culminar en setiembre. Paquete 3: Se encuentra en Desarrollo. Está pendiente que el usuario gestione la ampliación de plazo e informe a Planeamiento. 25/07/2025: Paquete 1, 2024-P0630 paso a producción en enero 2025. Paquete 2, Está presentando retrasos, se está realizando el 3er ciclo de pruebas en calidad y está planificado culminar en agosto. Paquete 3: Se encuentra en Desarrollo. Está pendiente que el usuario gestione la ampliación e informe a Planeamiento. 17/07/2025: Paquete 1, 2024-P0630 paso a producción en enero 2025. Paquete 2, Está presentando retrasos, se está realizando el 2do ciclo de pruebas en calidad y está planificado culminar en agosto. Paquete 3: Se encuentra en Desarrollo. Está pendiente la ampliación de plazo por parte del área usuaria e informar a Planeamiento. 11/06/2025:Según la información enviada de Planeamiento en el mes de Mayo se precisa lo siguiente: Los atrasos se deben a incidencias técnicas presentadas en el proceso ATM (NCR) y de Atención a Solicitudes (perfiles y accesos). En relación a ATM´s no existe contrato vigente con NCR lo que dificulta la realización de pruebas en desarrollo. En cuanto atención de solicitudes, seguridad informática tuvo demoras en la asignación de perfiles y accesos. 03/06/2025: Según la información enviada de Planeamiento mediante correo respecto al proyecto en el mes de abril se tiene que: Debido a los inconvenientes técnicos con los que se cuenta en entorno de Desarrollo para los aplicativos de: Estados de cuenta de ahorro (ECAI) y contractuales con el proveedor NCR para Cajeros Automáticos, continúan los pendientes para pasar a entorno de certificación 2 de los 4 procesos que contempla el paquete número 02 (entregable 02). 07/05/2025: Según la información remitida por Planeamiento mediante correo: A nivel proveedor se esta avanzando con el desarrollo de los 4 bots esperando que se concreto lo que se indica en el párrafo anterior. Queda pendiente la asignación de las credenciales del journal NCR (consultas de ATM). 31/12/2024: Referente a RPA, el avance del primer entregable es de un 90%, se viene gestionando la certificación de los 3 procesos mencionados pertenecientes al primer paquete. No se contó con los requerimientos técnicos dentro de los plazos (TI) para cumplir con el hito 1 : instalación y configuración de la plataforma RPA. Por ello se presentara un control de cambios a fin de corregir y alinear el cronograma. 23/05/24 Mediante acta de comité estratégico de proyectos con fecha 06.05/24 se informa que se aprobó el control de cambios del proyecto , los usuarios deben formalizar el nuevo cronograma del proyecto y remitirlo a planeamiento. Validar que el contrato esté firmado y revisar cronograma, 1er entregable inicia el 07/06/24 (Desarrollo, QA, Producción). 03/05/2024 En proceso logístico para el otorgamiento de la Buena pro 05/04/24 Según correo remitido por MOrtiz, menciona la solicitud al área de Logística para ampliar el plazo de solución de consultas y observaciones e integración de bases del proceso de contratación. 21/03/24 Según cronograma ya estan por culminar el proceso logística. P&D agendará una reunión para revisar las siguientes actividades que involucra a TI y cuando se estarían iniciando. Pendiente que el usuario remita modelo de negocio para registrar el Proyecto en la demanda estrategica priorizada. 03/06/2025: Según la información enviada de Planeamiento mediante correo respecto al proyecto en el mes de abril se tiene que: Debido a los inconvenientes técnicos con los que se cuenta en entorno de Desarrollo para los aplicativos de: Estados de cuenta de ahorro (ECAI) y contractuales con el proveedor NCR para Cajeros Automáticos, continúan los pendientes para pasar a entorno de certificación 2 de los 4 procesos que contempla el paquete número 02 (entregable 02). 30/04/25: Del Paquete 1 Se cerro pase 2024-P0630 en el Clear Quest. Del Paquete 2 Se está presentando retrasos, aún se encuentra en Desarrollo y el área usuaria ha solicitado dividir los requerimientos a fin de pasar a Certificación los que ya se encuentre finalizados en desarrollo. La fecha que debió estar en PRODUCCION es el 21/04. Del paquete 3: El área usuaria ha solicitado el registro de los nuevos roles para avanzar con la automatización de los demás procesos. 31/03/25: Se emitió el MEMORANDO N° 00000016 - 2025-BN/2550 con el Informe 0004-2025-2550 correspondiente a la ejecución de los Entregables 1, 2 y 3 de la PRESTACION PRINCIPAL para el 1er pago. Del Paquete 1 que se pasó a Producción aún está pendiente el Cierre del pase en el Clear Quest. Del Paquete 2 Ambiente Desarrollo. Se está presentando retrasos: Proceso 11: Atención de solicitudes Reportaron que no había data en el STD, se explicó que debido a que la cuenta es nueva no tendría asignado ningún trámite y que lo mismo pasara en Producción, es decir cuando se cree la cuenta del Robot, posterior a ello podría visualizar tramites cuando se le derive o copie. También reportador que la versión en Desarrollo (v6) y el contratista tenía mapeado la versión (v5), Se explico que la versión actual es la V6, sin embargo, las opciones a los cuales ingresan es el mismo y no había cambiado. Proceso 12: Información ATM: Se estaba presentando incidentes en OnDemand y se indicó que deben de ejecutar a través del Internet Explorer. Pendiente las credenciales para NCR, se solicitó la generación en Certificación que se ejecutaría en el ambiente de Desarrollo. Proceso 13: Agentes Corresponsales. Para la 2da semana de abril ya estarían iniciando las pruebas con Usuario. Proceso 17: Certificados Depósitos Judiciales, expusieron que por la demora en las credenciales para la sesión de emulación se estaba retrasando. Se indico que utilizaran la cuenta de la sesión que usaron en las pruebas del 1er paquete. 21/03/25: Mediante correo del 21/03/25 de Planeamiento se indica: Ya se encuentra en producción el 100% del primer paquete de procesos. Ya se inicio el desarrollo del segundo entregable, con un avance del 25% (perfiles , accesos y seguridad). Por parte del contratista esta en proceso el levantamiento de información. 28/02/2025: Del paquete 1 (en producción). Para el proceso 1: El área usuaria había solicitado el ROL para la Gerencia de Operaciones el cual género que no se visualicen las tareas realizadas por el Robot y solicitaron la modificación del Rol hacia la Secc. Administración de Cuentas y Pagaduría. El proceso 8: El área usuaria reporto inconsistencia y luego solicitaron la reinstalación del Office el cual ya había sido realizado. A la espera que vuelvan a validar los 2 procesos. 17/02/2025 Se generaron las cuentas de para los Procesos 1 , 8 y el area usuaria indico los horarios para programar su ejecución en el ambiente de Producción e indico que el proceso 10 pasará a modo stand by. 31/01/2025 Está pendiente la generación de las cuentas de acceso de los Bots. En reunión con el área usuaria y se revisó la matriz aplicativos por procesos correspondiente al paquete 2 (4 procesos que se automatizaran) de los que se indicó que se aclaren donde se indica Host Emulación y no está el nombre de la aplicación y sobre la creación de carpetas compartidas ya que actualmente no se puede solicitar la creación de carpetas. 28/01/2025: Se certifico el primer paquete de automatizaciones de los 3 procesos el 24/01/. Se registrará en la demanda 2 requerimientos adicionales para atender otros 2 paquetes que comprenden (4 procesos y 3 procesos) 31/12/24: Referente a RPA, el avance del primer entregable es de un 90%, se viene gestionando la certificación de los 3 procesos mencionados pertenecientes al primer paquete. No se contó con los requerimientos técnicos dentro de los plazos (TI) para cumplir con el hito 1 : instalación y configuración de la plataforma RPA. Por ello se presentara un control de cambios a fin de corregir y alinear el cronograma. 16/12/24: Se registró en el Backlog 22/07/25: El dia de ayer se tuvo la reunion con el Proveedor para definir el perfil de accesos de la Plataforma del RPA y el dia de hoy Certificacion comenzo a validar que cada perfil de Accesos, de completar esta actividad, Certificacion solictra la validacion a traves del ISIM y con ello tener el acta de las pruebas de integracion del RPA con ISIM. Esta pendiente terminar las pruebas de las Alertas. De acuerdo a lo indicadp por Certificación ya tienen 2 actas firmadas de 2 de los bots, mañana tendran del 3er bot | AV34: ='Portafolio P&D'!B17 -> 0
A35: 31 | E35: Proyecto-Hijo | F35: Proyecto 31 | H35: G2 | AH35: No Aplica | AI35: 45809 | AK35: No aplica | AL35: No aplica | AM35: =IF(DemandaEstrateg_[[#This Row],[Tipo de Requerimiento]]="Proyecto",(DemandaEstrateg_[[#This Row],[% Avance ejecutado]]-DemandaEstrateg_[[#This Row],[% Avance Planificado]])/DemandaEstrateg_[[#This Row],[% Avance Planificado]],"No aplica") -> No aplica | AN35: =IF(DemandaEstrateg_[[#This Row],[Tipo de Requerimiento]]="Proyecto",(DemandaEstrateg_[[#This Row],[% Avance ejecutado]]-DemandaEstrateg_[[#This Row],[% Avance Planificado]])/DemandaEstrateg_[[#This Row],[% Avance Planificado]],"No aplica") -> No aplica | AQ35: 2025-II | AR35: Pendiente | AS35: 10. Descartado | AT35: =VLOOKUP(DemandaEstrateg_[[#This Row],[Estado TI]],#REF!,3,FALSE) -> #REF! | AU35: 05/09/2025: Se descarta el requerimiento, debido a que la integración será trabajado en el ID 2292. 13/02/25 En proceso de atención por el proveedor. 16//12/24 Se registro en el Backlog | AV35: No Aplica
A36: 32 | E36: Proyecto-Hijo | F36: Proyecto 32 | H36: G2 | AH36: 45645 | AI36: 45688 | AK36: No aplica | AL36: No aplica | AM36: =IF(DemandaEstrateg_[[#This Row],[Tipo de Requerimiento]]="Proyecto",(DemandaEstrateg_[[#This Row],[% Avance ejecutado]]-DemandaEstrateg_[[#This Row],[% Avance Planificado]])/DemandaEstrateg_[[#This Row],[% Avance Planificado]],"No aplica") -> No aplica | AN36: =IF(DemandaEstrateg_[[#This Row],[Tipo de Requerimiento]]="Proyecto",(DemandaEstrateg_[[#This Row],[% Avance ejecutado]]-DemandaEstrateg_[[#This Row],[% Avance Planificado]])/DemandaEstrateg_[[#This Row],[% Avance Planificado]],"No aplica") -> No aplica | AP36: 45992 | AQ36: 2025-IV | AR36: Aprobado | AS36: =VLOOKUP(DemandaEstrateg_[[#This Row],[Últ. Estado CQ 30.04]],#REF!,3,FALSE) -> #REF! | AT36: =VLOOKUP(DemandaEstrateg_[[#This Row],[Estado TI]],#REF!,3,FALSE) -> #REF! | AU36: 27/12/2024: Se registró en el Backlog como trámite Regularizado | AV36: No Aplica
A37: 33 | E37: Proyecto-Hijo | F37: Proyecto 33 | H37: G2 | AH37: 45686 | AI37: 45777 | AK37: No aplica | AL37: No aplica | AM37: =IF(DemandaEstrateg_[[#This Row],[Tipo de Requerimiento]]="Proyecto",(DemandaEstrateg_[[#This Row],[% Avance ejecutado]]-DemandaEstrateg_[[#This Row],[% Avance Planificado]])/DemandaEstrateg_[[#This Row],[% Avance Planificado]],"No aplica") -> No aplica | AN37: =IF(DemandaEstrateg_[[#This Row],[Tipo de Requerimiento]]="Proyecto",(DemandaEstrateg_[[#This Row],[% Avance ejecutado]]-DemandaEstrateg_[[#This Row],[% Avance Planificado]])/DemandaEstrateg_[[#This Row],[% Avance Planificado]],"No aplica") -> No aplica | AQ37: 2026-I | AR37: Rechazado | AS37: =VLOOKUP(DemandaEstrateg_[[#This Row],[Últ. Estado CQ 30.04]],#REF!,3,FALSE) -> #REF! | AT37: =VLOOKUP(DemandaEstrateg_[[#This Row],[Estado TI]],#REF!,3,FALSE) -> #REF! | AU37: 18/02/25: Se revisó con el equipo de construcción y se aprobó su formalización por Comité de Demanda 23/01/2025: Se registró en el Backlog, se creó trámite y se priorizó. | AV37: No Aplica
A38: 34 | E38: Proyecto-Hijo | F38: Proyecto 34 | H38: G2 | AH38: 45686 | AI38: 45748 | AK38: No aplica | AL38: No aplica | AM38: =IF(DemandaEstrateg_[[#This Row],[Tipo de Requerimiento]]="Proyecto",(DemandaEstrateg_[[#This Row],[% Avance ejecutado]]-DemandaEstrateg_[[#This Row],[% Avance Planificado]])/DemandaEstrateg_[[#This Row],[% Avance Planificado]],"No aplica") -> No aplica | AN38: =IF(DemandaEstrateg_[[#This Row],[Tipo de Requerimiento]]="Proyecto",(DemandaEstrateg_[[#This Row],[% Avance ejecutado]]-DemandaEstrateg_[[#This Row],[% Avance Planificado]])/DemandaEstrateg_[[#This Row],[% Avance Planificado]],"No aplica") -> No aplica | AQ38: 2026-I | AR38: Certificado | AS38: =VLOOKUP(DemandaEstrateg_[[#This Row],[Últ. Estado CQ 30.04]],#REF!,3,FALSE) -> #REF! | AT38: =VLOOKUP(DemandaEstrateg_[[#This Row],[Estado TI]],#REF!,3,FALSE) -> #REF! | AU38: 23/01/2025: Se registró en el Backlog y se creó trámite. Es requerimiento hijo de ID 2056. | AV38: No Aplica
A39: 35 | E39: Proyecto-Hijo | F39: Proyecto 35 | H39: G2 | AH39: 45686 | AI39: 45748 | AK39: No aplica | AL39: No aplica | AM39: =IF(DemandaEstrateg_[[#This Row],[Tipo de Requerimiento]]="Proyecto",(DemandaEstrateg_[[#This Row],[% Avance ejecutado]]-DemandaEstrateg_[[#This Row],[% Avance Planificado]])/DemandaEstrateg_[[#This Row],[% Avance Planificado]],"No aplica") -> No aplica | AN39: =IF(DemandaEstrateg_[[#This Row],[Tipo de Requerimiento]]="Proyecto",(DemandaEstrateg_[[#This Row],[% Avance ejecutado]]-DemandaEstrateg_[[#This Row],[% Avance Planificado]])/DemandaEstrateg_[[#This Row],[% Avance Planificado]],"No aplica") -> No aplica | AQ39: 2026-I | AR39: Certificado | AS39: =VLOOKUP(DemandaEstrateg_[[#This Row],[Últ. Estado CQ 30.04]],#REF!,3,FALSE) -> #REF! | AT39: =VLOOKUP(DemandaEstrateg_[[#This Row],[Estado TI]],#REF!,3,FALSE) -> #REF! | AU39: 23/01/2025: Se registró en el Backlog y se creó trámite. Es requerimiento hijo de ID 2056. | AV39: No Aplica
A40: 36 | E40: Proyecto-Hijo | F40: Proyecto 36 | H40: G2 | AH40: 45686 | AI40: 45748 | AK40: No aplica | AL40: No aplica | AM40: =IF(DemandaEstrateg_[[#This Row],[Tipo de Requerimiento]]="Proyecto",(DemandaEstrateg_[[#This Row],[% Avance ejecutado]]-DemandaEstrateg_[[#This Row],[% Avance Planificado]])/DemandaEstrateg_[[#This Row],[% Avance Planificado]],"No aplica") -> No aplica | AN40: =IF(DemandaEstrateg_[[#This Row],[Tipo de Requerimiento]]="Proyecto",(DemandaEstrateg_[[#This Row],[% Avance ejecutado]]-DemandaEstrateg_[[#This Row],[% Avance Planificado]])/DemandaEstrateg_[[#This Row],[% Avance Planificado]],"No aplica") -> No aplica | AQ40: 2026-I | AR40: Asignado | AS40: =VLOOKUP(DemandaEstrateg_[[#This Row],[Últ. Estado CQ 30.04]],#REF!,3,FALSE) -> #REF! | AT40: =VLOOKUP(DemandaEstrateg_[[#This Row],[Estado TI]],#REF!,3,FALSE) -> #REF! | AU40: 23/01/2025: Se registró en el Backlog y se creó trámite. Es requerimiento hijo de ID 2056. | AV40: No Aplica
A41: 37 | E41: Proyecto-Hijo | F41: Proyecto 37 | H41: G2 | AH41: 45791 | AI41: Pendiente | AK41: No aplica | AL41: No aplica | AM41: =IF(DemandaEstrateg_[[#This Row],[Tipo de Requerimiento]]="Proyecto",(DemandaEstrateg_[[#This Row],[% Avance ejecutado]]-DemandaEstrateg_[[#This Row],[% Avance Planificado]])/DemandaEstrateg_[[#This Row],[% Avance Planificado]],"No aplica") -> No aplica | AN41: =IF(DemandaEstrateg_[[#This Row],[Tipo de Requerimiento]]="Proyecto",(DemandaEstrateg_[[#This Row],[% Avance ejecutado]]-DemandaEstrateg_[[#This Row],[% Avance Planificado]])/DemandaEstrateg_[[#This Row],[% Avance Planificado]],"No aplica") -> No aplica | AQ41: 2026-I | AR41: Certificado | AS41: =VLOOKUP(DemandaEstrateg_[[#This Row],[Últ. Estado CQ 30.04]],#REF!,3,FALSE) -> #REF! | AT41: =VLOOKUP(DemandaEstrateg_[[#This Row],[Estado TI]],#REF!,3,FALSE) -> #REF! | AU41: En Pruebas en Desarrollo, pase a Calidad la primera semana de marzo. 29/01/25 Se requiere su registro en el Backlog y en la Demanda Estratégica, por ser parte del proyecto Cuenta DNI- Nuevas Funcionalidades. RQ hijo 2056 30/01/2025: Se registró en el Backlog y se creó trámite. | AV41: No Aplica
A42: 38 | E42: Proyecto-Hijo | F42: Proyecto 38 | H42: G2 | AH42: 45638 | AI42: 45823 | AK42: No aplica | AL42: No aplica | AM42: =IF(DemandaEstrateg_[[#This Row],[Tipo de Requerimiento]]="Proyecto",(DemandaEstrateg_[[#This Row],[% Avance ejecutado]]-DemandaEstrateg_[[#This Row],[% Avance Planificado]])/DemandaEstrateg_[[#This Row],[% Avance Planificado]],"No aplica") -> No aplica | AN42: =IF(DemandaEstrateg_[[#This Row],[Tipo de Requerimiento]]="Proyecto",(DemandaEstrateg_[[#This Row],[% Avance ejecutado]]-DemandaEstrateg_[[#This Row],[% Avance Planificado]])/DemandaEstrateg_[[#This Row],[% Avance Planificado]],"No aplica") -> No aplica | AP42: 46021 | AQ42: 2025-IV | AR42: Descartado | AS42: =VLOOKUP(DemandaEstrateg_[[#This Row],[Últ. Estado CQ 30.04]],#REF!,3,FALSE) -> #REF! | AT42: =VLOOKUP(DemandaEstrateg_[[#This Row],[Estado TI]],#REF!,3,FALSE) -> #REF! | AU42: 24/01/25 Se registra el paquete 3 como parte de la implementación del Proyecto de Robotización. | AV42: No Aplica
A43: 39 | E43: Proyecto-Hijo | F43: Proyecto 39 | H43: G2 | AH43: 45663 | AI43: 45777 | AK43: No aplica | AL43: No aplica | AM43: =IF(DemandaEstrateg_[[#This Row],[Tipo de Requerimiento]]="Proyecto",(DemandaEstrateg_[[#This Row],[% Avance ejecutado]]-DemandaEstrateg_[[#This Row],[% Avance Planificado]])/DemandaEstrateg_[[#This Row],[% Avance Planificado]],"No aplica") -> No aplica | AN43: =IF(DemandaEstrateg_[[#This Row],[Tipo de Requerimiento]]="Proyecto",(DemandaEstrateg_[[#This Row],[% Avance ejecutado]]-DemandaEstrateg_[[#This Row],[% Avance Planificado]])/DemandaEstrateg_[[#This Row],[% Avance Planificado]],"No aplica") -> No aplica | AQ43: 2026-I | AR43: Asignado | AS43: =VLOOKUP(DemandaEstrateg_[[#This Row],[Últ. Estado CQ 30.04]],#REF!,3,FALSE) -> #REF! | AT43: =VLOOKUP(DemandaEstrateg_[[#This Row],[Estado TI]],#REF!,3,FALSE) -> #REF! | AU43: 17/02/2025: Se registró en el Backlog como trámite Rugularizado. Es requerimiento hijo de 2056. | AV43: No Aplica
A44: 40 | E44: Proyecto-Hijo | F44: Proyecto 40 | H44: G2 | AH44: 45664 | AI44: 45735 | AJ44: 45735 | AK44: No aplica | AL44: No aplica | AM44: =IF(DemandaEstrateg_[[#This Row],[Tipo de Requerimiento]]="Proyecto",(DemandaEstrateg_[[#This Row],[% Avance ejecutado]]-DemandaEstrateg_[[#This Row],[% Avance Planificado]])/DemandaEstrateg_[[#This Row],[% Avance Planificado]],"No aplica") -> No aplica | AN44: =IF(DemandaEstrateg_[[#This Row],[Tipo de Requerimiento]]="Proyecto",(DemandaEstrateg_[[#This Row],[% Avance ejecutado]]-DemandaEstrateg_[[#This Row],[% Avance Planificado]])/DemandaEstrateg_[[#This Row],[% Avance Planificado]],"No aplica") -> No aplica | AP44: 45717 | AQ44: 2025-I | AR44: Transitorio_Regularizado | AS44: =VLOOKUP(DemandaEstrateg_[[#This Row],[Últ. Estado CQ 30.04]],#REF!,3,FALSE) -> #REF! | AT44: =VLOOKUP(DemandaEstrateg_[[#This Row],[Estado TI]],#REF!,3,FALSE) -> #REF! | AU44: 17/02/2025: Se registró en el Backlog como trámite Es requerimiento hijo de 2487. | AV44: No Aplica
A45: 41 | E45: Proyecto-Hijo | F45: Proyecto 41 | H45: G2 | AH45: 45663 | AI45: 45747 | AK45: No aplica | AL45: No aplica | AM45: =IF(DemandaEstrateg_[[#This Row],[Tipo de Requerimiento]]="Proyecto",(DemandaEstrateg_[[#This Row],[% Avance ejecutado]]-DemandaEstrateg_[[#This Row],[% Avance Planificado]])/DemandaEstrateg_[[#This Row],[% Avance Planificado]],"No aplica") -> No aplica | AN45: =IF(DemandaEstrateg_[[#This Row],[Tipo de Requerimiento]]="Proyecto",(DemandaEstrateg_[[#This Row],[% Avance ejecutado]]-DemandaEstrateg_[[#This Row],[% Avance Planificado]])/DemandaEstrateg_[[#This Row],[% Avance Planificado]],"No aplica") -> No aplica | AP45: 46023 | AQ45: 2026-I | AR45: Asignado | AS45: =VLOOKUP(DemandaEstrateg_[[#This Row],[Últ. Estado CQ 30.04]],#REF!,3,FALSE) -> #REF! | AT45: =VLOOKUP(DemandaEstrateg_[[#This Row],[Estado TI]],#REF!,3,FALSE) -> #REF! | AU45: 17/02/2025: Se registró en el Backlog como trámite Es requerimiento hijo de 2487. | AV45: No Aplica
A46: 42 | E46: Proyecto-Hijo | F46: Proyecto 42 | H46: G2 | AH46: 45663 | AI46: 45747 | AK46: No aplica | AL46: No aplica | AM46: =IF(DemandaEstrateg_[[#This Row],[Tipo de Requerimiento]]="Proyecto",(DemandaEstrateg_[[#This Row],[% Avance ejecutado]]-DemandaEstrateg_[[#This Row],[% Avance Planificado]])/DemandaEstrateg_[[#This Row],[% Avance Planificado]],"No aplica") -> No aplica | AN46: =IF(DemandaEstrateg_[[#This Row],[Tipo de Requerimiento]]="Proyecto",(DemandaEstrateg_[[#This Row],[% Avance ejecutado]]-DemandaEstrateg_[[#This Row],[% Avance Planificado]])/DemandaEstrateg_[[#This Row],[% Avance Planificado]],"No aplica") -> No aplica | AP46: 46023 | AQ46: 2026-I | AR46: Asignado | AS46: =VLOOKUP(DemandaEstrateg_[[#This Row],[Últ. Estado CQ 30.04]],#REF!,3,FALSE) -> #REF! | AT46: =VLOOKUP(DemandaEstrateg_[[#This Row],[Estado TI]],#REF!,3,FALSE) -> #REF! | AU46: 17/02/2025: Se registró en el Backlog como trámite Es requerimiento hijo de 2487. | AV46: No Aplica
A47: 43 | E47: Proyecto-Hijo | F47: Proyecto 43 | H47: G2 | AH47: 45691 | AI47: 45747 | AK47: No aplica | AL47: No aplica | AM47: =IF(DemandaEstrateg_[[#This Row],[Tipo de Requerimiento]]="Proyecto",(DemandaEstrateg_[[#This Row],[% Avance ejecutado]]-DemandaEstrateg_[[#This Row],[% Avance Planificado]])/DemandaEstrateg_[[#This Row],[% Avance Planificado]],"No aplica") -> No aplica | AN47: =IF(DemandaEstrateg_[[#This Row],[Tipo de Requerimiento]]="Proyecto",(DemandaEstrateg_[[#This Row],[% Avance ejecutado]]-DemandaEstrateg_[[#This Row],[% Avance Planificado]])/DemandaEstrateg_[[#This Row],[% Avance Planificado]],"No aplica") -> No aplica | AP47: 46023 | AQ47: 2026-I | AR47: Asignado | AS47: =VLOOKUP(DemandaEstrateg_[[#This Row],[Últ. Estado CQ 30.04]],#REF!,3,FALSE) -> #REF! | AT47: =VLOOKUP(DemandaEstrateg_[[#This Row],[Estado TI]],#REF!,3,FALSE) -> #REF! | AU47: 17/02/2025: Se registró en el Backlog como trámite Es requerimiento hijo de 2487. | AV47: No Aplica
A48: 44 | E48: Proyecto | F48: Proyecto 44 | H48: G2 | AH48: ='Portafolio P&D'!Y37 -> 0 | AI48: ='Portafolio P&D'!Z37 -> 0 | AK48: ='Portafolio P&D'!AA37 -> 1 | AL48: ='Portafolio P&D'!AB37 -> 1 | AM48: =IF(DemandaEstrateg_[[#This Row],[Tipo de Requerimiento]]="Proyecto",(DemandaEstrateg_[[#This Row],[% Avance ejecutado]]-DemandaEstrateg_[[#This Row],[% Avance Planificado]])/DemandaEstrateg_[[#This Row],[% Avance Planificado]],"No aplica") -> 0 | AN48: =IF(DemandaEstrateg_[[#This Row],[Tipo de Requerimiento]]="Proyecto",(DemandaEstrateg_[[#This Row],[% Avance ejecutado]]-DemandaEstrateg_[[#This Row],[% Avance Planificado]])/DemandaEstrateg_[[#This Row],[% Avance Planificado]],"No aplica") -> 0 | AP48: 45962 | AQ48: 2025-IV | AR48: 09. Finalizado | AS48: 09. Finalizado | AT48: =VLOOKUP(DemandaEstrateg_[[#This Row],[Estado TI]],#REF!,3,FALSE) -> #REF! | AU48: 06/10/2025: El pase de Apertura en línea 2024-M0098 paso a producción en setiembre 2025. El pase Apertura masiva Batch: 2024-M0218 paso a producción en setiembre 2025. La Tabla de Control 2024-M0465 Certificado en julio y la Mejora de la Tabla de Control: 2025-M0523 Certificado en setiembre. Pase a Producción en octubre. El Tarifario 2025-M0308 se encuentra en pruebas en Calidad de los canales WEB, Ventanilla, APP, ATM, se certificará el 17/10. Debido a que se priorizo el pase del nuevo tarifario en el canal de Agente corresponsales, posterior a este despliegue se continuará con la implementación del cobro de comisiones en Cuenta Digital para este canal. Tarifario Agente se tiene como compromiso iniciar el 6/10/ y finalizar 28/11. Está pendiente que el usuario gestione la ampliación de plazo e informe a Planeamiento. 05/09/2025: El pase de Apertura en línea se desplego en Producción. Pendiente la regularización del estado del pase. El pase Apertura masiva Batch: Certificado el 01/09. El Tarifario se encuentra en pruebas en Calidad de los canales WEB, Ventanilla, APP, ATM. La Tabla de Control Certificado el 14/07. La Mejora de la Tabla de Control: En Desarrollo. Está pasando a Certificación la 1era semana de Setiembre. Debido a que se priorizo el pase del nuevo tarifario en el canal de Agente corresponsales, posterior a este despliegue se continuará con la implementación del cobro de comisiones en Cuenta Digital para este canal. 25/07/2025: El pase de Apertura en línea se desplego en Producción. Pendiente la regularización del estado del pase. El pase Apertura masiva Batch paso a Certificación para su atención. El Tarifario se encuentra en pruebas en Desarrollo los canales WEB, Ventanilla, APP y se encuentran en proceso de desarrollo los canales ATM y Agentes. La Tabla de Control se encuentra Certificado. 17/07/2025: El pase de Apertura en línea se desplego en Producción. Pendiente la regularización del estado del pase. El pase Apertura masiva Batch según lo informado por desarrollo estarían pasando a Certificación la 4ta semana de julio. El Tarifario se encuentra en pruebas en Desarrollo los canales WEB, Ventanilla, APP y se encuentran en proceso de desarrollo los canales ATM y Agentes. La Tabla de Control se encuentra Certificado. 11/06/2025:Según la información enviada de Planeamiento en el mes de Mayo se precisa lo siguiente: Realizando pruebas de proceso de apertura masiva Batch de Cuentas Digitales BN (Código 2024-M0218) en el ambiente de certificación. En relación al entregable “Tabla de Control de Calidad” (Código 2024-M0465), este también se encuentra en pruebas dentro del entorno de certificación. Se concluyó la definición de estrategia de migración, realizado por la Gerencia de Operaciones, Banca Digital y la Subgerencia de Construcción de Aplicaciones. 03/06/2025: Según la información enviada de Planeamiento mediante correo respecto al proyecto en el mes de abril se tiene que: Se logró concluir con las pruebas en ambiente de desarrollo para el proceso de apertura de Cta. Digital BN en Línea (individual y masivo - 2024-M0098). Se han realizado las reuniones de entendimiento con la Sección Control de Calidad, Sección Sistemas Bancarios y la Sección Arquitectura de Datos y Aplicaciones. Se encuentra en proceso las pruebas en ambiente de certificación con el apoyo del área usuaria Sección Apertura de Cuentas. Se concluyó las pruebas en ambiente de desarrollo para el proceso de Apertura masiva batch de Cta. Digital BN (2024-M0218), se encuentra en proceso las reuniones de entendimiento con la Sección Calidad para iniciar las pruebas en ambiente de certificación. La Sección Control de Calidad realizó observaciones al proceso Tabla de Control calidad (2024-M0465), las mismas que fueron revisada y subsanadas por la l Sección Servicios Bancarios. Se están preparando para indicar las pruebas en certificación Se establecieron los lineamientos para la estrategia de migración, en conjunto la Gerencia de Operaciones, banca Digital y la Subgerencia de Construcción de Aplicaciones. 07/05/2025: Según la información remitida por Planeamiento mediante correo: A nivel tareas, actualmente se encuentra en la Etapa de Implementación del Proyecto. Continúan las pruebas en desarrollo con la participación de los usuario (Secc. Apertura de Cuentas) y la fabrica de SW del BN, encargada de los desarrollo, para el componente 2024-M0098 - Adecuación proceso de apertura de cta. DNI en Linea (individual y masivo ), actividad que presenta atraso y perjudica el avance de otras actividades (pruebas en canales). Las pruebas con los canales de atención se encuentra en pausa, hasta que Continúan las pruebas en desarrollo con la participación de los usuario (Secc. Apertura de Cuentas) y la fabrica de SW del BN, encargada de los desarrollo, para el componente 2024-M0218-Apertura masiva batch. Se viene coordinando las actividades previas para iniciar la pruebas en certificación, como es la carga inicial de los DNI's, para el componente 2024-M0465-Tabla de Control. 03/02/2025 Este proyecto tiene los mantenimientos: 2024-M0098: Adecuación Proceso de Apertura de CTA DNI en Linea (individualy masivo) y funcionamiento en canales de atencion: Se encuentra en pruebas con usuario Ambiente de Desarrollo 2024-M0218: Apertura Masiva batch: Se encuentra en pruebas con usuario Ambiente Desarrollo 2024-M0645: Tabla de Control: El 05/02 Inician las pruebas con usuario Ambiente Desarrollo. 31/01/25: Aprobado en comité de Dic24. Se encuentra en proceso de Desarrollo. 03/06/2025: Según la información enviada de Planeamiento mediante correo respecto al proyecto en el mes de abril se tiene que: Se logró concluir con las pruebas en ambiente de desarrollo para el proceso de apertura de Cta. Digital BN en Línea (individual y masivo - 2024-M0098). Se han realizado las reuniones de entendimiento con la Sección Control de Calidad, Sección Sistemas Bancarios y la Sección Arquitectura de Datos y Aplicaciones. Se encuentra en proceso las pruebas en ambiente de certificación con el apoyo del área usuaria Sección Apertura de Cuentas. Se concluyó las pruebas en ambiente de desarrollo para el proceso de Apertura masiva batch de Cta. Digital BN (2024-M0218), se encuentra en proceso las reuniones de entendimiento con la Sección Calidad para iniciar las pruebas en ambiente de certificación. La Sección Control de Calidad realizó observaciones al proceso Tabla de Control calidad (2024-M0465), las mismas que fueron revisada y subsanadas por la l Sección Servicios Bancarios. Se están preparando para indicar las pruebas en certificación Se establecieron los lineamientos para la estrategia de migración, en conjunto la Gerencia de Operaciones, banca Digital y la Subgerencia de Construcción de Aplicaciones. 30/04/2025 El pase de Apertura en línea paso a Certificación el 15.04 (fecha planificada 06.05). Están realizando el despliegue y elaborando los casos de prueba. El pase Apertura masiva Batch según lo informado por desarrollo deberá de pasar posterior al pase de apertura en línea. El 25/04 se tuvo reunión con Finanzas a fin de realizar consultas acerca del Tarifario para Cuenta Digital y el 29/04 Finanzas confirmo la actualización del tarifario en Desarrollo y se dio el inicio a las pruebas unitaria. Paso a Certificación el mantenimiento de Tabla de Control el 30/04. 31/03/2025:Para la Tabla de Control se solicitó al área usuaria los DNIs para la carga inicial, con ello Calidad podrá iniciar las pruebas. Se implemento los requerimientos solicitados por el área usuaria y ya encuentra en pruebas de usuario en el ambiente de Desarrollo para la Apertura de cuenta en Línea y se encuentra cerrando los el desarrollo de los requerimientos para Aperturas de cuentas en Batch. Cabe indicar que debido a pase PARTIDOS POLITICOS (2024-M0550 MN: Apertura de Cuentas Corrientes Partidos Políticos) se priorizo este pase el cual afecto la implementación de los requerimientos solicitados 21/03/25: Mediante correo del 21/03/25 de Planeamiento se indica: La primera semana de febrero de aprobó el Tarifario para Cuenta Digital BN trabajada en conjunto con la Subgerencia de Estudios Económicos y Financieros | Gerencia Finanzas y Tesorería; así mismo trasladó Oficina de proyecto de TI para el registro correspondiente e inicio de su inclusión en la construcción Cuenta Digital BN. 28/02/25: El usuario realizo la prueba en el ambiente de desarrollo de la Tabla de Control y dio su conformidad. El área usuaria solicito nuevos requerimientos funcionales que serán asociados a los requerimientos de Apertura de cuentas en Línea y Apertura de cuentas Batch 28/02/2025: Se registró el Proyecto Cuenta Digital en el Portafolio de Demanda Estratégica. 28/02/25: Se registra el Proyecto Cuenta Digital BN en el Backlog. | AV48: ='Portafolio P&D'!B37 -> 0
A49: 45 | E49: Proyecto | F49: Proyecto 45 | H49: G2 | AH49: 45600 | AI49: 45518 | AK49: 0.87 | AL49: 0.72 | AM49: =IF(DemandaEstrateg_[[#This Row],[Tipo de Requerimiento]]="Proyecto",(DemandaEstrateg_[[#This Row],[% Avance ejecutado]]-DemandaEstrateg_[[#This Row],[% Avance Planificado]])/DemandaEstrateg_[[#This Row],[% Avance Planificado]],"No aplica") -> -0.17241379 | AN49: =IF(DemandaEstrateg_[[#This Row],[Tipo de Requerimiento]]="Proyecto",(DemandaEstrateg_[[#This Row],[% Avance ejecutado]]-DemandaEstrateg_[[#This Row],[% Avance Planificado]])/DemandaEstrateg_[[#This Row],[% Avance Planificado]],"No aplica") -> -0.17241379 | AP49: 46248 | AQ49: 2026-III | AR49: Pendiente | AS49: 03. En Desarrollo | AT49: =VLOOKUP(DemandaEstrateg_[[#This Row],[Estado TI]],#REF!,3,FALSE) -> #REF! | AU49: 01/12/2025: El proyecto se dividio en dos Fases, Fase I - Sistema SIAF del MEF - BCRP/LBTR (Fecha Fin 30-01-2026), Fase II Sistema SIAF del MEF - Operaciones de Pagaduría del Estado MEF-SIAF y SUNAT – Servicios Adicionales (Fecha Fin 14-08-2026) El proyecto se encuentra en la etapa de Pruebas en Desarrollo (Fase I), previo al pase de pruebas en ambiente de Certificacion. Las pruebas en el ambiente de Certificacion debieron comenzar el 03 de Noviembre del 2025, por lo tanto el proyecto con fecha de corte al 4 de Diciembre,se encuentra retrasado en un mes calendario. Esta pendiente para concluir en esta fase : - Actualizacion de documentacion requerida por el area de Control de Calidad, acerca de procedimientos en la Guias de Implantacion y formatos requeridos conforme a procedimientos del Banco - Resolucion de pruebas de vulnerabilidades, coordinacion de cuentas principal e integradora, perfiles de acceso, integracion con ISIM - Documentacion Guia para la Creacion de un nuevo CICS para el ambiente de Certifcacion Se esta realizando acciones y reuniones que permitan - Alinear con control de calidad los entregables pendientes, cerrar las observaciones de seguridad,y asegurar la disponibilidad del ambiente de Certificacion y gestionar algun bloqueo en las tareas En cuanto al cronograma, se espera recuperar la desviacion identificada de 3% y normalizar los plazos comprometidos, priorizando actividades, acelerando validaciones en certificacion, y aumentando la frecuencia del seguimiento al proyecto 07/10/2025: Se está realizando pruebas en Desarrollo y se tiene planificado culminar en octubre. Las pruebas en el ambiente de Certificación inician en noviembre y finaliza el 16.01.2026. Está pendiente que el usuario gestione la ampliación de plazo e informe a Planeamiento. 05/09/2025: Con fecha 14 de agosto de 2025 se remitió al área usuaria los nuevos plazos considerando los adicionales como las mejoras con LBTR, así como Contabilidad del BN. A la fecha no se ha recibido respuesta respecto a ello. De acuerdo a lo informado por Planeamiento el proyecto se encuentra al 82% de cumplimiento. La fecha fin del proyecto tiene planificado terminar en marzo 2026. 25/07/2025: Se ha creado un nuevo CCIS para Pagaduría que es independiente a Interoperabilidad, se están realizando pruebas internas y está pendiente la prueba integral. De acuerdo con el TDR la Fase I debió finalizar en Jun_2025, sin embargo, el plazo se está ampliando y se tiene planificado culminar la Fase I en Ago_2025. Pendiente la solicitud de ampliación de plazo por parte del área usuaria e informar a planeamiento. 17/07/2025: Se ha realizado pruebas internas y está pendiente la prueba integral. El equipo técnico realizo una evaluación y debido a que la solución de Pagaduría debe de soportar una sobre carga, se ha implementado un nuevo CICS idéntico a Interoperabilidad que es independiente. De acuerdo con el TDR la Fase I debió finalizar en Jun_2025, sin embargo, el plazo se está ampliando y se tiene planificado culminar la Fase I en Ago_2025. Pendiente la solicitud de ampliación de plazo por parte del área usuaria e informar a planeamiento. 11/06/2025:Según la información enviada de Planeamiento en el mes de Mayo se precisa lo siguiente: Nos encontramos en la etapa de Desarrollo y Construcción la fase I del proyecto de Pagaduría: Integración LBTR-SIAF-BCRP. En relación a las pruebas de desarrollo (Desarrollo Novatronic y Banco), además se ha comprometido la participación del MEF y BCRP, lo que implica pruebas de conectividad para este mes y en el mes de junio se realizarian las pruebas integrales entre el Banco, MEF y BCRP. Novatronic se atraso en el desarrollo de sus interfases, para el mes de mayo ha acelerado el desarrollo de sus aplicaciones. 03/06/2025: Según la información enviada de Planeamiento mediante correo respecto al proyecto en el mes de abril se tiene que: Se ha finalizado la revisión de estructuras de interfaces de todos los flujos (para las fases I y II) Se han realizado coordinaciones con el BCRP a fin de revisar el proceso de conciliación que realizan las entidades, asimismo mediante correo electrónico (02.05.2025) se ha solicitado a dicha entidad asegurar su participación en las pruebas de conectividad e intercambio de información para la ejecución de las pruebas preliminares a iniciarse en la segunda quincena de mayo del presente. Con carta Nro. 005-2025 BN3100 (29.04.2025) se comunicó a la Dirección General del Tesoro Público el estado del desarrollo que viene realizando el Banco referente a la implementación del proyecto de pagaduría para la interconexión entre los sistemas transaccionales del SIAF y LBTR del BCRP; solicitando la cooperación de su equipo técnico en las pruebas de conectividad e intercambio de información para las pruebas preliminares a realizarse en la 2da quincena de mayo del 2025. 07/05/2025: Según la información remitida por Planeamiento mediante correo: A nivel tareas, actualmente se encuentra en la Etapa de Implementación del Proyecto. - Se ha culminado la revisión de flujos y esquemas de la fase I (Integración SIAF-BN-LBTR), está pendiente de que TI confirme el desarrollo de la interfaz Host. - Se ha coordinado con TI (H. Zevallos) la asignación de un recurso adicional (Nestor Acha), que apoye a E. Cárdenas con la implementación de la TXn HOST (cargo, abono, extorno, consulta) requerido por Novatronic para la integración con el SIAF; asimismo la asignación de otro recurso para el proceso de Conciliación. - Se encuentra en la actividad de habilitación de ambiente y servidores para las pruebas funcionales de la fase I, está pendiente de que Novatronic valide la conectividad (Al mes de Abril ya se concluyo la actividad). - Pendiente una reunión entre Novatronic y TI del BN a fin de revisar el flujo de la fase II (al mes de abril ya se concluyó la actividad). 08/04/2025: Mediante el Acta de Reuniòn 01-2025 el Comitè de Proyectos aprobò el proyecto. 17/02/25 Revisión del Flujo 1 - MEF LBTR: Se remitio la informacion solictada por Novatronic. Avance: 100% . Análisis y Diseño 50% (Novatronic) Proporcionar las EETT de Txn del Host BN 50% Generacion de Archivos y Casos de Pruebas MEF/SUNAT - BN (Sunat no cuenta con la infor.) 50% 31/01/25: Aprobado en comité de Ene25. En reuniones técnicas con el proveedor. 20/05/2024 Mediante correo de Jorge Lavalle se notifica laentrega de la propuesta comercial y los TDRs para su validación,se genera reunion para su revisión el 22-05. 07/05/2024 Mediante correo se hace envìo de los TDRs del proyecto. 30/04/2024 Mediante correo de Antonio Luyo se entrega el documento de las TDr s del proyecto a Martin Nicho, para luego ser remitidas a Jorge Lavalle y Marco Ortiz. 29/04/2024 Mediante correo de Jorge Lavalle se pide la validación de los TDRs del proyecto 25/04/2024 Por correo de Martin Nicho se pide la asistencia para dar respuesta al usuario sobre los requerimientos del proyecto, se establece un orden de prioridad para la atención de los mismo: Seguridad informática, Arquitectura, Construcción y Producción. Se espera la formalización de la inscripción del proyecto a la lista de proyectos estratégicos por Jorge Lavalle. 22/04/2024 Con correo remitido por Jorge Lavalle se pone en consideración la priorización de los TDRs, una vez teniendo los TDRs finales finaliza la revisión del contrato e inicia la formalización. Se hace llegar el contrato, propuesta y, esquema general y técnico de solución. 03/06/2025: Según la información enviada de Planeamiento mediante correo respecto al proyecto en el mes de abril se tiene que: Se ha finalizado la revisión de estructuras de interfaces de todos los flujos (para las fases I y II) Se han realizado coordinaciones con el BCRP a fin de revisar el proceso de conciliación que realizan las entidades, asimismo mediante correo electrónico (02.05.2025) se ha solicitado a dicha entidad asegurar su participación en las pruebas de conectividad e intercambio de información para la ejecución de las pruebas preliminares a iniciarse en la segunda quincena de mayo del presente. Con carta Nro. 005-2025 BN3100 (29.04.2025) se comunicó a la Dirección General del Tesoro Público el estado del desarrollo que viene realizando el Banco referente a la implementación del proyecto de pagaduría para la interconexión entre los sistemas transaccionales del SIAF y LBTR del BCRP; solicitando la cooperación de su equipo técnico en las pruebas de conectividad e intercambio de información para las pruebas preliminares a realizarse en la 2da quincena de mayo del 2025. 30/04/25: El 14/04 Se tuvo reunión presencial con SUNAT y se indicó que esperarían a más tardar 1 mes para que informen su participación. El 15/04 Se tuvo reunión con el BCRP y se informó que las pruebas preliminares iniciarían el 15.05. Se tuvo reuniones técnicas entre el BN y Novatronic. De acuerdo con el TdR se presenta retraso, la Fase I finaliza en Jun_2025 sin embargo por demora del MEF se amplio el plazo y se tiene planificado culminar la Fase I el Ago_2025. 31/03/25 Se han realizado reuniones entre el BN, Novatronic y el área usuaria a fin de revisar las Especificaciones Técnicas. El área de TI a remitido correos respondiendo las consultas realizadas por el contratista. El avance de las actividades es la siguiente: Revisión de esquemas, flujos y otros (requisito) – Novatronic – Se culmino Habilitar los ambientes de prueba (servidores, software base, enlaces, conexiones FTP con MEF, pruebas de funcionamiento) – En proceso. Implementación - Actividades de Novatronic: análisis y diseño de las EETT, Sistema de Pagaduría (proceso de lotes), Sistema Orquestador, integración sistema LBTR (adecuaciones de interfaces), pruebas integrales – En proceso. Implementación - Actividades del BN (Host MF): generación de archivos y casos de prueba, validación de las EETT (Host), pruebas internas, validación de archivos de conciliación, generación de archivos y pruebas internas – En proceso. 28/02/2025: El avance de las actividades es la siguiente: El BN envió a Novatronic los archivos para la revisión del Flujo 1 (MEF-LBTR) (100%). Flujo 7 SUNAT (50%) Habilitar Servidor y software base (30%) El Análisis y Diseño - Novatronic (80%). Las especificaciones técnicas de las Transacciones de Host-BN (80%). Generación de Archivos y Casos de Pruebas (50%). 28/02/2025: Se registró en el Portafolio de Demanda Estratégica. 28/02/25 Se registra el Proyecto: Implementación del Sistema de Procesamiento de Operaciones de Pagaduría del Estado MEF-SIAF y SUNAT | AV49: ='Portafolio P&D'!B36 -> 0
A50: 46 | E50: Proyecto-Hijo | F50: Proyecto 46 | H50: G2 | AK50: ='Portafolio P&D'!AA8 -> 0.87 | AL50: ='Portafolio P&D'!AB8 -> 0.84 | AM50: =IF(DemandaEstrateg_[[#This Row],[Tipo de Requerimiento]]="Proyecto",(DemandaEstrateg_[[#This Row],[% Avance ejecutado]]-DemandaEstrateg_[[#This Row],[% Avance Planificado]])/DemandaEstrateg_[[#This Row],[% Avance Planificado]],"No aplica") -> No aplica | AN50: =IF(DemandaEstrateg_[[#This Row],[Tipo de Requerimiento]]="Proyecto",(DemandaEstrateg_[[#This Row],[% Avance ejecutado]]-DemandaEstrateg_[[#This Row],[% Avance Planificado]])/DemandaEstrateg_[[#This Row],[% Avance Planificado]],"No aplica") -> No aplica | AR50: Pendiente | AS50: 03. En Desarrollo | AT50: =VLOOKUP(DemandaEstrateg_[[#This Row],[Estado TI]],#REF!,3,FALSE) -> #REF! | AU50: 30/12/2025:Se debe enviar a la Gerencia de Planeamiento y Control de Gestión el cronograma detallado del entregable Configuración de enero para que puedan realizar un mayor seguimiento de las actividades que involucra este entregable. Es así que la gerencia de Banca Digital señala que ya tiene el cronograma; sin embargo, se está procediendo a ser firmado por todos los participantes. 21/03/2025: Se solicita registro en el Backlog. Se coordinará con el equipo técnico para su atención respectiva. | AV50: No Aplica
A51: 47 | E51: Proyecto-Hijo | F51: Proyecto 47 | H51: G2 | AH51: 45721 | AI51: Pendiente | AK51: No aplica | AL51: No aplica | AM51: =IF(DemandaEstrateg_[[#This Row],[Tipo de Requerimiento]]="Proyecto",(DemandaEstrateg_[[#This Row],[% Avance ejecutado]]-DemandaEstrateg_[[#This Row],[% Avance Planificado]])/DemandaEstrateg_[[#This Row],[% Avance Planificado]],"No aplica") -> No aplica | AN51: =IF(DemandaEstrateg_[[#This Row],[Tipo de Requerimiento]]="Proyecto",(DemandaEstrateg_[[#This Row],[% Avance ejecutado]]-DemandaEstrateg_[[#This Row],[% Avance Planificado]])/DemandaEstrateg_[[#This Row],[% Avance Planificado]],"No aplica") -> No aplica | AQ51: 2026-I | AR51: Certificado | AS51: =VLOOKUP(DemandaEstrateg_[[#This Row],[Últ. Estado CQ 30.04]],#REF!,3,FALSE) -> #REF! | AT51: =VLOOKUP(DemandaEstrateg_[[#This Row],[Estado TI]],#REF!,3,FALSE) -> #REF! | AU51: 24/03/25: Se regularizó registro en Backlog | AV51: No Aplica
A52: 48 | E52: Proyecto-Hijo | F52: Proyecto 48 | H52: G2 | AH52: 45705 | AI52: 45805 | AK52: No aplica | AL52: No aplica | AM52: =IF(DemandaEstrateg_[[#This Row],[Tipo de Requerimiento]]="Proyecto",(DemandaEstrateg_[[#This Row],[% Avance ejecutado]]-DemandaEstrateg_[[#This Row],[% Avance Planificado]])/DemandaEstrateg_[[#This Row],[% Avance Planificado]],"No aplica") -> No aplica | AN52: =IF(DemandaEstrateg_[[#This Row],[Tipo de Requerimiento]]="Proyecto",(DemandaEstrateg_[[#This Row],[% Avance ejecutado]]-DemandaEstrateg_[[#This Row],[% Avance Planificado]])/DemandaEstrateg_[[#This Row],[% Avance Planificado]],"No aplica") -> No aplica | AQ52: 2025-II | AR52: Descartado | AS52: =VLOOKUP(DemandaEstrateg_[[#This Row],[Últ. Estado CQ 30.04]],#REF!,3,FALSE) -> #REF! | AT52: =VLOOKUP(DemandaEstrateg_[[#This Row],[Estado TI]],#REF!,3,FALSE) -> #REF! | AU52: 24/03/25: Se regularizó registro en Backlog | AV52: No Aplica
A53: 49 | E53: Proyecto-Hijo | F53: Proyecto 49 | H53: G2 | AH53: 45624 | AI53: 45727 | AJ53: 45727 | AK53: No aplica | AL53: No aplica | AM53: =IF(DemandaEstrateg_[[#This Row],[Tipo de Requerimiento]]="Proyecto",(DemandaEstrateg_[[#This Row],[% Avance ejecutado]]-DemandaEstrateg_[[#This Row],[% Avance Planificado]])/DemandaEstrateg_[[#This Row],[% Avance Planificado]],"No aplica") -> No aplica | AN53: =IF(DemandaEstrateg_[[#This Row],[Tipo de Requerimiento]]="Proyecto",(DemandaEstrateg_[[#This Row],[% Avance ejecutado]]-DemandaEstrateg_[[#This Row],[% Avance Planificado]])/DemandaEstrateg_[[#This Row],[% Avance Planificado]],"No aplica") -> No aplica | AP53: 45717 | AQ53: 2025-I | AR53: Transitorio_Regularizado | AS53: =VLOOKUP(DemandaEstrateg_[[#This Row],[Últ. Estado CQ 30.04]],#REF!,3,FALSE) -> #REF! | AT53: =VLOOKUP(DemandaEstrateg_[[#This Row],[Estado TI]],#REF!,3,FALSE) -> #REF! | AU53: 24/03/25: Se regularizó registro en Backlog. | AV53: No Aplica
A54: 50 | E54: Proyecto-Hijo | F54: Proyecto 50 | H54: G2 | AH54: Pendiente | AI54: 46037 | AK54: No aplica | AL54: No aplica | AM54: =IF(DemandaEstrateg_[[#This Row],[Tipo de Requerimiento]]="Proyecto",(DemandaEstrateg_[[#This Row],[% Avance ejecutado]]-DemandaEstrateg_[[#This Row],[% Avance Planificado]])/DemandaEstrateg_[[#This Row],[% Avance Planificado]],"No aplica") -> No aplica | AN54: =IF(DemandaEstrateg_[[#This Row],[Tipo de Requerimiento]]="Proyecto",(DemandaEstrateg_[[#This Row],[% Avance ejecutado]]-DemandaEstrateg_[[#This Row],[% Avance Planificado]])/DemandaEstrateg_[[#This Row],[% Avance Planificado]],"No aplica") -> No aplica | AP54: 46248 | AQ54: 2026-III | AR54: Pendiente | AS54: 01. Registrado | AT54: =VLOOKUP(DemandaEstrateg_[[#This Row],[Estado TI]],#REF!,3,FALSE) -> #REF! | AU54: 02/04/25 Se registra el Proyecto: FASE 2: Implementación del Sistema de Procesamiento de Operaciones de Pagaduría del Estado MEF-SIAF y SUNAT – Servicios Adicionales | AV54: No Aplica
A55: 51 | E55: Proyecto | F55: Proyecto 51 | H55: G2 | AH55: ='Portafolio P&D'!Y40 -> 0 | AI55: ='Portafolio P&D'!Z40 -> 0 | AK55: ='Portafolio P&D'!AA40 -> 0.58 | AL55: ='Portafolio P&D'!AB40 -> 0.45 | AM55: =IF(DemandaEstrateg_[[#This Row],[Tipo de Requerimiento]]="Proyecto",(DemandaEstrateg_[[#This Row],[% Avance ejecutado]]-DemandaEstrateg_[[#This Row],[% Avance Planificado]])/DemandaEstrateg_[[#This Row],[% Avance Planificado]],"No aplica") -> -0.22413793 | AN55: =IF(DemandaEstrateg_[[#This Row],[Tipo de Requerimiento]]="Proyecto",(DemandaEstrateg_[[#This Row],[% Avance ejecutado]]-DemandaEstrateg_[[#This Row],[% Avance Planificado]])/DemandaEstrateg_[[#This Row],[% Avance Planificado]],"No aplica") -> -0.22413793 | AP55: 45901 | AQ55: 2025-III | AR55: Pendiente | AS55: 09. Finalizado | AT55: =VLOOKUP(DemandaEstrateg_[[#This Row],[Estado TI]],#REF!,3,FALSE) -> #REF! | AU55: 05/09/2025: Está pendiente que el área usuaria resuelva el tema del tarifario de comisiones CCE. Debido a los fraudes presentados, se está priorizando la atención de mejoras funcionales y de seguridad solicitados para un canal seguro. 05/09/2025: El MEMORANDO adjunto (N° 00000228 - 2025 - BN/3111) fue devuelto, por lo que se esta retirando su registro en la Demanda Estratégica CT. Además, el mantenimiento no se encuentra activo en Producción. El equipo de Construcción sugiere un nuevo ciclo de pruebas cuando culmine la implementación de mejoras. 25/07/2025: El mantenimiento asociado al Proyecto, se encuentra en proceso de certificación, el compromiso es certificar el mantenimiento el mes de Agosto. 17/07/2025: Se está realizando la atención de Pago de haberes que está planificado culminar en agosto 2025 03/06/2025: Según la información enviada de Planeamiento mediante correo respecto al proyecto en el mes de abril se tiene que: A pesar de los correos enviados por el analista asigando y el subgerente de planeamiento, aún no se han presentado el cronograma ni la evaluación costo-beneficio. La justificación es que están coordinando con el área de TI, la cual tiene sus propios plazos para atender y desarrollar esas actividades. 21/05/2025: Según el Acta de Reunión N°04-2025 del Comité de Proyectos, se llevará una reunión entre la Gerencia General, Gerencia de Operaciones y la Gerencia de TI para determinar los cambios que tendrá dicho proyecto. 30/04/25: Proyecto aprobado por el Comité Ejecutivo de proyectos, comunicado mediante acta N° 03-2025 de fecha 19 de marzo 2025. De acuerdo a lo dispuesto por Gerencia General, actualmente se viene atendiendo las incidencias de Banca Empresarial, posterior a ello se iniciará la atención de la Fase IV del proyecto. 21/04/2025 Proyecto aprobado por el Comité Ejecutivo de proyectos, comunicado mediante acta N° 03-2025 de fecha 19 de marzo 2025. | AV55: ='Portafolio P&D'!B40 -> 0
A56: 52 | E56: Proyecto-Hijo | F56: Proyecto 52 | H56: G2 | AH56: 45749 | AI56: Pendiente | AK56: No aplica | AL56: No aplica | AM56: =IF(DemandaEstrateg_[[#This Row],[Tipo de Requerimiento]]="Proyecto",(DemandaEstrateg_[[#This Row],[% Avance ejecutado]]-DemandaEstrateg_[[#This Row],[% Avance Planificado]])/DemandaEstrateg_[[#This Row],[% Avance Planificado]],"No aplica") -> No aplica | AN56: =IF(DemandaEstrateg_[[#This Row],[Tipo de Requerimiento]]="Proyecto",(DemandaEstrateg_[[#This Row],[% Avance ejecutado]]-DemandaEstrateg_[[#This Row],[% Avance Planificado]])/DemandaEstrateg_[[#This Row],[% Avance Planificado]],"No aplica") -> No aplica | AQ56: 2026-I | AR56: Certificado | AS56: =VLOOKUP(DemandaEstrateg_[[#This Row],[Últ. Estado CQ 30.04]],#REF!,3,FALSE) -> #REF! | AT56: =VLOOKUP(DemandaEstrateg_[[#This Row],[Estado TI]],#REF!,3,FALSE) -> #REF! | AU56: 29/04/2025: Se regularizó requerimiento en el Backlog. | AV56: No Aplica
A57: 53 | E57: Proyecto-Hijo | F57: Proyecto 53 | H57: G2 | AH57: 45785 | AI57: 45884 | AK57: No aplica | AL57: No aplica | AM57: =IF(DemandaEstrateg_[[#This Row],[Tipo de Requerimiento]]="Proyecto",(DemandaEstrateg_[[#This Row],[% Avance ejecutado]]-DemandaEstrateg_[[#This Row],[% Avance Planificado]])/DemandaEstrateg_[[#This Row],[% Avance Planificado]],"No aplica") -> No aplica | AN57: =IF(DemandaEstrateg_[[#This Row],[Tipo de Requerimiento]]="Proyecto",(DemandaEstrateg_[[#This Row],[% Avance ejecutado]]-DemandaEstrateg_[[#This Row],[% Avance Planificado]])/DemandaEstrateg_[[#This Row],[% Avance Planificado]],"No aplica") -> No aplica | AQ57: 2026-I | AR57: Asignado | AS57: =VLOOKUP(DemandaEstrateg_[[#This Row],[Últ. Estado CQ 30.04]],#REF!,3,FALSE) -> #REF! | AT57: =VLOOKUP(DemandaEstrateg_[[#This Row],[Estado TI]],#REF!,3,FALSE) -> #REF! | AU57: 07/05/2025: Se registró requerimiento en el Backlog. RQ Hijo de 2649 | AV57: No Aplica
A58: 54 | E58: Proyecto-Hijo | F58: Proyecto 54 | H58: G2 | AH58: 45797 | AI58: 45884 | AK58: No aplica | AL58: No aplica | AM58: =IF(DemandaEstrateg_[[#This Row],[Tipo de Requerimiento]]="Proyecto",(DemandaEstrateg_[[#This Row],[% Avance ejecutado]]-DemandaEstrateg_[[#This Row],[% Avance Planificado]])/DemandaEstrateg_[[#This Row],[% Avance Planificado]],"No aplica") -> No aplica | AN58: =IF(DemandaEstrateg_[[#This Row],[Tipo de Requerimiento]]="Proyecto",(DemandaEstrateg_[[#This Row],[% Avance ejecutado]]-DemandaEstrateg_[[#This Row],[% Avance Planificado]])/DemandaEstrateg_[[#This Row],[% Avance Planificado]],"No aplica") -> No aplica | AP58: 46037 | AQ58: 2026-I | AR58: Asignado | AS58: =VLOOKUP(DemandaEstrateg_[[#This Row],[Últ. Estado CQ 30.04]],#REF!,3,FALSE) -> #REF! | AT58: =VLOOKUP(DemandaEstrateg_[[#This Row],[Estado TI]],#REF!,3,FALSE) -> #REF! | AU58: 19/05/25: Se registra el FASE 1: Integraciones - Implementación de Novatronic al Backlog y se crea trámite. RQ hijo de 2649 | AV58: No Aplica
A59: 55 | E59: Proyecto | F59: Proyecto 55 | H59: G2 | AH59: 45297 | AI59: 46534 | AK59: 0.48 | AL59: 0.23 | AM59: =IF(DemandaEstrateg_[[#This Row],[Tipo de Requerimiento]]="Proyecto",(DemandaEstrateg_[[#This Row],[% Avance ejecutado]]-DemandaEstrateg_[[#This Row],[% Avance Planificado]])/DemandaEstrateg_[[#This Row],[% Avance Planificado]],"No aplica") -> -0.52083333 | AN59: =IF(DemandaEstrateg_[[#This Row],[Tipo de Requerimiento]]="Proyecto",(DemandaEstrateg_[[#This Row],[% Avance ejecutado]]-DemandaEstrateg_[[#This Row],[% Avance Planificado]])/DemandaEstrateg_[[#This Row],[% Avance Planificado]],"No aplica") -> -0.52083333 | AP59: 46534 | AQ59: 2027-II | AR59: Pendiente | AS59: 03. En Desarrollo | AT59: =VLOOKUP(DemandaEstrateg_[[#This Row],[Estado TI]],#REF!,3,FALSE) -> #REF! | AU59: 30/12:2025: De acuerdo con el acta de reunión del comité de proyectos, se debe realizar un informe sobre el estado situacional del proyecto y la Gerencia de Banca Digital debe agendar una reunión con la gerencia de TI y el proveedor para ver posibles mejoras. 06/10/2025 Con Informe Técnico N° 00000040 - 2025-BN/2560 de fecha 06/10 TI emite respuesta sobre el entregable Despliegue del Ambiente de Certificación (QA). El proveedor solicito 3 Certificados SSL para el ambiente de Desarrollo a través del correo electrónico y el equipo de la Oficina de Seguridad Informática solicito que remitan el certificate signing request (CSR) para que procedan a la emisión. A la fecha el proveedor aun no lo remite. El equipo de TI viene dando el apoyo técnico a las consultar y requerimientos realizados por el Proveedor. Está pendiente que el usuario gestione la ampliación de plazo e informar a Planeamiento. 05/09/2025: Con Informe Técnico N° 00000015 - 2025-BN/2550 de fecha 14/07 TI emite respuesta sobre el entregable: Despliegue Base para los Ambientes. Con Informe Técnico N° 00000032 - 2025-BN/2560 de fecha 13/08 TI emite respuesta sobre el entregable Despliegue del Ambiente de Desarrollo (DEV). Banca Digital con Carta Nº 00000051-2025-BN/7920 de fecha 21/08 dio la conformidad Diseño UX/UI. En reunión de seguimiento entre el Proveedor, Banca Digital y TI del 27/08 el proveedor informo el avance de la implementación: Infraestructura de QA: 20% Implementación del ambiente de seguridad: 8.8% Se están realizando la revisión en conjunto entre PeruApps y TI de la Matriz de Servicios para el desarrollo del MVP1. 25/07/2025: En reunión diaria el área usuaria comunico: • El contratista solicito ampliación de plazo para la presentación del Informe de despliegue del ambiente de Desarrollo (DEV) sobre las observaciones reportadas por TI el 14.07. El área usuaria comunico la aceptación a la solicitud. Pendiente que informe la fecha de presentación. • El área usuaria dio la conformidad del Análisis Funcional el 25/07 y está pendiente la conformidad del Diseño UX/UI el 07/08. Se suscribió la 3era Adenda debido al fideicomiso asociado al Contratista. 17/07/2025: El 24.06.2025 el contratista remitió el Informe de Despliegue Base (Componente 10.1. Servicios compartidos) y se reportó observaciones. El 11.07 el contratista remite la subsanación de las correcciones con el cual TI dará respuesta el 18/07. Continua pendiente la aprobación de los entregables: Análisis Funcional, Diseño UX/UI, por parte del área usuaria. 07/07/2025: El 24.06.2025 el contratista remitio, respecto al Informe de Despliegue Base (Componente 10.1. Servicios compartidos) , el 25.06.2025, TI mediante correo electroncico reporto las observaciones al Informe presentado. El 03.07.2025 , contratista remitio Carta Notarial del contratista, respecto a la Clausura Novena del Contrato. Siguen pendientes de aprobacion los entegables de funcionalidad (Casos de uso), infraestructura y user testing. 11/06/2025:Según la información enviada de Planeamiento en el mes de Mayo se precisa lo siguiente: Incumplimiento de (03) entregables por parte de la empresa contratada relacionados a los temas de funcionalidad (Casos de uso), infraestructura y user testing. Cabe resaltar que se firmó la adenda de mejora el 30.05.2025; sin embargo, está pendiente el cronograma consensuado con TI. El área usuaria gestionará la solicitud de cambios por parte del área líder del proyecto 03/06/2025: Según la información enviada de Planeamiento mediante correo respecto al proyecto en el mes de abril se tiene que: Se cuenta en proceso de subsanaciòn por parte del proveedor, lo relacionado a la culminación de los casos de uso y observaciones del user testing efectuado. Asu vez, la adenda de mejora evaluada por el área legal cuenta con el informe de TI, el cual será remitido a la Gerencial General para su aprobación. Se estima presentación de solicitud de cambios previo informe posterior a rpta de GG. 02/06/2025 En daily del 29/5/2025 se indico que Segunda Adenda se encuentra en Logistica. Asimismo las Epicas 1 y 2 se encuentraban firmadas y en procesos de firmas la Epica 3. 23/05/2025: Se registra el Proyecto Nueva Plataforma de Banca Móvil y Banca por Internet. Se registró en el Backlog. 07/05/2025: Según la información remitida por Planeamiento mediante correo: Se encuentra pendiente por parte del proveedor subsanar las observaciones formuladas a los casos de uso; por lo que aún no habrá acta de conformidad y se preparará informe de penalidad. 07/05/2025: Se cambió el nombre del Proyecto "Nueva app BN y Nuevo Home Banking "Multired Virtual" "a Plataforma de Banca Móvil y Banca por Internet, según lo remitido por Planeamiento. 30/4/2025: Se tuvo reunión con el equipo técnico de TI, equipo de Banca Digital y Gerencia General se respondieron las consultas técnicas y se quedo a las la espera del pronunciamiento de Banca Digital sobre los precios unitarios. 22/4/2025: Se firmó Carta de Compromiso (Carta N° 018-2025-BN/7901) relacionado a las actividades en curso. 31/03/25: En respuesta a la Carta 009-PCDBN-PERUAPPS-2025 - "Entrega de Informe de Despliegue de la Implementación de la Infraestructura Base en AWS para los ambientes a Implementar (Desarrollo, Certificación y Producción)" se emite el infirme técnico N° 00000005 - 2025-BN/2550 el 05.03.2025 en el cual se remiten observaciones al entregable. El contratista remite la Carta 015-PCDBN-PERUAPPS-2025 - "Respuesta a Observaciones al Informe de Implementación Base de la Infraestructura AWS" y se emite el Informe Técnico 00000008 - 2025-BN/2550 el 31.04.2025 (se envió a través de correo) en el cual se solicita al contratista ampliar el sustento técnico y realizar ajustes al informe presentado. Se está a la espera de la respuesta del Contratista para que TI emita un nuevo informe el cual para que el área usuaria pueda solicitar la Adenda. Las actividades de Despliegue del ambiente DEV no se puede iniciar hasta la conformidad del despliegue de la Infraestructura Base AWS. 28/02/25: TI se encuentra participando en reuniones técnicas con el proveedor. Se tuvo reunión con el Contratista el 17/02 en el cual presentaron la "Matriz de Requerimiento – Implementación Infraestructura Base AWS v1.0" en dicho cuadro se mostró componentes que no están incluidos en los TdR y componentes que si están incluidos en los TdR, sin embargo no se tenía la claridad si se estaba cumpliendo con todo lo indicado en los TdR. El equipo de Arquitectura elaboro una matriz con todos los ítems indicados en los TdR (funcionalidades, características) a fin que el contratista defina con que herramienta y/o componente se cubría lo indicado en los TdR, esto se remitió con la Carta N°003-2025-BN/7901 de fecha 25.02. Se indico al area responsable del contraro que coordine con Logista a cerca de los diferenciales (componentes que se indicaban en la matriz presentada por el contratista y que no están indicado en los TdR. 17/02/25: TI se encuentra participando en reuniones técnicas con el proveedor y en reuniones de trabajo funcional (opcional). El 17.02 El contratista remitió la Matriz de Trazabilidad de Requerimientos correspondiente al despliegue y se agendara reuniones para la revisión. 31/02/25 El avance Sobre las actividades de Implementación de Infraestructura Cloud (AWS) 43% y Sobre las actividades del Diseño, desarrollo e implementación de la solución 12% En esta ultima actividad me indicaron que han avanzado con la elaboracion de 59 CU de un total de 286 03/06/2025: Según la información enviada de Planeamiento mediante correo respecto al proyecto en el mes de abril se tiene que: Se cuenta en proceso de subsanaciòn por parte del proveedor, lo relacionado a la culminación de los casos de uso y observaciones del user testing efectuado. Asu vez, la adenda de mejora evaluada por el área legal cuenta con el informe de TI, el cual será remitido a la Gerencial General para su aprobación. Se estima presentación de solicitud de cambios previo informe posterior a rpta de GG. 30/5/2025: EL 30/5/2025 se firmo la Segunda Adenda al contrato. Se tiene firmado las EPICAS 1 y 2, y estan en proceso la Epica 3. 23/05/2025: Se registra el Proyecto Nueva Plataforma de Banca Móvil y Banca por Internet. Se registró en el Backlog. | AV59: ='Portafolio P&D'!B35 -> 0
A60: 56 | E60: Proyecto-Hijo | F60: Proyecto 56 | H60: G2 | AH60: 45820 | AI60: Pendiente | AJ60: 46037 | AK60: No aplica | AL60: No aplica | AM60: =IF(DemandaEstrateg_[[#This Row],[Tipo de Requerimiento]]="Proyecto",(DemandaEstrateg_[[#This Row],[% Avance ejecutado]]-DemandaEstrateg_[[#This Row],[% Avance Planificado]])/DemandaEstrateg_[[#This Row],[% Avance Planificado]],"No aplica") -> No aplica | AN60: =IF(DemandaEstrateg_[[#This Row],[Tipo de Requerimiento]]="Proyecto",(DemandaEstrateg_[[#This Row],[% Avance ejecutado]]-DemandaEstrateg_[[#This Row],[% Avance Planificado]])/DemandaEstrateg_[[#This Row],[% Avance Planificado]],"No aplica") -> No aplica | AP60: 46023 | AQ60: 2026-I | AR60: Transitorio_procesado | AS60: =VLOOKUP(DemandaEstrateg_[[#This Row],[Últ. Estado CQ 30.04]],#REF!,3,FALSE) -> #REF! | AT60: =VLOOKUP(DemandaEstrateg_[[#This Row],[Estado TI]],#REF!,3,FALSE) -> #REF! | AU60: 15/01/26: Segun CQ el requerimiento fue atendido el el día 16/06/2025, pero el cierre del mantenimiento se dio el 15/01/26 13/06/25: Se registró en el Backlog. | AV60: No Aplica
A61: 57 | E61: Proyecto | F61: Proyecto 57 | H61: G2 | AH61: ='Portafolio P&D'!Y38 -> 0 | AI61: ='Portafolio P&D'!Z38 -> 0 | AK61: ='Portafolio P&D'!AA38 -> 1 | AL61: ='Portafolio P&D'!AB38 -> 1 | AM61: =IF(DemandaEstrateg_[[#This Row],[Tipo de Requerimiento]]="Proyecto",(DemandaEstrateg_[[#This Row],[% Avance ejecutado]]-DemandaEstrateg_[[#This Row],[% Avance Planificado]])/DemandaEstrateg_[[#This Row],[% Avance Planificado]],"No aplica") -> 0 | AN61: =IF(DemandaEstrateg_[[#This Row],[Tipo de Requerimiento]]="Proyecto",(DemandaEstrateg_[[#This Row],[% Avance ejecutado]]-DemandaEstrateg_[[#This Row],[% Avance Planificado]])/DemandaEstrateg_[[#This Row],[% Avance Planificado]],"No aplica") -> 0 | AP61: 45901 | AQ61: 2025-III | AR61: Pendiente | AS61: 09. Finalizado | AT61: =VLOOKUP(DemandaEstrateg_[[#This Row],[Estado TI]],#REF!,3,FALSE) -> #REF! | AU61: 03/10/2025: Al cierre de setiembre, el proveedor cumplió la totalidad de las actividades programadas conforme al cronograma establecido. Asimismo, se concluyó el Informe de Cierre y las lecciones aprendidas, que serán remitidos a la Gerencia de Planeamiento y Control de Gestión. 05/09/2025: Se reportó que el proveedor culminó con las actividades de la etapa de implementación del proyecto de acuerdo con el cronograma planificado. Asimismo, se ha iniciado la elaboración del informe de cierre del proyecto y la recopilación de las lecciones aprendidas. 25/07/2025: Se culminó la instalación de los equipos en la Sede de Chiclayo. Actualmente, se han iniciado las actividades correspondientes a la configuración y migración. 07/07/2025: Se reportó que el proveedor ha culminado con la entrega de los bienes en las tres sedes contempladas en el alcance del proyecto. Asimismo, se ha finalizado la instalación de los equipos en las sedes de San Isidro y San Borja. En cuanto a la sede de Chiclayo, se informó que la instalación se viene ejecutando de manera anticipada contribuyendo al cumplimiento oportuno de los hitos establecidos 16/06/2025: Se registró en el Backlog. Proyecto aprobado en Comité Ejecutivo de Proyectos, mediante acta N°3 del 19/03/2025. | AV61: ='Portafolio P&D'!B38 -> 0
A62: 58 | E62: Proyecto-Hijo | F62: Proyecto 58 | H62: G2 | AH62: 45824 | AI62: 45989 | AK62: No aplica | AL62: No aplica | AM62: =IF(DemandaEstrateg_[[#This Row],[Tipo de Requerimiento]]="Proyecto",(DemandaEstrateg_[[#This Row],[% Avance ejecutado]]-DemandaEstrateg_[[#This Row],[% Avance Planificado]])/DemandaEstrateg_[[#This Row],[% Avance Planificado]],"No aplica") -> No aplica | AN62: =IF(DemandaEstrateg_[[#This Row],[Tipo de Requerimiento]]="Proyecto",(DemandaEstrateg_[[#This Row],[% Avance ejecutado]]-DemandaEstrateg_[[#This Row],[% Avance Planificado]])/DemandaEstrateg_[[#This Row],[% Avance Planificado]],"No aplica") -> No aplica | AP62: 46023 | AQ62: 2026-I | AR62: Asignado | AS62: =VLOOKUP(DemandaEstrateg_[[#This Row],[Últ. Estado CQ 30.04]],#REF!,3,FALSE) -> #REF! | AT62: =VLOOKUP(DemandaEstrateg_[[#This Row],[Estado TI]],#REF!,3,FALSE) -> #REF! | AU62: 25/06/2025: Se regularizó requerimiento en el Backlog. | AV62: No Aplica
A63: 59 | E63: Proyecto-Hijo | F63: Proyecto 59 | H63: G2 | AH63: 45824 | AI63: 45989 | AK63: No aplica | AL63: No aplica | AM63: =IF(DemandaEstrateg_[[#This Row],[Tipo de Requerimiento]]="Proyecto",(DemandaEstrateg_[[#This Row],[% Avance ejecutado]]-DemandaEstrateg_[[#This Row],[% Avance Planificado]])/DemandaEstrateg_[[#This Row],[% Avance Planificado]],"No aplica") -> No aplica | AN63: =IF(DemandaEstrateg_[[#This Row],[Tipo de Requerimiento]]="Proyecto",(DemandaEstrateg_[[#This Row],[% Avance ejecutado]]-DemandaEstrateg_[[#This Row],[% Avance Planificado]])/DemandaEstrateg_[[#This Row],[% Avance Planificado]],"No aplica") -> No aplica | AP63: 46023 | AQ63: 2026-I | AR63: Asignado | AS63: =VLOOKUP(DemandaEstrateg_[[#This Row],[Últ. Estado CQ 30.04]],#REF!,3,FALSE) -> #REF! | AT63: =VLOOKUP(DemandaEstrateg_[[#This Row],[Estado TI]],#REF!,3,FALSE) -> #REF! | AU63: 25/06/2025: Se regularizó requerimiento en el Backlog. | AV63: No Aplica
A64: 60 | E64: Proyecto-Hijo | F64: Proyecto 60 | H64: G2 | AH64: 45824 | AI64: 45989 | AK64: No aplica | AL64: No aplica | AM64: =IF(DemandaEstrateg_[[#This Row],[Tipo de Requerimiento]]="Proyecto",(DemandaEstrateg_[[#This Row],[% Avance ejecutado]]-DemandaEstrateg_[[#This Row],[% Avance Planificado]])/DemandaEstrateg_[[#This Row],[% Avance Planificado]],"No aplica") -> No aplica | AN64: =IF(DemandaEstrateg_[[#This Row],[Tipo de Requerimiento]]="Proyecto",(DemandaEstrateg_[[#This Row],[% Avance ejecutado]]-DemandaEstrateg_[[#This Row],[% Avance Planificado]])/DemandaEstrateg_[[#This Row],[% Avance Planificado]],"No aplica") -> No aplica | AP64: 46023 | AQ64: 2026-I | AR64: Asignado | AS64: =VLOOKUP(DemandaEstrateg_[[#This Row],[Últ. Estado CQ 30.04]],#REF!,3,FALSE) -> #REF! | AT64: =VLOOKUP(DemandaEstrateg_[[#This Row],[Estado TI]],#REF!,3,FALSE) -> #REF! | AU64: 25/06/2025: Se regularizó requerimiento en el Backlog. | AV64: No Aplica
A65: 61 | E65: Proyecto-Hijo | F65: Proyecto 61 | H65: G2 | AH65: 45824 | AI65: 45989 | AK65: No aplica | AL65: No aplica | AM65: =IF(DemandaEstrateg_[[#This Row],[Tipo de Requerimiento]]="Proyecto",(DemandaEstrateg_[[#This Row],[% Avance ejecutado]]-DemandaEstrateg_[[#This Row],[% Avance Planificado]])/DemandaEstrateg_[[#This Row],[% Avance Planificado]],"No aplica") -> No aplica | AN65: =IF(DemandaEstrateg_[[#This Row],[Tipo de Requerimiento]]="Proyecto",(DemandaEstrateg_[[#This Row],[% Avance ejecutado]]-DemandaEstrateg_[[#This Row],[% Avance Planificado]])/DemandaEstrateg_[[#This Row],[% Avance Planificado]],"No aplica") -> No aplica | AP65: 46023 | AQ65: 2026-I | AR65: Trasitorio_autorizado | AS65: =VLOOKUP(DemandaEstrateg_[[#This Row],[Últ. Estado CQ 30.04]],#REF!,3,FALSE) -> #REF! | AT65: =VLOOKUP(DemandaEstrateg_[[#This Row],[Estado TI]],#REF!,3,FALSE) -> #REF! | AU65: 25/06/2025: Se regularizó requerimiento en el Backlog. | AV65: No Aplica
A66: 62 | E66: Proyecto-Hijo | F66: Proyecto 62 | H66: G2 | AH66: 45824 | AI66: 45989 | AK66: No aplica | AL66: No aplica | AM66: =IF(DemandaEstrateg_[[#This Row],[Tipo de Requerimiento]]="Proyecto",(DemandaEstrateg_[[#This Row],[% Avance ejecutado]]-DemandaEstrateg_[[#This Row],[% Avance Planificado]])/DemandaEstrateg_[[#This Row],[% Avance Planificado]],"No aplica") -> No aplica | AN66: =IF(DemandaEstrateg_[[#This Row],[Tipo de Requerimiento]]="Proyecto",(DemandaEstrateg_[[#This Row],[% Avance ejecutado]]-DemandaEstrateg_[[#This Row],[% Avance Planificado]])/DemandaEstrateg_[[#This Row],[% Avance Planificado]],"No aplica") -> No aplica | AP66: 46023 | AQ66: 2026-I | AR66: Asignado | AS66: =VLOOKUP(DemandaEstrateg_[[#This Row],[Últ. Estado CQ 30.04]],#REF!,3,FALSE) -> #REF! | AT66: =VLOOKUP(DemandaEstrateg_[[#This Row],[Estado TI]],#REF!,3,FALSE) -> #REF! | AU66: 25/06/2025: Se regularizó requerimiento en el Backlog. | AV66: No Aplica
A67: 63 | E67: Proyecto-Hijo | F67: Proyecto 63 | H67: G2 | AH67: 45824 | AI67: 45989 | AK67: No aplica | AL67: No aplica | AM67: =IF(DemandaEstrateg_[[#This Row],[Tipo de Requerimiento]]="Proyecto",(DemandaEstrateg_[[#This Row],[% Avance ejecutado]]-DemandaEstrateg_[[#This Row],[% Avance Planificado]])/DemandaEstrateg_[[#This Row],[% Avance Planificado]],"No aplica") -> No aplica | AN67: =IF(DemandaEstrateg_[[#This Row],[Tipo de Requerimiento]]="Proyecto",(DemandaEstrateg_[[#This Row],[% Avance ejecutado]]-DemandaEstrateg_[[#This Row],[% Avance Planificado]])/DemandaEstrateg_[[#This Row],[% Avance Planificado]],"No aplica") -> No aplica | AP67: 46023 | AQ67: 2026-I | AR67: Asignado | AS67: =VLOOKUP(DemandaEstrateg_[[#This Row],[Últ. Estado CQ 30.04]],#REF!,3,FALSE) -> #REF! | AT67: =VLOOKUP(DemandaEstrateg_[[#This Row],[Estado TI]],#REF!,3,FALSE) -> #REF! | AU67: 25/06/2025: Se regularizó requerimiento en el Backlog. | AV67: No Aplica
A68: 64 | E68: Proyecto-Hijo | F68: Proyecto 64 | H68: G2 | AH68: Pendiente | AI68: 45989 | AK68: No aplica | AL68: No aplica | AM68: =IF(DemandaEstrateg_[[#This Row],[Tipo de Requerimiento]]="Proyecto",(DemandaEstrateg_[[#This Row],[% Avance ejecutado]]-DemandaEstrateg_[[#This Row],[% Avance Planificado]])/DemandaEstrateg_[[#This Row],[% Avance Planificado]],"No aplica") -> No aplica | AN68: =IF(DemandaEstrateg_[[#This Row],[Tipo de Requerimiento]]="Proyecto",(DemandaEstrateg_[[#This Row],[% Avance ejecutado]]-DemandaEstrateg_[[#This Row],[% Avance Planificado]])/DemandaEstrateg_[[#This Row],[% Avance Planificado]],"No aplica") -> No aplica | AP68: 46023 | AQ68: 2026-I | AR68: Pendiente | AS68: 01. Registrado | AT68: =VLOOKUP(DemandaEstrateg_[[#This Row],[Estado TI]],#REF!,3,FALSE) -> #REF! | AU68: 01/07/2025: Se registró requerimiento en el Backlog y se creó el trámite respectivo. Requerimiento asociado al Proyecto Sentinel (ID 2487) | AV68: No Aplica
A69: 65 | E69: Proyecto-Hijo | F69: Proyecto 65 | H69: G2 | AM69: =IF(DemandaEstrateg_[[#This Row],[Tipo de Requerimiento]]="Proyecto",(DemandaEstrateg_[[#This Row],[% Avance ejecutado]]-DemandaEstrateg_[[#This Row],[% Avance Planificado]])/DemandaEstrateg_[[#This Row],[% Avance Planificado]],"No aplica") -> No aplica | AN69: =IF(DemandaEstrateg_[[#This Row],[Tipo de Requerimiento]]="Proyecto",(DemandaEstrateg_[[#This Row],[% Avance ejecutado]]-DemandaEstrateg_[[#This Row],[% Avance Planificado]])/DemandaEstrateg_[[#This Row],[% Avance Planificado]],"No aplica") -> No aplica | AR69: Asignado | AS69: =VLOOKUP(DemandaEstrateg_[[#This Row],[Últ. Estado CQ 30.04]],#REF!,3,FALSE) -> #REF! | AT69: =VLOOKUP(DemandaEstrateg_[[#This Row],[Estado TI]],#REF!,3,FALSE) -> #REF! | AU69: 25/07/2025: Se registró en el Backlog como regularizado. | AV69: No Aplica
A70: 66 | E70: Proyecto | F70: Proyecto 66 | H70: G2 | AH70: 45965 | AI70: 46234 | AK70: 0.27 | AL70: 0.27 | AM70: =IF(DemandaEstrateg_[[#This Row],[Tipo de Requerimiento]]="Proyecto",(DemandaEstrateg_[[#This Row],[% Avance ejecutado]]-DemandaEstrateg_[[#This Row],[% Avance Planificado]])/DemandaEstrateg_[[#This Row],[% Avance Planificado]],"No aplica") -> 0 | AN70: =IF(DemandaEstrateg_[[#This Row],[Tipo de Requerimiento]]="Proyecto",(DemandaEstrateg_[[#This Row],[% Avance ejecutado]]-DemandaEstrateg_[[#This Row],[% Avance Planificado]])/DemandaEstrateg_[[#This Row],[% Avance Planificado]],"No aplica") -> 0 | AP70: 46555 | AQ70: 2027-II | AR70: Asignado | AS70: =VLOOKUP(DemandaEstrateg_[[#This Row],[Últ. Estado CQ 30.04]],#REF!,3,FALSE) -> #REF! | AT70: =VLOOKUP(DemandaEstrateg_[[#This Row],[Estado TI]],#REF!,3,FALSE) -> #REF! | AU70: 30/12/2025: Según el acta de reunión del comité de proyectos, se debe agendar una reunión con las gerencias de TI, Planeamiento y Control de Gestión para reevaluar el alcance del proyecto y la gerencia de TI debe revisar las fechas propuestas del nuevo cronograma, el cual se pretende presentar a inicios del próximo año. 01/12/2025 Segun consta en Acta de Constitucion del Proyecto, el Proyecto seria de Marzo 2025 a Julio 2026, empezando la etapa de Desarrollo en Octubre 2025 Se debe indicar que la duracion estimada se realizo considerando la inclusion de tres recursos para la etapa de desarrollo. Se realizaron coordinaciones con el lider tecnico designado de parte de TI, para la elaboracion de un cronograma previo de desarrollo de la aplicacion y agregar el tiempo estimado de certificacion y produccion. Al 7 de Noviembre con tiempos estimados recibidos, se actualizo el cronograma y se advierte que este proyecto se extiende hasta Junio 2027, debido a que ahora solo se incluye la participacion de solo un recurso en la etapa de desarrollo, y ademas el inicio de la etapa de desarrollo se actualizo de Octubre 2025 a Noviembre 2025 Al 01-12-2025 las actividades de Desarollo de la Aplicacion avanza, segun cronograma establecido 5%, y se lleva a cabo reuniones con el area usuario para su revision. Se espera que en Febrero 2026, se cuente con 2 recursos adicionales, con lo que se podria acelerar las actividades y finalizar el proyecto , segun calculos realizados en Noviembre 2026. "30/09/2025: Según la información enviada de Planeamiento en el mes de Septiembre se precisa lo siguiente: El proyecto “Aplicativo de Evaluación de Desempeño por Objetivos (EDDO)” . Desde su aprobación el 21 de agosto de 2025, se han cumplido los pasos formales requeridos, incluyendo la remisión de los documentos técnicos (FI, CN, AC) y el envío del Anexo 01 a la Gerencia de TI. A la fecha (13 de octubre de 2025), el proyecto se encuentra en proceso de confirmación del cronograma de atención con la Oficina de Proyectos y Procesos de TI, lo que evidencia un avance sostenido hacia la planificación del desarrollo del aplicativo. 10/09/25: Se registró en el Backlog | AV70: ='Portafolio P&D'!B42 -> 0
A71: 67 | E71: Proyecto-Hijo | F71: Proyecto 67 | H71: G2 | AH71: 45838 | AI71: 45989 | AM71: =IF(DemandaEstrateg_[[#This Row],[Tipo de Requerimiento]]="Proyecto",(DemandaEstrateg_[[#This Row],[% Avance ejecutado]]-DemandaEstrateg_[[#This Row],[% Avance Planificado]])/DemandaEstrateg_[[#This Row],[% Avance Planificado]],"No aplica") -> No aplica | AN71: =IF(DemandaEstrateg_[[#This Row],[Tipo de Requerimiento]]="Proyecto",(DemandaEstrateg_[[#This Row],[% Avance ejecutado]]-DemandaEstrateg_[[#This Row],[% Avance Planificado]])/DemandaEstrateg_[[#This Row],[% Avance Planificado]],"No aplica") -> No aplica | AP71: 46023 | AQ71: 2026-I | AR71: Asignado | AS71: =VLOOKUP(DemandaEstrateg_[[#This Row],[Últ. Estado CQ 30.04]],#REF!,3,FALSE) -> #REF! | AT71: =VLOOKUP(DemandaEstrateg_[[#This Row],[Estado TI]],#REF!,3,FALSE) -> #REF! | AU71: 12/08/2025: Se registró el requerimiento perteneciente al Proyecto Sentinel en la Demanda Estratégica CT. 11/08/2025: Cartera reasignada a Percy Silva 30/05/25: Según CQ, actualizó el estado a 03. En Desarrollo 28/05/2025: Se regularizó requerimiento en el Backlog. | AV71: No Aplica
A72: 68 | E72: Proyecto-Hijo | F72: Proyecto 68 | G72: Adecuación del proceso de extracción de datos de transacciones para el proyecto SENTINEL, continuación de las adecuaciones - TRX prioridad 2. | H72: G2 | AH72: 45838 | AI72: 45989 | AM72: =IF(DemandaEstrateg_[[#This Row],[Tipo de Requerimiento]]="Proyecto",(DemandaEstrateg_[[#This Row],[% Avance ejecutado]]-DemandaEstrateg_[[#This Row],[% Avance Planificado]])/DemandaEstrateg_[[#This Row],[% Avance Planificado]],"No aplica") -> No aplica | AN72: =IF(DemandaEstrateg_[[#This Row],[Tipo de Requerimiento]]="Proyecto",(DemandaEstrateg_[[#This Row],[% Avance ejecutado]]-DemandaEstrateg_[[#This Row],[% Avance Planificado]])/DemandaEstrateg_[[#This Row],[% Avance Planificado]],"No aplica") -> No aplica | AP72: 46023 | AQ72: 2026-I | AR72: Trasitorio_autorizado | AS72: =VLOOKUP(DemandaEstrateg_[[#This Row],[Últ. Estado CQ 30.04]],#REF!,3,FALSE) -> #REF! | AT72: =VLOOKUP(DemandaEstrateg_[[#This Row],[Estado TI]],#REF!,3,FALSE) -> #REF! | AU72: 07/07/2025: Se registró el requerimiento perteneciente al Proyecto Sentinel en la Demanda Estratégica CT. 01/07/2025: Se registró requerimiento en el Backlog y se creó el trámite respectivo. Requerimiento asociado al Proyecto Sentinel (ID 2487) | AV72: No Aplica
A73: 69 | E73: Proyecto | F73: Proyecto 69 | G73: Realizar cambios de ingeniería que se necesiten en los Cajeros Automáticos Depositarios a fin de que sean integrados en el aplicativo ESPLINK | H73: G2 | AH73: 45943 | AI73: 46356 | AK73: 0.38 | AL73: 0.39 | AM73: =IF(DemandaEstrateg_[[#This Row],[Tipo de Requerimiento]]="Proyecto",(DemandaEstrateg_[[#This Row],[% Avance ejecutado]]-DemandaEstrateg_[[#This Row],[% Avance Planificado]])/DemandaEstrateg_[[#This Row],[% Avance Planificado]],"No aplica") -> 0.026315789 | AN73: =IF(DemandaEstrateg_[[#This Row],[Tipo de Requerimiento]]="Proyecto",(DemandaEstrateg_[[#This Row],[% Avance ejecutado]]-DemandaEstrateg_[[#This Row],[% Avance Planificado]])/DemandaEstrateg_[[#This Row],[% Avance Planificado]],"No aplica") -> 0.026315789 | AP73: 46266 | AQ73: 2026-III | AR73: Registrado | AS73: 03. En Desarrollo | AT73: =VLOOKUP(DemandaEstrateg_[[#This Row],[Estado TI]],#REF!,3,FALSE) -> #REF! | AU73: 31/12/2025: Estamos avanzando con las actividades de desarrollo, planifcadas segun el cronograma establecido por el equipo, se acordo asignar mantenimientos a los equipos de Sistemas Bancarios y Sistemas Administrativos. 01/12/2025: Culminaron las actividades Etapa 1 de la prestación principal. Iniciamos la Etapa 2 con las actividades del equipo TI BN, Proveedor y Bevertec. Se está avanzando las actividades según el cronograma establecido por el equipo. 06/10/25: Se encuentra iniciando la etapa de revisión, se presentaron observaciones que fueron subsanados por el proveedor, está pendiente del informe de Seguridad Física. Luego de la presentación al día siguiente inicia los 200 días para la implementación. Los cajeros depositarios están en el laboratorio. Pendiente de Bevertec remita su propuesta de los desarrollos. 05/09/2025: El 25/08 se entregaron los cinco (5) cajeros depositarios. El 26 y 27 de agosto los equipos de TI y área usuaria realizaron la verificación física de equipos. El equipo de TI elaborara el informe con las observaciones encontradas que serán remitidas al Proveedor para la subsanación de los mismos. El 29/08 el área usuaria remitió mediante correo electrónico la documentación de los Cajeros Depositarios al equipo técnico el cual será regularizado mediante memorando. También se realizó la presentación de los flujos funcionales y el área usuaria debe actualizar y remitir el Anexo 1, asimismo se deberá elaborar el PCR para que el BN estime sus esfuerzos en las implementaciones pertinentes. El equipo de Construcción recomendó que se trabaje con más de un PRC a fin de agilizar las atenciones. 25/07/2025 De acuerdo a reunión del 07/07, el Proveedor Diebold remitió el manual técnico del ATM que se internará y los comandos para extracción de los contadores para interpretación del switch, el mismo que fue reenviado al Proveedor Bevertec. Queda pendiente que los usuarios remitan el Anexo 1 actualizado con los flujos de cada transacción, la definición de aquellas transacciones que van por contacless y la relación de dispositivos del ATM que serán monitoreados. El BN-Construcción se encuentra validando los desarrollos que serán trasladados al Proveedor Bevertec. Pendiente actualizar cronograma en coordinación con el Proveedor y usuarios. 17/07/2025: Actualmente se vienen desarrollando sesiones de trabajo conjuntas con TI, área usuaria y el proveedor Diebold. Se espera que el área usuaria remita su Anexo 1 actualizado de acuerdo a lo solicitado en reunión del 07/07. Se agendará reuniones para revisar el cronograma y definir actividades técnicas y plazos. 07/07/2025 : Actualmente se vienen desarrollando sesiones de trabajo conjuntas con la Gerencia de Tecnologías de Información y el proveedor Diebold, orientadas al diseño de la arquitectura de la solución y la gestión de los componentes de TI, en paralelo a la espera de la recepción física de los bienes.Asimismo sesiones con area usuario para definir el flujo funcional. 11/06/2025:Según la información enviada de Planeamiento en el mes de Mayo se precisa lo siguiente: Se están realizando sesiones de trabajo para el diseño de la arquitectura de solución y gestión de componente de TI en conjunto con el equipo de la Gerencia de Tecnologías de Información y el proveedor Diebold, mientras se espera la recepción física de los bienes. 03/06/2025: Según la información enviada de Planeamiento mediante correo respecto al proyecto al mes de abril se tiene que: Se realizó la firma correspondiente del contrato con el postor ganador Diebold Nixdorf Perú SRL., asimismo, se llevó a cabo la ceremonia del Kickoff con las áreas correspondientes. 07/05/2025: Según la información remitida por Planeamiento mediante correo: Para lograr el perfeccionamiento del contrato, el postor ganador Diebold logró subsanar las observaciones de la respectiva documentación en coordinación con el área de Logística e Innovación Digital, lo cual permitirá que la firma de contrato se pueda concretar dentro de los plazos previstos. 31/01/25: Para lograr el perfeccionamiento del contrato, el postor ganador Diebold logró subsanar las observaciones de la respectiva documentación en coordinación con el área de Logística e Innovación Digital, lo cual permitirá que la firma de contrato se pueda concretar dentro de los plazos previstos.En absolución de consultas y observaciones hasta este viernes 31ene25. 31/12/2024: Al 13.12.2024 se encuentra en proceso de reformulación de ETMs por resolución del Tribunal OSCE declaró nulo el proceso de selección (05.12.2024). El 27.12.2024 se convocó en el SEACE la LP-SM-4-2024-BN-1 23/05/24 Mediante acta de comité estratégico de proyectos con fecha 06.05.24 se aprobó el control de cambios del alcance del proyecto, los usuarios deben formalizar el nuevo cronograma del proyecto y remitirlo a planeamiento. 03/05/2024 Se ha devuelto Anexo 1 con observaciones 26/04/2024 Mediante correo de Pablo Arias se entrega el Anexo 1 del proyecto, el cuál se devuelve con observaciones notificadas dentro del documeneto al remitente en mención. A la espera de la devolución con observaciones levantadas, firmado y remitido por STD. 26/04/2024 A la espera de remitirse a TI el Anexo 1 y Anexo 2, asi mismo el registro de los requerimientos en OPP para su posterior categorización de cartera. 25/04/2024 Mediante Memo N° 63-2024-BN2810 en que se entrega la nueva lista de proyectos con componente TI se crea el proyecto en base de datos y se asigna el Lider usuario al proyecto, anteriormente no existia. 03/06/2025: Según la información enviada de Planeamiento mediante correo respecto al proyecto en el mes de abril se tiene que: Se realizó la firma correspondiente del contrato con el postor ganador Diebold Nixdorf Perú SRL., asimismo, se llevó a cabo la ceremonia del Kickoff con las áreas correspondientes. 02/06/2025 El 13/5/2025 se realizó reunión entre Contratista y Equipo TI para revisar el alcance técnico del proyecto. El 29/5/2025 en ruenion con Banca Digital se solicito actualizar el Anexo 1, según observaciones indicadas durante la reunion. 09/05/2025: El Kick Off se relaizo el 29/4/2025 entre personal involucrado del BANCO y Contratista (Diebold Nixdorf Perú SRL) ; El 5/5/2025 el contratista remitio por mesa de partes el entregable: "Detalle técnico de la integración Contacless". Se programo una reunion inicial tecnica para el 13/5/2025 entre Banco y Diebold 22/04/25: El proyecto fue asignado al nuevo gestor Rubén Cerda de la empresa TSOFT a partir del 14/04. 04/04/25 Se ha coordinado con el equipo de Construcción para que se vaya planificando los desarrollos asociados al Proyecto. Se observó el Anexo 1 remitido por el usuario, se espera que realicen los ajustes a las precisiones indicadas en dicho documento. 07/02/2025: Se creó trámite y se registró en la Demanda Priorizada. | AV73: ='Portafolio P&D'!B8 -> 0
A74: 70 | E74: Proyecto-Hijo | F74: Proyecto 70 | G74: Proyecto EDDO – Fase II: DashBoard (según determinado perfil), Consultas, Reportes con Gráficos, Notificaciones y publicación de resultados en POEM | H74: G2 | AM74: =IF(DemandaEstrateg_[[#This Row],[Tipo de Requerimiento]]="Proyecto",(DemandaEstrateg_[[#This Row],[% Avance ejecutado]]-DemandaEstrateg_[[#This Row],[% Avance Planificado]])/DemandaEstrateg_[[#This Row],[% Avance Planificado]],"No aplica") -> No aplica | AN74: =IF(DemandaEstrateg_[[#This Row],[Tipo de Requerimiento]]="Proyecto",(DemandaEstrateg_[[#This Row],[% Avance ejecutado]]-DemandaEstrateg_[[#This Row],[% Avance Planificado]])/DemandaEstrateg_[[#This Row],[% Avance Planificado]],"No aplica") -> No aplica | AP74: 46555 | AQ74: 2027-II | AR74: Pendiente | AS74: 01. Registrado | AT74: =VLOOKUP(DemandaEstrateg_[[#This Row],[Estado TI]],#REF!,3,FALSE) -> #REF! | AU74: 17/09/25: Se registró en el Backlog y se creó trámite. Proyecto hijo de ID 3025. | AV74: No Aplica
A75: 71 | E75: Proyecto-Hijo | F75: Proyecto 71 | G75: Desarrollo de APIs para el Quiosco Multimedio | H75: G2 | AH75: 45629 | AI75: 46070 | AK75: 1 | AL75: 0.76 | AM75: =IF(DemandaEstrateg_[[#This Row],[Tipo de Requerimiento]]="Proyecto",(DemandaEstrateg_[[#This Row],[% Avance ejecutado]]-DemandaEstrateg_[[#This Row],[% Avance Planificado]])/DemandaEstrateg_[[#This Row],[% Avance Planificado]],"No aplica") -> No aplica | AN75: =IF(DemandaEstrateg_[[#This Row],[Tipo de Requerimiento]]="Proyecto",(DemandaEstrateg_[[#This Row],[% Avance ejecutado]]-DemandaEstrateg_[[#This Row],[% Avance Planificado]])/DemandaEstrateg_[[#This Row],[% Avance Planificado]],"No aplica") -> No aplica | AP75: 46062 | AQ75: 2026-I | AR75: Asignado | AS75: =VLOOKUP(DemandaEstrateg_[[#This Row],[Últ. Estado CQ 30.04]],#REF!,3,FALSE) -> #REF! | AT75: =VLOOKUP(DemandaEstrateg_[[#This Row],[Estado TI]],#REF!,3,FALSE) -> #REF! | AU75: 04/07/2025: Se registró requerimiento en el Backlog. Requerimiento asociados al Proyecto Quiosco Multimedia | AV75: No Aplica
A76: 72 | E76: Proyecto-Hijo | F76: Proyecto 72 | G76: Pruebas de Modelos basados en reglas del entregable 10 – Proyecto Sentinel | H76: G2 | AM76: =IF(DemandaEstrateg_[[#This Row],[Tipo de Requerimiento]]="Proyecto",(DemandaEstrateg_[[#This Row],[% Avance ejecutado]]-DemandaEstrateg_[[#This Row],[% Avance Planificado]])/DemandaEstrateg_[[#This Row],[% Avance Planificado]],"No aplica") -> No aplica | AN76: =IF(DemandaEstrateg_[[#This Row],[Tipo de Requerimiento]]="Proyecto",(DemandaEstrateg_[[#This Row],[% Avance ejecutado]]-DemandaEstrateg_[[#This Row],[% Avance Planificado]])/DemandaEstrateg_[[#This Row],[% Avance Planificado]],"No aplica") -> No aplica | AP76: No Aplica | AQ76: No Aplica | AR76: Pendiente | AS76: 10. Descartado | AT76: =VLOOKUP(DemandaEstrateg_[[#This Row],[Estado TI]],#REF!,3,FALSE) -> #REF! | AU76: 10/11/25: Se registró en Backlog. 10/11/25: Se creo Tramite Proyecto Hijo de ID 1753 | AV76: ='Portafolio P&D'!B144 -> 0
